Workbook

Sheet 【表示用】各メンバーCH
B2: ◆各メンバーCH（成立＋確度A）
D3: 9月 | E3: 10月 | F3: 11月 | G3: 12月 | H3: 1月 | I3: 2月 | J3: 3月 | K3: 4月 | L3: 5月 | M3: 6月 | N3: 7月 | O3: 8月
B4: 波多野 | C4: ①目標 | D4: 0.3 | E4: 0.3 | F4: 0.3 | G4: 0.3 | H4: 0.3 | I4: 0.3 | J4: 0.3 | K4: 0.3 | L4: 0.3 | M4: 0.3 | N4: 0.3 | O4: 0.3
C5: ②見積 | D5: =SUMIFS('【入力用③】案件ごとCH（D案件以上）'!O$5:O$1048576,'【入力用③】案件ごとCH（D案件以上）'!$N$5:$N$1048576,【表示用】各メンバーCH!$B4,'【入力用③】案件ごとCH（D案件以上）'!$H$5:$H$1048576,"成立")+SUMIFS('【入力用③】案件ごとCH（D案件以上）'!O$5:O$1048576,'【入力用③】案件ごとCH（D案件以上）'!$N$5:$N$1048576,【表示用】各メンバーCH!$B4,'【入力用③】案件ごとCH（D案件以上）'!$H$5:$H$1048576,"A") -> 0.28 | E5: =SUMIFS('【入力用③】案件ごとCH（D案件以上）'!P$5:P$1048576,'【入力用③】案件ごとCH（D案件以上）'!$N$5:$N$1048576,【表示用】各メンバーCH!$B4,'【入力用③】案件ごとCH（D案件以上）'!$H$5:$H$1048576,"成立")+SUMIFS('【入力用③】案件ごとCH（D案件以上）'!P$5:P$1048576,'【入力用③】案件ごとCH（D案件以上）'!$N$5:$N$1048576,【表示用】各メンバーCH!$B4,'【入力用③】案件ごとCH（D案件以上）'!$H$5:$H$1048576,"A") -> 0.33 | F5: =SUMIFS('【入力用③】案件ごとCH（D案件以上）'!Q$5:Q$1048576,'【入力用③】案件ごとCH（D案件以上）'!$N$5:$N$1048576,【表示用】各メンバーCH!$B4,'【入力用③】案件ごとCH（D案件以上）'!$H$5:$H$1048576,"成立")+SUMIFS('【入力用③】案件ごとCH（D案件以上）'!Q$5:Q$1048576,'【入力用③】案件ごとCH（D案件以上）'!$N$5:$N$1048576,【表示用】各メンバーCH!$B4,'【入力用③】案件ごとCH（D案件以上）'!$H$5:$H$1048576,"A") -> 0.31 | G5: =SUMIFS('【入力用③】案件ごとCH（D案件以上）'!R$5:R$1048576,'【入力用③】案件ごとCH（D案件以上）'!$N$5:$N$1048576,【表示用】各メンバーCH!$B4,'【入力用③】案件ごとCH（D案件以上）'!$H$5:$H$1048576,"成立")+SUMIFS('【入力用③】案件ごとCH（D案件以上）'!R$5:R$1048576,'【入力用③】案件ごとCH（D案件以上）'!$N$5:$N$1048576,【表示用】各メンバーCH!$B4,'【入力用③】案件ごとCH（D案件以上）'!$H$5:$H$1048576,"A") -> 0.31 | H5: =SUMIFS('【入力用③】案件ごとCH（D案件以上）'!S$5:S$1048576,'【入力用③】案件ごとCH（D案件以上）'!$N$5:$N$1048576,【表示用】各メンバーCH!$B4,'【入力用③】案件ごとCH（D案件以上）'!$H$5:$H$1048576,"成立")+SUMIFS('【入力用③】案件ごとCH（D案件以上）'!S$5:S$1048576,'【入力用③】案件ごとCH（D案件以上）'!$N$5:$N$1048576,【表示用】各メンバーCH!$B4,'【入力用③】案件ごとCH（D案件以上）'!$H$5:$H$1048576,"A") -> 0.19 | I5: =SUMIFS('【入力用③】案件ごとCH（D案件以上）'!T$5:T$1048576,'【入力用③】案件ごとCH（D案件以上）'!$N$5:$N$1048576,【表示用】各メンバーCH!$B4,'【入力用③】案件ごとCH（D案件以上）'!$H$5:$H$1048576,"成立")+SUMIFS('【入力用③】案件ごとCH（D案件以上）'!T$5:T$1048576,'【入力用③】案件ごとCH（D案件以上）'!$N$5:$N$1048576,【表示用】各メンバーCH!$B4,'【入力用③】案件ごとCH（D案件以上）'!$H$5:$H$1048576,"A") -> 0.2 | J5: =SUMIFS('【入力用③】案件ごとCH（D案件以上）'!U$5:U$1048576,'【入力用③】案件ごとCH（D案件以上）'!$N$5:$N$1048576,【表示用】各メンバーCH!$B4,'【入力用③】案件ごとCH（D案件以上）'!$H$5:$H$1048576,"成立")+SUMIFS('【入力用③】案件ごとCH（D案件以上）'!U$5:U$1048576,'【入力用③】案件ごとCH（D案件以上）'!$N$5:$N$1048576,【表示用】各メンバーCH!$B4,'【入力用③】案件ごとCH（D案件以上）'!$H$5:$H$1048576,"A") -> 0.2 | K5: =SUMIFS('【入力用③】案件ごとCH（D案件以上）'!V$5:V$1048576,'【入力用③】案件ごとCH（D案件以上）'!$N$5:$N$1048576,【表示用】各メンバーCH!$B4,'【入力用③】案件ごとCH（D案件以上）'!$H$5:$H$1048576,"成立")+SUMIFS('【入力用③】案件ごとCH（D案件以上）'!V$5:V$1048576,'【入力用③】案件ごとCH（D案件以上）'!$N$5:$N$1048576,【表示用】各メンバーCH!$B4,'【入力用③】案件ごとCH（D案件以上）'!$H$5:$H$1048576,"A") -> 0.2 | ... O5: =SUMIFS('【入力用③】案件ごとCH（D案件以上）'!Z$5:Z$1048576,'【入力用③】案件ごとCH（D案件以上）'!$N$5:$N$1048576,【表示用】各メンバーCH!$B4,'【入力用③】案件ごとCH（D案件以上）'!$H$5:$H$1048576,"成立")+SUMIFS('【入力用③】案件ごとCH（D案件以上）'!Z$5:Z$1048576,'【入力用③】案件ごとCH（D案件以上）'!$N$5:$N$1048576,【表示用】各メンバーCH!$B4,'【入力用③】案件ごとCH（D案件以上）'!$H$5:$H$1048576,"A") -> 0
C6: ③GAP（②-①） | D6: =D5-D4 -> -0.02 | E6: =E5-E4 -> 0.03 | F6: =F5-F4 -> 0.01 | G6: =G5-G4 -> 0.01 | H6: =H5-H4 -> -0.11 | I6: =I5-I4 -> -0.1 | J6: =J5-J4 -> -0.1 | K6: =K5-K4 -> -0.1 | ... O6: =O5-O4 -> -0.3
B7: 小川 | C7: ①目標 | D7: 0.5 | E7: 0.5 | F7: 0.5 | G7: 0.5 | H7: 0.5 | I7: 0.5 | J7: 0.5 | K7: 0.5 | L7: 0.5 | M7: 0.5 | N7: 0.5 | O7: 0.5
C8: ②見積 | D8: =SUMIFS('【入力用③】案件ごとCH（D案件以上）'!O$5:O$1048576,'【入力用③】案件ごとCH（D案件以上）'!$N$5:$N$1048576,【表示用】各メンバーCH!$B7,'【入力用③】案件ごとCH（D案件以上）'!$H$5:$H$1048576,"成立")+SUMIFS('【入力用③】案件ごとCH（D案件以上）'!O$5:O$1048576,'【入力用③】案件ごとCH（D案件以上）'!$N$5:$N$1048576,【表示用】各メンバーCH!$B7,'【入力用③】案件ごとCH（D案件以上）'!$H$5:$H$1048576,"A") -> 0.209 | E8: =SUMIFS('【入力用③】案件ごとCH（D案件以上）'!P$5:P$1048576,'【入力用③】案件ごとCH（D案件以上）'!$N$5:$N$1048576,【表示用】各メンバーCH!$B7,'【入力用③】案件ごとCH（D案件以上）'!$H$5:$H$1048576,"成立")+SUMIFS('【入力用③】案件ごとCH（D案件以上）'!P$5:P$1048576,'【入力用③】案件ごとCH（D案件以上）'!$N$5:$N$1048576,【表示用】各メンバーCH!$B7,'【入力用③】案件ごとCH（D案件以上）'!$H$5:$H$1048576,"A") -> 0.14 | F8: =SUMIFS('【入力用③】案件ごとCH（D案件以上）'!Q$5:Q$1048576,'【入力用③】案件ごとCH（D案件以上）'!$N$5:$N$1048576,【表示用】各メンバーCH!$B7,'【入力用③】案件ごとCH（D案件以上）'!$H$5:$H$1048576,"成立")+SUMIFS('【入力用③】案件ごとCH（D案件以上）'!Q$5:Q$1048576,'【入力用③】案件ごとCH（D案件以上）'!$N$5:$N$1048576,【表示用】各メンバーCH!$B7,'【入力用③】案件ごとCH（D案件以上）'!$H$5:$H$1048576,"A") -> 0.14 | G8: =SUMIFS('【入力用③】案件ごとCH（D案件以上）'!R$5:R$1048576,'【入力用③】案件ごとCH（D案件以上）'!$N$5:$N$1048576,【表示用】各メンバーCH!$B7,'【入力用③】案件ごとCH（D案件以上）'!$H$5:$H$1048576,"成立")+SUMIFS('【入力用③】案件ごとCH（D案件以上）'!R$5:R$1048576,'【入力用③】案件ごとCH（D案件以上）'!$N$5:$N$1048576,【表示用】各メンバーCH!$B7,'【入力用③】案件ごとCH（D案件以上）'!$H$5:$H$1048576,"A") -> 0.14 | H8: =SUMIFS('【入力用③】案件ごとCH（D案件以上）'!S$5:S$1048576,'【入力用③】案件ごとCH（D案件以上）'!$N$5:$N$1048576,【表示用】各メンバーCH!$B7,'【入力用③】案件ごとCH（D案件以上）'!$H$5:$H$1048576,"成立")+SUMIFS('【入力用③】案件ごとCH（D案件以上）'!S$5:S$1048576,'【入力用③】案件ごとCH（D案件以上）'!$N$5:$N$1048576,【表示用】各メンバーCH!$B7,'【入力用③】案件ごとCH（D案件以上）'!$H$5:$H$1048576,"A") -> 0.13 | I8: =SUMIFS('【入力用③】案件ごとCH（D案件以上）'!T$5:T$1048576,'【入力用③】案件ごとCH（D案件以上）'!$N$5:$N$1048576,【表示用】各メンバーCH!$B7,'【入力用③】案件ごとCH（D案件以上）'!$H$5:$H$1048576,"成立")+SUMIFS('【入力用③】案件ごとCH（D案件以上）'!T$5:T$1048576,'【入力用③】案件ごとCH（D案件以上）'!$N$5:$N$1048576,【表示用】各メンバーCH!$B7,'【入力用③】案件ごとCH（D案件以上）'!$H$5:$H$1048576,"A") -> 0.21 | J8: =SUMIFS('【入力用③】案件ごとCH（D案件以上）'!U$5:U$1048576,'【入力用③】案件ごとCH（D案件以上）'!$N$5:$N$1048576,【表示用】各メンバーCH!$B7,'【入力用③】案件ごとCH（D案件以上）'!$H$5:$H$1048576,"成立")+SUMIFS('【入力用③】案件ごとCH（D案件以上）'!U$5:U$1048576,'【入力用③】案件ごとCH（D案件以上）'!$N$5:$N$1048576,【表示用】各メンバーCH!$B7,'【入力用③】案件ごとCH（D案件以上）'!$H$5:$H$1048576,"A") -> 0.08 | K8: =SUMIFS('【入力用③】案件ごとCH（D案件以上）'!V$5:V$1048576,'【入力用③】案件ごとCH（D案件以上）'!$N$5:$N$1048576,【表示用】各メンバーCH!$B7,'【入力用③】案件ごとCH（D案件以上）'!$H$5:$H$1048576,"成立")+SUMIFS('【入力用③】案件ごとCH（D案件以上）'!V$5:V$1048576,'【入力用③】案件ごとCH（D案件以上）'!$N$5:$N$1048576,【表示用】各メンバーCH!$B7,'【入力用③】案件ごとCH（D案件以上）'!$H$5:$H$1048576,"A") -> 0 | ... O8: =SUMIFS('【入力用③】案件ごとCH（D案件以上）'!Z$5:Z$1048576,'【入力用③】案件ごとCH（D案件以上）'!$N$5:$N$1048576,【表示用】各メンバーCH!$B7,'【入力用③】案件ごとCH（D案件以上）'!$H$5:$H$1048576,"成立")+SUMIFS('【入力用③】案件ごとCH（D案件以上）'!Z$5:Z$1048576,'【入力用③】案件ごとCH（D案件以上）'!$N$5:$N$1048576,【表示用】各メンバーCH!$B7,'【入力用③】案件ごとCH（D案件以上）'!$H$5:$H$1048576,"A") -> 0
C9: ③GAP（②-①） | D9: =D8-D7 -> -0.291 | E9: =E8-E7 -> -0.36 | F9: =F8-F7 -> -0.36 | G9: =G8-G7 -> -0.36 | H9: =H8-H7 -> -0.37 | I9: =I8-I7 -> -0.29 | J9: =J8-J7 -> -0.42 | K9: =K8-K7 -> -0.5 | ... O9: =O8-O7 -> -0.5
B10: 啓亮 | C10: ①目標 | D10: 0.8 | E10: 0.8 | F10: 0.8 | G10: 0.8 | H10: 0.8 | I10: 0.8 | J10: 0.8 | K10: 0.8 | L10: 0.8 | M10: 0.8 | N10: 0.8 | O10: 0.8
C11: ②見積 | D11: =SUMIFS('【入力用③】案件ごとCH（D案件以上）'!O$5:O$1048576,'【入力用③】案件ごとCH（D案件以上）'!$N$5:$N$1048576,【表示用】各メンバーCH!$B10,'【入力用③】案件ごとCH（D案件以上）'!$H$5:$H$1048576,"成立")+SUMIFS('【入力用③】案件ごとCH（D案件以上）'!O$5:O$1048576,'【入力用③】案件ごとCH（D案件以上）'!$N$5:$N$1048576,【表示用】各メンバーCH!$B10,'【入力用③】案件ごとCH（D案件以上）'!$H$5:$H$1048576,"A") -> 0.5246 | E11: =SUMIFS('【入力用③】案件ごとCH（D案件以上）'!P$5:P$1048576,'【入力用③】案件ごとCH（D案件以上）'!$N$5:$N$1048576,【表示用】各メンバーCH!$B10,'【入力用③】案件ごとCH（D案件以上）'!$H$5:$H$1048576,"成立")+SUMIFS('【入力用③】案件ごとCH（D案件以上）'!P$5:P$1048576,'【入力用③】案件ごとCH（D案件以上）'!$N$5:$N$1048576,【表示用】各メンバーCH!$B10,'【入力用③】案件ごとCH（D案件以上）'!$H$5:$H$1048576,"A") -> 0.444 | F11: =SUMIFS('【入力用③】案件ごとCH（D案件以上）'!Q$5:Q$1048576,'【入力用③】案件ごとCH（D案件以上）'!$N$5:$N$1048576,【表示用】各メンバーCH!$B10,'【入力用③】案件ごとCH（D案件以上）'!$H$5:$H$1048576,"成立")+SUMIFS('【入力用③】案件ごとCH（D案件以上）'!Q$5:Q$1048576,'【入力用③】案件ごとCH（D案件以上）'!$N$5:$N$1048576,【表示用】各メンバーCH!$B10,'【入力用③】案件ごとCH（D案件以上）'!$H$5:$H$1048576,"A") -> 0.784 | G11: =SUMIFS('【入力用③】案件ごとCH（D案件以上）'!R$5:R$1048576,'【入力用③】案件ごとCH（D案件以上）'!$N$5:$N$1048576,【表示用】各メンバーCH!$B10,'【入力用③】案件ごとCH（D案件以上）'!$H$5:$H$1048576,"成立")+SUMIFS('【入力用③】案件ごとCH（D案件以上）'!R$5:R$1048576,'【入力用③】案件ごとCH（D案件以上）'!$N$5:$N$1048576,【表示用】各メンバーCH!$B10,'【入力用③】案件ごとCH（D案件以上）'!$H$5:$H$1048576,"A") -> 0.51 | H11: =SUMIFS('【入力用③】案件ごとCH（D案件以上）'!S$5:S$1048576,'【入力用③】案件ごとCH（D案件以上）'!$N$5:$N$1048576,【表示用】各メンバーCH!$B10,'【入力用③】案件ごとCH（D案件以上）'!$H$5:$H$1048576,"成立")+SUMIFS('【入力用③】案件ごとCH（D案件以上）'!S$5:S$1048576,'【入力用③】案件ごとCH（D案件以上）'!$N$5:$N$1048576,【表示用】各メンバーCH!$B10,'【入力用③】案件ごとCH（D案件以上）'!$H$5:$H$1048576,"A") -> 1.61 | I11: =SUMIFS('【入力用③】案件ごとCH（D案件以上）'!T$5:T$1048576,'【入力用③】案件ごとCH（D案件以上）'!$N$5:$N$1048576,【表示用】各メンバーCH!$B10,'【入力用③】案件ごとCH（D案件以上）'!$H$5:$H$1048576,"成立")+SUMIFS('【入力用③】案件ごとCH（D案件以上）'!T$5:T$1048576,'【入力用③】案件ごとCH（D案件以上）'!$N$5:$N$1048576,【表示用】各メンバーCH!$B10,'【入力用③】案件ごとCH（D案件以上）'!$H$5:$H$1048576,"A") -> 1.685 | J11: =SUMIFS('【入力用③】案件ごとCH（D案件以上）'!U$5:U$1048576,'【入力用③】案件ごとCH（D案件以上）'!$N$5:$N$1048576,【表示用】各メンバーCH!$B10,'【入力用③】案件ごとCH（D案件以上）'!$H$5:$H$1048576,"成立")+SUMIFS('【入力用③】案件ごとCH（D案件以上）'!U$5:U$1048576,'【入力用③】案件ごとCH（D案件以上）'!$N$5:$N$1048576,【表示用】各メンバーCH!$B10,'【入力用③】案件ごとCH（D案件以上）'!$H$5:$H$1048576,"A") -> 1.49 | K11: =SUMIFS('【入力用③】案件ごとCH（D案件以上）'!V$5:V$1048576,'【入力用③】案件ごとCH（D案件以上）'!$N$5:$N$1048576,【表示用】各メンバーCH!$B10,'【入力用③】案件ごとCH（D案件以上）'!$H$5:$H$1048576,"成立")+SUMIFS('【入力用③】案件ごとCH（D案件以上）'!V$5:V$1048576,'【入力用③】案件ごとCH（D案件以上）'!$N$5:$N$1048576,【表示用】各メンバーCH!$B10,'【入力用③】案件ごとCH（D案件以上）'!$H$5:$H$1048576,"A") -> 0.77 | ... O11: =SUMIFS('【入力用③】案件ごとCH（D案件以上）'!Z$5:Z$1048576,'【入力用③】案件ごとCH（D案件以上）'!$N$5:$N$1048576,【表示用】各メンバーCH!$B10,'【入力用③】案件ごとCH（D案件以上）'!$H$5:$H$1048576,"成立")+SUMIFS('【入力用③】案件ごとCH（D案件以上）'!Z$5:Z$1048576,'【入力用③】案件ごとCH（D案件以上）'!$N$5:$N$1048576,【表示用】各メンバーCH!$B10,'【入力用③】案件ごとCH（D案件以上）'!$H$5:$H$1048576,"A") -> 0.27
C12: ③GAP（②-①） | D12: =D11-D10 -> -0.2754 | E12: =E11-E10 -> -0.356 | F12: =F11-F10 -> -0.016 | G12: =G11-G10 -> -0.29 | H12: =H11-H10 -> 0.81 | I12: =I11-I10 -> 0.885 | J12: =J11-J10 -> 0.69 | K12: =K11-K10 -> -0.03 | ... O12: =O11-O10 -> -0.53
B13: 友祐 | C13: ①目標 | D13: 0.9 | E13: 0.9 | F13: 0.9 | G13: 0.9 | H13: 0.9 | I13: 0.9 | J13: 0.9 | K13: 0.9 | L13: 0.9 | M13: 0.9 | N13: 0.9 | O13: 0.9
C14: ②見積 | D14: =SUMIFS('【入力用③】案件ごとCH（D案件以上）'!O$5:O$1048576,'【入力用③】案件ごとCH（D案件以上）'!$N$5:$N$1048576,【表示用】各メンバーCH!$B13,'【入力用③】案件ごとCH（D案件以上）'!$H$5:$H$1048576,"成立")+SUMIFS('【入力用③】案件ごとCH（D案件以上）'!O$5:O$1048576,'【入力用③】案件ごとCH（D案件以上）'!$N$5:$N$1048576,【表示用】各メンバーCH!$B13,'【入力用③】案件ごとCH（D案件以上）'!$H$5:$H$1048576,"A") -> 1.97 | E14: =SUMIFS('【入力用③】案件ごとCH（D案件以上）'!P$5:P$1048576,'【入力用③】案件ごとCH（D案件以上）'!$N$5:$N$1048576,【表示用】各メンバーCH!$B13,'【入力用③】案件ごとCH（D案件以上）'!$H$5:$H$1048576,"成立")+SUMIFS('【入力用③】案件ごとCH（D案件以上）'!P$5:P$1048576,'【入力用③】案件ごとCH（D案件以上）'!$N$5:$N$1048576,【表示用】各メンバーCH!$B13,'【入力用③】案件ごとCH（D案件以上）'!$H$5:$H$1048576,"A") -> 2.205 | F14: =SUMIFS('【入力用③】案件ごとCH（D案件以上）'!Q$5:Q$1048576,'【入力用③】案件ごとCH（D案件以上）'!$N$5:$N$1048576,【表示用】各メンバーCH!$B13,'【入力用③】案件ごとCH（D案件以上）'!$H$5:$H$1048576,"成立")+SUMIFS('【入力用③】案件ごとCH（D案件以上）'!Q$5:Q$1048576,'【入力用③】案件ごとCH（D案件以上）'!$N$5:$N$1048576,【表示用】各メンバーCH!$B13,'【入力用③】案件ごとCH（D案件以上）'!$H$5:$H$1048576,"A") -> 2.202 | G14: =SUMIFS('【入力用③】案件ごとCH（D案件以上）'!R$5:R$1048576,'【入力用③】案件ごとCH（D案件以上）'!$N$5:$N$1048576,【表示用】各メンバーCH!$B13,'【入力用③】案件ごとCH（D案件以上）'!$H$5:$H$1048576,"成立")+SUMIFS('【入力用③】案件ごとCH（D案件以上）'!R$5:R$1048576,'【入力用③】案件ごとCH（D案件以上）'!$N$5:$N$1048576,【表示用】各メンバーCH!$B13,'【入力用③】案件ごとCH（D案件以上）'!$H$5:$H$1048576,"A") -> 0.9 | H14: =SUMIFS('【入力用③】案件ごとCH（D案件以上）'!S$5:S$1048576,'【入力用③】案件ごとCH（D案件以上）'!$N$5:$N$1048576,【表示用】各メンバーCH!$B13,'【入力用③】案件ごとCH（D案件以上）'!$H$5:$H$1048576,"成立")+SUMIFS('【入力用③】案件ごとCH（D案件以上）'!S$5:S$1048576,'【入力用③】案件ごとCH（D案件以上）'!$N$5:$N$1048576,【表示用】各メンバーCH!$B13,'【入力用③】案件ごとCH（D案件以上）'!$H$5:$H$1048576,"A") -> 1.46 | I14: =SUMIFS('【入力用③】案件ごとCH（D案件以上）'!T$5:T$1048576,'【入力用③】案件ごとCH（D案件以上）'!$N$5:$N$1048576,【表示用】各メンバーCH!$B13,'【入力用③】案件ごとCH（D案件以上）'!$H$5:$H$1048576,"成立")+SUMIFS('【入力用③】案件ごとCH（D案件以上）'!T$5:T$1048576,'【入力用③】案件ごとCH（D案件以上）'!$N$5:$N$1048576,【表示用】各メンバーCH!$B13,'【入力用③】案件ごとCH（D案件以上）'!$H$5:$H$1048576,"A") -> 1.27 | J14: =SUMIFS('【入力用③】案件ごとCH（D案件以上）'!U$5:U$1048576,'【入力用③】案件ごとCH（D案件以上）'!$N$5:$N$1048576,【表示用】各メンバーCH!$B13,'【入力用③】案件ごとCH（D案件以上）'!$H$5:$H$1048576,"成立")+SUMIFS('【入力用③】案件ごとCH（D案件以上）'!U$5:U$1048576,'【入力用③】案件ごとCH（D案件以上）'!$N$5:$N$1048576,【表示用】各メンバーCH!$B13,'【入力用③】案件ごとCH（D案件以上）'!$H$5:$H$1048576,"A") -> 0.635 | K14: =SUMIFS('【入力用③】案件ごとCH（D案件以上）'!V$5:V$1048576,'【入力用③】案件ごとCH（D案件以上）'!$N$5:$N$1048576,【表示用】各メンバーCH!$B13,'【入力用③】案件ごとCH（D案件以上）'!$H$5:$H$1048576,"成立")+SUMIFS('【入力用③】案件ごとCH（D案件以上）'!V$5:V$1048576,'【入力用③】案件ごとCH（D案件以上）'!$N$5:$N$1048576,【表示用】各メンバーCH!$B13,'【入力用③】案件ごとCH（D案件以上）'!$H$5:$H$1048576,"A") -> 0.045 | ... O14: =SUMIFS('【入力用③】案件ごとCH（D案件以上）'!Z$5:Z$1048576,'【入力用③】案件ごとCH（D案件以上）'!$N$5:$N$1048576,【表示用】各メンバーCH!$B13,'【入力用③】案件ごとCH（D案件以上）'!$H$5:$H$1048576,"成立")+SUMIFS('【入力用③】案件ごとCH（D案件以上）'!Z$5:Z$1048576,'【入力用③】案件ごとCH（D案件以上）'!$N$5:$N$1048576,【表示用】各メンバーCH!$B13,'【入力用③】案件ごとCH（D案件以上）'!$H$5:$H$1048576,"A") -> 0
C15: ③GAP（②-①） | D15: =D14-D13 -> 1.07 | E15: =E14-E13 -> 1.305 | F15: =F14-F13 -> 1.302 | G15: =G14-G13 -> 0 | H15: =H14-H13 -> 0.56 | I15: =I14-I13 -> 0.37 | J15: =J14-J13 -> -0.265 | K15: =K14-K13 -> -0.855 | ... O15: =O14-O13 -> -0.9
B16: 芹澤 | C16: ①目標 | D16: 0.9 | E16: 0.9 | F16: 0.9 | G16: 0.9 | H16: 0.9 | I16: 0.9 | J16: 0.9 | K16: 0.9 | L16: 0.9 | M16: 0.9 | N16: 0.9 | O16: 0.9
C17: ②見積 | D17: =SUMIFS('【入力用③】案件ごとCH（D案件以上）'!O$5:O$1048576,'【入力用③】案件ごとCH（D案件以上）'!$N$5:$N$1048576,【表示用】各メンバーCH!$B16,'【入力用③】案件ごとCH（D案件以上）'!$H$5:$H$1048576,"成立")+SUMIFS('【入力用③】案件ごとCH（D案件以上）'!O$5:O$1048576,'【入力用③】案件ごとCH（D案件以上）'!$N$5:$N$1048576,【表示用】各メンバーCH!$B16,'【入力用③】案件ごとCH（D案件以上）'!$H$5:$H$1048576,"A") -> 0.98 | E17: =SUMIFS('【入力用③】案件ごとCH（D案件以上）'!P$5:P$1048576,'【入力用③】案件ごとCH（D案件以上）'!$N$5:$N$1048576,【表示用】各メンバーCH!$B16,'【入力用③】案件ごとCH（D案件以上）'!$H$5:$H$1048576,"成立")+SUMIFS('【入力用③】案件ごとCH（D案件以上）'!P$5:P$1048576,'【入力用③】案件ごとCH（D案件以上）'!$N$5:$N$1048576,【表示用】各メンバーCH!$B16,'【入力用③】案件ごとCH（D案件以上）'!$H$5:$H$1048576,"A") -> 1.25 | F17: =SUMIFS('【入力用③】案件ごとCH（D案件以上）'!Q$5:Q$1048576,'【入力用③】案件ごとCH（D案件以上）'!$N$5:$N$1048576,【表示用】各メンバーCH!$B16,'【入力用③】案件ごとCH（D案件以上）'!$H$5:$H$1048576,"成立")+SUMIFS('【入力用③】案件ごとCH（D案件以上）'!Q$5:Q$1048576,'【入力用③】案件ごとCH（D案件以上）'!$N$5:$N$1048576,【表示用】各メンバーCH!$B16,'【入力用③】案件ごとCH（D案件以上）'!$H$5:$H$1048576,"A") -> 0.9 | G17: =SUMIFS('【入力用③】案件ごとCH（D案件以上）'!R$5:R$1048576,'【入力用③】案件ごとCH（D案件以上）'!$N$5:$N$1048576,【表示用】各メンバーCH!$B16,'【入力用③】案件ごとCH（D案件以上）'!$H$5:$H$1048576,"成立")+SUMIFS('【入力用③】案件ごとCH（D案件以上）'!R$5:R$1048576,'【入力用③】案件ごとCH（D案件以上）'!$N$5:$N$1048576,【表示用】各メンバーCH!$B16,'【入力用③】案件ごとCH（D案件以上）'!$H$5:$H$1048576,"A") -> 1.183 | H17: =SUMIFS('【入力用③】案件ごとCH（D案件以上）'!S$5:S$1048576,'【入力用③】案件ごとCH（D案件以上）'!$N$5:$N$1048576,【表示用】各メンバーCH!$B16,'【入力用③】案件ごとCH（D案件以上）'!$H$5:$H$1048576,"成立")+SUMIFS('【入力用③】案件ごとCH（D案件以上）'!S$5:S$1048576,'【入力用③】案件ごとCH（D案件以上）'!$N$5:$N$1048576,【表示用】各メンバーCH!$B16,'【入力用③】案件ごとCH（D案件以上）'!$H$5:$H$1048576,"A") -> 0.4 | I17: =SUMIFS('【入力用③】案件ごとCH（D案件以上）'!T$5:T$1048576,'【入力用③】案件ごとCH（D案件以上）'!$N$5:$N$1048576,【表示用】各メンバーCH!$B16,'【入力用③】案件ごとCH（D案件以上）'!$H$5:$H$1048576,"成立")+SUMIFS('【入力用③】案件ごとCH（D案件以上）'!T$5:T$1048576,'【入力用③】案件ごとCH（D案件以上）'!$N$5:$N$1048576,【表示用】各メンバーCH!$B16,'【入力用③】案件ごとCH（D案件以上）'!$H$5:$H$1048576,"A") -> 0.55 | J17: =SUMIFS('【入力用③】案件ごとCH（D案件以上）'!U$5:U$1048576,'【入力用③】案件ごとCH（D案件以上）'!$N$5:$N$1048576,【表示用】各メンバーCH!$B16,'【入力用③】案件ごとCH（D案件以上）'!$H$5:$H$1048576,"成立")+SUMIFS('【入力用③】案件ごとCH（D案件以上）'!U$5:U$1048576,'【入力用③】案件ごとCH（D案件以上）'!$N$5:$N$1048576,【表示用】各メンバーCH!$B16,'【入力用③】案件ごとCH（D案件以上）'!$H$5:$H$1048576,"A") -> 0.1 | K17: =SUMIFS('【入力用③】案件ごとCH（D案件以上）'!V$5:V$1048576,'【入力用③】案件ごとCH（D案件以上）'!$N$5:$N$1048576,【表示用】各メンバーCH!$B16,'【入力用③】案件ごとCH（D案件以上）'!$H$5:$H$1048576,"成立")+SUMIFS('【入力用③】案件ごとCH（D案件以上）'!V$5:V$1048576,'【入力用③】案件ごとCH（D案件以上）'!$N$5:$N$1048576,【表示用】各メンバーCH!$B16,'【入力用③】案件ごとCH（D案件以上）'!$H$5:$H$1048576,"A") -> 0 | ... O17: =SUMIFS('【入力用③】案件ごとCH（D案件以上）'!Z$5:Z$1048576,'【入力用③】案件ごとCH（D案件以上）'!$N$5:$N$1048576,【表示用】各メンバーCH!$B16,'【入力用③】案件ごとCH（D案件以上）'!$H$5:$H$1048576,"成立")+SUMIFS('【入力用③】案件ごとCH（D案件以上）'!Z$5:Z$1048576,'【入力用③】案件ごとCH（D案件以上）'!$N$5:$N$1048576,【表示用】各メンバーCH!$B16,'【入力用③】案件ごとCH（D案件以上）'!$H$5:$H$1048576,"A") -> 0
C18: ③GAP（②-①） | D18: =D17-D16 -> 0.08 | E18: =E17-E16 -> 0.35 | F18: =F17-F16 -> 0 | G18: =G17-G16 -> 0.283 | H18: =H17-H16 -> -0.5 | I18: =I17-I16 -> -0.35 | J18: =J17-J16 -> -0.8 | K18: =K17-K16 -> -0.9 | ... O18: =O17-O16 -> -0.9
B19: 弓本 | C19: ①目標 | D19: 0.9 | E19: 0.9 | F19: 0.9 | G19: 0.9 | H19: 0.9 | I19: 0.9 | J19: 0.9 | K19: 0.9 | L19: 0.9 | M19: 0.9 | N19: 0.9 | O19: 0.9
C20: ②見積 | D20: =SUMIFS('【入力用③】案件ごとCH（D案件以上）'!O$5:O$1048576,'【入力用③】案件ごとCH（D案件以上）'!$N$5:$N$1048576,【表示用】各メンバーCH!$B19,'【入力用③】案件ごとCH（D案件以上）'!$H$5:$H$1048576,"成立")+SUMIFS('【入力用③】案件ごとCH（D案件以上）'!O$5:O$1048576,'【入力用③】案件ごとCH（D案件以上）'!$N$5:$N$1048576,【表示用】各メンバーCH!$B19,'【入力用③】案件ごとCH（D案件以上）'!$H$5:$H$1048576,"A") -> 0.75 | E20: =SUMIFS('【入力用③】案件ごとCH（D案件以上）'!P$5:P$1048576,'【入力用③】案件ごとCH（D案件以上）'!$N$5:$N$1048576,【表示用】各メンバーCH!$B19,'【入力用③】案件ごとCH（D案件以上）'!$H$5:$H$1048576,"成立")+SUMIFS('【入力用③】案件ごとCH（D案件以上）'!P$5:P$1048576,'【入力用③】案件ごとCH（D案件以上）'!$N$5:$N$1048576,【表示用】各メンバーCH!$B19,'【入力用③】案件ごとCH（D案件以上）'!$H$5:$H$1048576,"A") -> 0.55 | F20: =SUMIFS('【入力用③】案件ごとCH（D案件以上）'!Q$5:Q$1048576,'【入力用③】案件ごとCH（D案件以上）'!$N$5:$N$1048576,【表示用】各メンバーCH!$B19,'【入力用③】案件ごとCH（D案件以上）'!$H$5:$H$1048576,"成立")+SUMIFS('【入力用③】案件ごとCH（D案件以上）'!Q$5:Q$1048576,'【入力用③】案件ごとCH（D案件以上）'!$N$5:$N$1048576,【表示用】各メンバーCH!$B19,'【入力用③】案件ごとCH（D案件以上）'!$H$5:$H$1048576,"A") -> 1.1 | G20: =SUMIFS('【入力用③】案件ごとCH（D案件以上）'!R$5:R$1048576,'【入力用③】案件ごとCH（D案件以上）'!$N$5:$N$1048576,【表示用】各メンバーCH!$B19,'【入力用③】案件ごとCH（D案件以上）'!$H$5:$H$1048576,"成立")+SUMIFS('【入力用③】案件ごとCH（D案件以上）'!R$5:R$1048576,'【入力用③】案件ごとCH（D案件以上）'!$N$5:$N$1048576,【表示用】各メンバーCH!$B19,'【入力用③】案件ごとCH（D案件以上）'!$H$5:$H$1048576,"A") -> 0.85 | H20: =SUMIFS('【入力用③】案件ごとCH（D案件以上）'!S$5:S$1048576,'【入力用③】案件ごとCH（D案件以上）'!$N$5:$N$1048576,【表示用】各メンバーCH!$B19,'【入力用③】案件ごとCH（D案件以上）'!$H$5:$H$1048576,"成立")+SUMIFS('【入力用③】案件ごとCH（D案件以上）'!S$5:S$1048576,'【入力用③】案件ごとCH（D案件以上）'!$N$5:$N$1048576,【表示用】各メンバーCH!$B19,'【入力用③】案件ごとCH（D案件以上）'!$H$5:$H$1048576,"A") -> 0.85 | I20: =SUMIFS('【入力用③】案件ごとCH（D案件以上）'!T$5:T$1048576,'【入力用③】案件ごとCH（D案件以上）'!$N$5:$N$1048576,【表示用】各メンバーCH!$B19,'【入力用③】案件ごとCH（D案件以上）'!$H$5:$H$1048576,"成立")+SUMIFS('【入力用③】案件ごとCH（D案件以上）'!T$5:T$1048576,'【入力用③】案件ごとCH（D案件以上）'!$N$5:$N$1048576,【表示用】各メンバーCH!$B19,'【入力用③】案件ごとCH（D案件以上）'!$H$5:$H$1048576,"A") -> 0.3 | J20: =SUMIFS('【入力用③】案件ごとCH（D案件以上）'!U$5:U$1048576,'【入力用③】案件ごとCH（D案件以上）'!$N$5:$N$1048576,【表示用】各メンバーCH!$B19,'【入力用③】案件ごとCH（D案件以上）'!$H$5:$H$1048576,"成立")+SUMIFS('【入力用③】案件ごとCH（D案件以上）'!U$5:U$1048576,'【入力用③】案件ごとCH（D案件以上）'!$N$5:$N$1048576,【表示用】各メンバーCH!$B19,'【入力用③】案件ごとCH（D案件以上）'!$H$5:$H$1048576,"A") -> 0 | K20: =SUMIFS('【入力用③】案件ごとCH（D案件以上）'!V$5:V$1048576,'【入力用③】案件ごとCH（D案件以上）'!$N$5:$N$1048576,【表示用】各メンバーCH!$B19,'【入力用③】案件ごとCH（D案件以上）'!$H$5:$H$1048576,"成立")+SUMIFS('【入力用③】案件ごとCH（D案件以上）'!V$5:V$1048576,'【入力用③】案件ごとCH（D案件以上）'!$N$5:$N$1048576,【表示用】各メンバーCH!$B19,'【入力用③】案件ごとCH（D案件以上）'!$H$5:$H$1048576,"A") -> 0 | ... O20: =SUMIFS('【入力用③】案件ごとCH（D案件以上）'!Z$5:Z$1048576,'【入力用③】案件ごとCH（D案件以上）'!$N$5:$N$1048576,【表示用】各メンバーCH!$B19,'【入力用③】案件ごとCH（D案件以上）'!$H$5:$H$1048576,"成立")+SUMIFS('【入力用③】案件ごとCH（D案件以上）'!Z$5:Z$1048576,'【入力用③】案件ごとCH（D案件以上）'!$N$5:$N$1048576,【表示用】各メンバーCH!$B19,'【入力用③】案件ごとCH（D案件以上）'!$H$5:$H$1048576,"A") -> 0
C21: ③GAP（②-①） | D21: =D20-D19 -> -0.15 | E21: =E20-E19 -> -0.35 | F21: =F20-F19 -> 0.2 | G21: =G20-G19 -> -0.05 | H21: =H20-H19 -> -0.05 | I21: =I20-I19 -> -0.6 | J21: =J20-J19 -> -0.9 | K21: =K20-K19 -> -0.9 | ... O21: =O20-O19 -> -0.9
B22: 丸田 | C22: ①目標 | D22: 0.9 | E22: 0.9 | F22: 0.9 | G22: 0.9 | H22: 0.9 | I22: 0.9 | J22: 0.9 | K22: 0.9 | L22: 0.9 | M22: 0.9 | N22: 0.9 | O22: 0.9
C23: ②見積 | D23: =SUMIFS('【入力用③】案件ごとCH（D案件以上）'!O$5:O$1048576,'【入力用③】案件ごとCH（D案件以上）'!$N$5:$N$1048576,【表示用】各メンバーCH!$B22,'【入力用③】案件ごとCH（D案件以上）'!$H$5:$H$1048576,"成立")+SUMIFS('【入力用③】案件ごとCH（D案件以上）'!O$5:O$1048576,'【入力用③】案件ごとCH（D案件以上）'!$N$5:$N$1048576,【表示用】各メンバーCH!$B22,'【入力用③】案件ごとCH（D案件以上）'!$H$5:$H$1048576,"A") -> 1.1659 | E23: =SUMIFS('【入力用③】案件ごとCH（D案件以上）'!P$5:P$1048576,'【入力用③】案件ごとCH（D案件以上）'!$N$5:$N$1048576,【表示用】各メンバーCH!$B22,'【入力用③】案件ごとCH（D案件以上）'!$H$5:$H$1048576,"成立")+SUMIFS('【入力用③】案件ごとCH（D案件以上）'!P$5:P$1048576,'【入力用③】案件ごとCH（D案件以上）'!$N$5:$N$1048576,【表示用】各メンバーCH!$B22,'【入力用③】案件ごとCH（D案件以上）'!$H$5:$H$1048576,"A") -> 2.2 | F23: =SUMIFS('【入力用③】案件ごとCH（D案件以上）'!Q$5:Q$1048576,'【入力用③】案件ごとCH（D案件以上）'!$N$5:$N$1048576,【表示用】各メンバーCH!$B22,'【入力用③】案件ごとCH（D案件以上）'!$H$5:$H$1048576,"成立")+SUMIFS('【入力用③】案件ごとCH（D案件以上）'!Q$5:Q$1048576,'【入力用③】案件ごとCH（D案件以上）'!$N$5:$N$1048576,【表示用】各メンバーCH!$B22,'【入力用③】案件ごとCH（D案件以上）'!$H$5:$H$1048576,"A") -> 1.35 | G23: =SUMIFS('【入力用③】案件ごとCH（D案件以上）'!R$5:R$1048576,'【入力用③】案件ごとCH（D案件以上）'!$N$5:$N$1048576,【表示用】各メンバーCH!$B22,'【入力用③】案件ごとCH（D案件以上）'!$H$5:$H$1048576,"成立")+SUMIFS('【入力用③】案件ごとCH（D案件以上）'!R$5:R$1048576,'【入力用③】案件ごとCH（D案件以上）'!$N$5:$N$1048576,【表示用】各メンバーCH!$B22,'【入力用③】案件ごとCH（D案件以上）'!$H$5:$H$1048576,"A") -> 1.64 | H23: =SUMIFS('【入力用③】案件ごとCH（D案件以上）'!S$5:S$1048576,'【入力用③】案件ごとCH（D案件以上）'!$N$5:$N$1048576,【表示用】各メンバーCH!$B22,'【入力用③】案件ごとCH（D案件以上）'!$H$5:$H$1048576,"成立")+SUMIFS('【入力用③】案件ごとCH（D案件以上）'!S$5:S$1048576,'【入力用③】案件ごとCH（D案件以上）'!$N$5:$N$1048576,【表示用】各メンバーCH!$B22,'【入力用③】案件ごとCH（D案件以上）'!$H$5:$H$1048576,"A") -> 0.52 | I23: =SUMIFS('【入力用③】案件ごとCH（D案件以上）'!T$5:T$1048576,'【入力用③】案件ごとCH（D案件以上）'!$N$5:$N$1048576,【表示用】各メンバーCH!$B22,'【入力用③】案件ごとCH（D案件以上）'!$H$5:$H$1048576,"成立")+SUMIFS('【入力用③】案件ごとCH（D案件以上）'!T$5:T$1048576,'【入力用③】案件ごとCH（D案件以上）'!$N$5:$N$1048576,【表示用】各メンバーCH!$B22,'【入力用③】案件ごとCH（D案件以上）'!$H$5:$H$1048576,"A") -> 0.8 | J23: =SUMIFS('【入力用③】案件ごとCH（D案件以上）'!U$5:U$1048576,'【入力用③】案件ごとCH（D案件以上）'!$N$5:$N$1048576,【表示用】各メンバーCH!$B22,'【入力用③】案件ごとCH（D案件以上）'!$H$5:$H$1048576,"成立")+SUMIFS('【入力用③】案件ごとCH（D案件以上）'!U$5:U$1048576,'【入力用③】案件ごとCH（D案件以上）'!$N$5:$N$1048576,【表示用】各メンバーCH!$B22,'【入力用③】案件ごとCH（D案件以上）'!$H$5:$H$1048576,"A") -> 0.8 | K23: =SUMIFS('【入力用③】案件ごとCH（D案件以上）'!V$5:V$1048576,'【入力用③】案件ごとCH（D案件以上）'!$N$5:$N$1048576,【表示用】各メンバーCH!$B22,'【入力用③】案件ごとCH（D案件以上）'!$H$5:$H$1048576,"成立")+SUMIFS('【入力用③】案件ごとCH（D案件以上）'!V$5:V$1048576,'【入力用③】案件ごとCH（D案件以上）'!$N$5:$N$1048576,【表示用】各メンバーCH!$B22,'【入力用③】案件ごとCH（D案件以上）'!$H$5:$H$1048576,"A") -> 0.4 | ... O23: =SUMIFS('【入力用③】案件ごとCH（D案件以上）'!Z$5:Z$1048576,'【入力用③】案件ごとCH（D案件以上）'!$N$5:$N$1048576,【表示用】各メンバーCH!$B22,'【入力用③】案件ごとCH（D案件以上）'!$H$5:$H$1048576,"成立")+SUMIFS('【入力用③】案件ごとCH（D案件以上）'!Z$5:Z$1048576,'【入力用③】案件ごとCH（D案件以上）'!$N$5:$N$1048576,【表示用】各メンバーCH!$B22,'【入力用③】案件ごとCH（D案件以上）'!$H$5:$H$1048576,"A") -> 0
C24: ③GAP（②-①） | D24: =D23-D22 -> 0.2659 | E24: =E23-E22 -> 1.3 | F24: =F23-F22 -> 0.45 | G24: =G23-G22 -> 0.74 | H24: =H23-H22 -> -0.38 | I24: =I23-I22 -> -0.1 | J24: =J23-J22 -> -0.1 | K24: =K23-K22 -> -0.5 | ... O24: =O23-O22 -> -0.9
B25: 加藤 | C25: ①目標 | D25: 0.9 | E25: 0.9 | F25: 0.9 | G25: 0.9 | H25: 0.9 | I25: 0.9 | J25: 0.9 | K25: 0.9 | L25: 0.9 | M25: 0.9 | N25: 0.9 | O25: 0.9
C26: ②見積 | D26: =SUMIFS('【入力用③】案件ごとCH（D案件以上）'!O$5:O$1048576,'【入力用③】案件ごとCH（D案件以上）'!$N$5:$N$1048576,【表示用】各メンバーCH!$B25,'【入力用③】案件ごとCH（D案件以上）'!$H$5:$H$1048576,"成立")+SUMIFS('【入力用③】案件ごとCH（D案件以上）'!O$5:O$1048576,'【入力用③】案件ごとCH（D案件以上）'!$N$5:$N$1048576,【表示用】各メンバーCH!$B25,'【入力用③】案件ごとCH（D案件以上）'!$H$5:$H$1048576,"A") -> 0.75 | E26: =SUMIFS('【入力用③】案件ごとCH（D案件以上）'!P$5:P$1048576,'【入力用③】案件ごとCH（D案件以上）'!$N$5:$N$1048576,【表示用】各メンバーCH!$B25,'【入力用③】案件ごとCH（D案件以上）'!$H$5:$H$1048576,"成立")+SUMIFS('【入力用③】案件ごとCH（D案件以上）'!P$5:P$1048576,'【入力用③】案件ごとCH（D案件以上）'!$N$5:$N$1048576,【表示用】各メンバーCH!$B25,'【入力用③】案件ごとCH（D案件以上）'!$H$5:$H$1048576,"A") -> 0.97 | F26: =SUMIFS('【入力用③】案件ごとCH（D案件以上）'!Q$5:Q$1048576,'【入力用③】案件ごとCH（D案件以上）'!$N$5:$N$1048576,【表示用】各メンバーCH!$B25,'【入力用③】案件ごとCH（D案件以上）'!$H$5:$H$1048576,"成立")+SUMIFS('【入力用③】案件ごとCH（D案件以上）'!Q$5:Q$1048576,'【入力用③】案件ごとCH（D案件以上）'!$N$5:$N$1048576,【表示用】各メンバーCH!$B25,'【入力用③】案件ごとCH（D案件以上）'!$H$5:$H$1048576,"A") -> 0.69 | G26: =SUMIFS('【入力用③】案件ごとCH（D案件以上）'!R$5:R$1048576,'【入力用③】案件ごとCH（D案件以上）'!$N$5:$N$1048576,【表示用】各メンバーCH!$B25,'【入力用③】案件ごとCH（D案件以上）'!$H$5:$H$1048576,"成立")+SUMIFS('【入力用③】案件ごとCH（D案件以上）'!R$5:R$1048576,'【入力用③】案件ごとCH（D案件以上）'!$N$5:$N$1048576,【表示用】各メンバーCH!$B25,'【入力用③】案件ごとCH（D案件以上）'!$H$5:$H$1048576,"A") -> 0.75 | H26: =SUMIFS('【入力用③】案件ごとCH（D案件以上）'!S$5:S$1048576,'【入力用③】案件ごとCH（D案件以上）'!$N$5:$N$1048576,【表示用】各メンバーCH!$B25,'【入力用③】案件ごとCH（D案件以上）'!$H$5:$H$1048576,"成立")+SUMIFS('【入力用③】案件ごとCH（D案件以上）'!S$5:S$1048576,'【入力用③】案件ごとCH（D案件以上）'!$N$5:$N$1048576,【表示用】各メンバーCH!$B25,'【入力用③】案件ごとCH（D案件以上）'!$H$5:$H$1048576,"A") -> 0.12 | I26: =SUMIFS('【入力用③】案件ごとCH（D案件以上）'!T$5:T$1048576,'【入力用③】案件ごとCH（D案件以上）'!$N$5:$N$1048576,【表示用】各メンバーCH!$B25,'【入力用③】案件ごとCH（D案件以上）'!$H$5:$H$1048576,"成立")+SUMIFS('【入力用③】案件ごとCH（D案件以上）'!T$5:T$1048576,'【入力用③】案件ごとCH（D案件以上）'!$N$5:$N$1048576,【表示用】各メンバーCH!$B25,'【入力用③】案件ごとCH（D案件以上）'!$H$5:$H$1048576,"A") -> 0.75 | J26: =SUMIFS('【入力用③】案件ごとCH（D案件以上）'!U$5:U$1048576,'【入力用③】案件ごとCH（D案件以上）'!$N$5:$N$1048576,【表示用】各メンバーCH!$B25,'【入力用③】案件ごとCH（D案件以上）'!$H$5:$H$1048576,"成立")+SUMIFS('【入力用③】案件ごとCH（D案件以上）'!U$5:U$1048576,'【入力用③】案件ごとCH（D案件以上）'!$N$5:$N$1048576,【表示用】各メンバーCH!$B25,'【入力用③】案件ごとCH（D案件以上）'!$H$5:$H$1048576,"A") -> 0.695 | K26: =SUMIFS('【入力用③】案件ごとCH（D案件以上）'!V$5:V$1048576,'【入力用③】案件ごとCH（D案件以上）'!$N$5:$N$1048576,【表示用】各メンバーCH!$B25,'【入力用③】案件ごとCH（D案件以上）'!$H$5:$H$1048576,"成立")+SUMIFS('【入力用③】案件ごとCH（D案件以上）'!V$5:V$1048576,'【入力用③】案件ごとCH（D案件以上）'!$N$5:$N$1048576,【表示用】各メンバーCH!$B25,'【入力用③】案件ごとCH（D案件以上）'!$H$5:$H$1048576,"A") -> 0.4 | ... O26: =SUMIFS('【入力用③】案件ごとCH（D案件以上）'!Z$5:Z$1048576,'【入力用③】案件ごとCH（D案件以上）'!$N$5:$N$1048576,【表示用】各メンバーCH!$B25,'【入力用③】案件ごとCH（D案件以上）'!$H$5:$H$1048576,"成立")+SUMIFS('【入力用③】案件ごとCH（D案件以上）'!Z$5:Z$1048576,'【入力用③】案件ごとCH（D案件以上）'!$N$5:$N$1048576,【表示用】各メンバーCH!$B25,'【入力用③】案件ごとCH（D案件以上）'!$H$5:$H$1048576,"A") -> 0
C27: ③GAP（②-①） | D27: =D26-D25 -> -0.15 | E27: =E26-E25 -> 0.07 | F27: =F26-F25 -> -0.21 | G27: =G26-G25 -> -0.15 | H27: =H26-H25 -> -0.78 | I27: =I26-I25 -> -0.15 | J27: =J26-J25 -> -0.205 | K27: =K26-K25 -> -0.5 | ... O27: =O26-O25 -> -0.9
B28: 古藤 | C28: ①目標 | D28: 0.8 | E28: 0.8 | F28: 0.8 | G28: 0.8 | H28: 0.8 | I28: 0.8 | J28: 0.8 | K28: 0.8 | L28: 0.8 | M28: 0.8 | N28: 0.8 | O28: 0.8
C29: ②見積 | D29: =SUMIFS('【入力用③】案件ごとCH（D案件以上）'!O$5:O$1048576,'【入力用③】案件ごとCH（D案件以上）'!$N$5:$N$1048576,【表示用】各メンバーCH!$B28,'【入力用③】案件ごとCH（D案件以上）'!$H$5:$H$1048576,"成立")+SUMIFS('【入力用③】案件ごとCH（D案件以上）'!O$5:O$1048576,'【入力用③】案件ごとCH（D案件以上）'!$N$5:$N$1048576,【表示用】各メンバーCH!$B28,'【入力用③】案件ごとCH（D案件以上）'!$H$5:$H$1048576,"A") -> 0 | E29: =SUMIFS('【入力用③】案件ごとCH（D案件以上）'!P$5:P$1048576,'【入力用③】案件ごとCH（D案件以上）'!$N$5:$N$1048576,【表示用】各メンバーCH!$B28,'【入力用③】案件ごとCH（D案件以上）'!$H$5:$H$1048576,"成立")+SUMIFS('【入力用③】案件ごとCH（D案件以上）'!P$5:P$1048576,'【入力用③】案件ごとCH（D案件以上）'!$N$5:$N$1048576,【表示用】各メンバーCH!$B28,'【入力用③】案件ごとCH（D案件以上）'!$H$5:$H$1048576,"A") -> 0 | F29: =SUMIFS('【入力用③】案件ごとCH（D案件以上）'!Q$5:Q$1048576,'【入力用③】案件ごとCH（D案件以上）'!$N$5:$N$1048576,【表示用】各メンバーCH!$B28,'【入力用③】案件ごとCH（D案件以上）'!$H$5:$H$1048576,"成立")+SUMIFS('【入力用③】案件ごとCH（D案件以上）'!Q$5:Q$1048576,'【入力用③】案件ごとCH（D案件以上）'!$N$5:$N$1048576,【表示用】各メンバーCH!$B28,'【入力用③】案件ごとCH（D案件以上）'!$H$5:$H$1048576,"A") -> 0 | G29: =SUMIFS('【入力用③】案件ごとCH（D案件以上）'!R$5:R$1048576,'【入力用③】案件ごとCH（D案件以上）'!$N$5:$N$1048576,【表示用】各メンバーCH!$B28,'【入力用③】案件ごとCH（D案件以上）'!$H$5:$H$1048576,"成立")+SUMIFS('【入力用③】案件ごとCH（D案件以上）'!R$5:R$1048576,'【入力用③】案件ごとCH（D案件以上）'!$N$5:$N$1048576,【表示用】各メンバーCH!$B28,'【入力用③】案件ごとCH（D案件以上）'!$H$5:$H$1048576,"A") -> 0 | H29: =SUMIFS('【入力用③】案件ごとCH（D案件以上）'!S$5:S$1048576,'【入力用③】案件ごとCH（D案件以上）'!$N$5:$N$1048576,【表示用】各メンバーCH!$B28,'【入力用③】案件ごとCH（D案件以上）'!$H$5:$H$1048576,"成立")+SUMIFS('【入力用③】案件ごとCH（D案件以上）'!S$5:S$1048576,'【入力用③】案件ごとCH（D案件以上）'!$N$5:$N$1048576,【表示用】各メンバーCH!$B28,'【入力用③】案件ごとCH（D案件以上）'!$H$5:$H$1048576,"A") -> 0 | I29: =SUMIFS('【入力用③】案件ごとCH（D案件以上）'!T$5:T$1048576,'【入力用③】案件ごとCH（D案件以上）'!$N$5:$N$1048576,【表示用】各メンバーCH!$B28,'【入力用③】案件ごとCH（D案件以上）'!$H$5:$H$1048576,"成立")+SUMIFS('【入力用③】案件ごとCH（D案件以上）'!T$5:T$1048576,'【入力用③】案件ごとCH（D案件以上）'!$N$5:$N$1048576,【表示用】各メンバーCH!$B28,'【入力用③】案件ごとCH（D案件以上）'!$H$5:$H$1048576,"A") -> 0.7 | J29: =SUMIFS('【入力用③】案件ごとCH（D案件以上）'!U$5:U$1048576,'【入力用③】案件ごとCH（D案件以上）'!$N$5:$N$1048576,【表示用】各メンバーCH!$B28,'【入力用③】案件ごとCH（D案件以上）'!$H$5:$H$1048576,"成立")+SUMIFS('【入力用③】案件ごとCH（D案件以上）'!U$5:U$1048576,'【入力用③】案件ごとCH（D案件以上）'!$N$5:$N$1048576,【表示用】各メンバーCH!$B28,'【入力用③】案件ごとCH（D案件以上）'!$H$5:$H$1048576,"A") -> 1 | K29: =SUMIFS('【入力用③】案件ごとCH（D案件以上）'!V$5:V$1048576,'【入力用③】案件ごとCH（D案件以上）'!$N$5:$N$1048576,【表示用】各メンバーCH!$B28,'【入力用③】案件ごとCH（D案件以上）'!$H$5:$H$1048576,"成立")+SUMIFS('【入力用③】案件ごとCH（D案件以上）'!V$5:V$1048576,'【入力用③】案件ごとCH（D案件以上）'!$N$5:$N$1048576,【表示用】各メンバーCH!$B28,'【入力用③】案件ごとCH（D案件以上）'!$H$5:$H$1048576,"A") -> 0 | ... O29: =SUMIFS('【入力用③】案件ごとCH（D案件以上）'!Z$5:Z$1048576,'【入力用③】案件ごとCH（D案件以上）'!$N$5:$N$1048576,【表示用】各メンバーCH!$B28,'【入力用③】案件ごとCH（D案件以上）'!$H$5:$H$1048576,"成立")+SUMIFS('【入力用③】案件ごとCH（D案件以上）'!Z$5:Z$1048576,'【入力用③】案件ごとCH（D案件以上）'!$N$5:$N$1048576,【表示用】各メンバーCH!$B28,'【入力用③】案件ごとCH（D案件以上）'!$H$5:$H$1048576,"A") -> 0
C30: ③GAP（②-①） | D30: =D29-D28 -> -0.8 | E30: =E29-E28 -> -0.8 | F30: =F29-F28 -> -0.8 | G30: =G29-G28 -> -0.8 | H30: =H29-H28 -> -0.8 | I30: =I29-I28 -> -0.1 | J30: =J29-J28 -> 0.2 | K30: =K29-K28 -> -0.8 | ... O30: =O29-O28 -> -0.8
B31: 小野寺 | C31: ①目標
C32: ②見積 | D32: =SUMIFS('【入力用③】案件ごとCH（D案件以上）'!O$5:O$1048576,'【入力用③】案件ごとCH（D案件以上）'!$N$5:$N$1048576,【表示用】各メンバーCH!$B31,'【入力用③】案件ごとCH（D案件以上）'!$H$5:$H$1048576,"成立")+SUMIFS('【入力用③】案件ごとCH（D案件以上）'!O$5:O$1048576,'【入力用③】案件ごとCH（D案件以上）'!$N$5:$N$1048576,【表示用】各メンバーCH!$B31,'【入力用③】案件ごとCH（D案件以上）'!$H$5:$H$1048576,"A") -> 0 | E32: =SUMIFS('【入力用③】案件ごとCH（D案件以上）'!P$5:P$1048576,'【入力用③】案件ごとCH（D案件以上）'!$N$5:$N$1048576,【表示用】各メンバーCH!$B31,'【入力用③】案件ごとCH（D案件以上）'!$H$5:$H$1048576,"成立")+SUMIFS('【入力用③】案件ごとCH（D案件以上）'!P$5:P$1048576,'【入力用③】案件ごとCH（D案件以上）'!$N$5:$N$1048576,【表示用】各メンバーCH!$B31,'【入力用③】案件ごとCH（D案件以上）'!$H$5:$H$1048576,"A") -> 0 | F32: =SUMIFS('【入力用③】案件ごとCH（D案件以上）'!Q$5:Q$1048576,'【入力用③】案件ごとCH（D案件以上）'!$N$5:$N$1048576,【表示用】各メンバーCH!$B31,'【入力用③】案件ごとCH（D案件以上）'!$H$5:$H$1048576,"成立")+SUMIFS('【入力用③】案件ごとCH（D案件以上）'!Q$5:Q$1048576,'【入力用③】案件ごとCH（D案件以上）'!$N$5:$N$1048576,【表示用】各メンバーCH!$B31,'【入力用③】案件ごとCH（D案件以上）'!$H$5:$H$1048576,"A") -> 0 | G32: =SUMIFS('【入力用③】案件ごとCH（D案件以上）'!R$5:R$1048576,'【入力用③】案件ごとCH（D案件以上）'!$N$5:$N$1048576,【表示用】各メンバーCH!$B31,'【入力用③】案件ごとCH（D案件以上）'!$H$5:$H$1048576,"成立")+SUMIFS('【入力用③】案件ごとCH（D案件以上）'!R$5:R$1048576,'【入力用③】案件ごとCH（D案件以上）'!$N$5:$N$1048576,【表示用】各メンバーCH!$B31,'【入力用③】案件ごとCH（D案件以上）'!$H$5:$H$1048576,"A") -> 0 | H32: =SUMIFS('【入力用③】案件ごとCH（D案件以上）'!S$5:S$1048576,'【入力用③】案件ごとCH（D案件以上）'!$N$5:$N$1048576,【表示用】各メンバーCH!$B31,'【入力用③】案件ごとCH（D案件以上）'!$H$5:$H$1048576,"成立")+SUMIFS('【入力用③】案件ごとCH（D案件以上）'!S$5:S$1048576,'【入力用③】案件ごとCH（D案件以上）'!$N$5:$N$1048576,【表示用】各メンバーCH!$B31,'【入力用③】案件ごとCH（D案件以上）'!$H$5:$H$1048576,"A") -> 0 | I32: =SUMIFS('【入力用③】案件ごとCH（D案件以上）'!T$5:T$1048576,'【入力用③】案件ごとCH（D案件以上）'!$N$5:$N$1048576,【表示用】各メンバーCH!$B31,'【入力用③】案件ごとCH（D案件以上）'!$H$5:$H$1048576,"成立")+SUMIFS('【入力用③】案件ごとCH（D案件以上）'!T$5:T$1048576,'【入力用③】案件ごとCH（D案件以上）'!$N$5:$N$1048576,【表示用】各メンバーCH!$B31,'【入力用③】案件ごとCH（D案件以上）'!$H$5:$H$1048576,"A") -> 0 | J32: =SUMIFS('【入力用③】案件ごとCH（D案件以上）'!U$5:U$1048576,'【入力用③】案件ごとCH（D案件以上）'!$N$5:$N$1048576,【表示用】各メンバーCH!$B31,'【入力用③】案件ごとCH（D案件以上）'!$H$5:$H$1048576,"成立")+SUMIFS('【入力用③】案件ごとCH（D案件以上）'!U$5:U$1048576,'【入力用③】案件ごとCH（D案件以上）'!$N$5:$N$1048576,【表示用】各メンバーCH!$B31,'【入力用③】案件ごとCH（D案件以上）'!$H$5:$H$1048576,"A") -> 0 | K32: =SUMIFS('【入力用③】案件ごとCH（D案件以上）'!V$5:V$1048576,'【入力用③】案件ごとCH（D案件以上）'!$N$5:$N$1048576,【表示用】各メンバーCH!$B31,'【入力用③】案件ごとCH（D案件以上）'!$H$5:$H$1048576,"成立")+SUMIFS('【入力用③】案件ごとCH（D案件以上）'!V$5:V$1048576,'【入力用③】案件ごとCH（D案件以上）'!$N$5:$N$1048576,【表示用】各メンバーCH!$B31,'【入力用③】案件ごとCH（D案件以上）'!$H$5:$H$1048576,"A") -> 0 | ... O32: =SUMIFS('【入力用③】案件ごとCH（D案件以上）'!Z$5:Z$1048576,'【入力用③】案件ごとCH（D案件以上）'!$N$5:$N$1048576,【表示用】各メンバーCH!$B31,'【入力用③】案件ごとCH（D案件以上）'!$H$5:$H$1048576,"成立")+SUMIFS('【入力用③】案件ごとCH（D案件以上）'!Z$5:Z$1048576,'【入力用③】案件ごとCH（D案件以上）'!$N$5:$N$1048576,【表示用】各メンバーCH!$B31,'【入力用③】案件ごとCH（D案件以上）'!$H$5:$H$1048576,"A") -> 0
C33: ③GAP（②-①） | D33: =D32-D31 -> 0 | E33: =E32-E31 -> 0 | F33: =F32-F31 -> 0 | G33: =G32-G31 -> 0 | H33: =H32-H31 -> 0 | I33: =I32-I31 -> 0 | J33: =J32-J31 -> 0 | K33: =K32-K31 -> 0 | ... O33: =O32-O31 -> 0

Sheet 【表示用】9期売上
B3: ＜単月実績（千円）＞
D4: 9月 | E4: 10月 | F4: 11月 | G4: 12月 | H4: 1月 | I4: 2月 | J4: 3月 | K4: 4月 | L4: 5月 | M4: 6月 | N4: 7月 | O4: 8月 | P4: 合計
C5: ①目標 | D5: 21000 | E5: 28000 | F5: 28000 | G5: 28000 | H5: 24500 | I5: 28000 | J5: 35000 | K5: 31500 | L5: 31500 | M5: 35000 | N5: 31500 | O5: 28000 | P5: =SUM(D5:O5) -> 350000
B6: 成立＋A | C6: ②実績 | D6: =SUM(D33:D34) -> 21320 | E6: =SUM(E33:E34) -> 23961 | F6: =SUM(F33:F34) -> 21500 | G6: =SUM(G33:G34) -> 19182 | H6: =SUM(H33:H34) -> 14900 | I6: =SUM(I33:I34) -> 21100 | J6: =SUM(J33:J34) -> 17350 | K6: =SUM(K33:K34) -> 7650 | ... P6: =SUM(P33:P34) -> 167613
C7: ③GAP（②-①） | D7: =D6-D5 -> 320 | E7: =E6-E5 -> -4039 | F7: =F6-F5 -> -6500 | G7: =G6-G5 -> -8818 | H7: =H6-H5 -> -9600 | I7: =I6-I5 -> -6900 | J7: =J6-J5 -> -17650 | K7: =K6-K5 -> -23850 | ... P7: =P6-P5 -> -182387
B8: 確度換算 | C8: ④実績 | D8: =D41 -> 21320 | E8: =E41 -> 24961 | F8: =F41 -> 22500 | G8: =G41 -> 20182 | H8: =H41 -> 15300 | I8: =I41 -> 21900 | J8: =J41 -> 19940 | K8: =K41 -> 12192 | ... O8: =O41 -> 4512 | P8: =SUM(D8:O8) -> 196701
C9: ⑤GAP（④-①） | D9: =D8-D5 -> 320 | E9: =E8-E5 -> -3039 | F9: =F8-F5 -> -5500 | G9: =G8-G5 -> -7818 | H9: =H8-H5 -> -9200 | I9: =I8-I5 -> -6100 | J9: =J8-J5 -> -15060 | K9: =K8-K5 -> -19308 | ... P9: =P8-P5 -> -153299
B11: ＜累積実績（千円）＞
D12: 9月 | E12: 10月 | F12: 11月 | G12: 12月 | H12: 1月 | I12: 2月 | J12: 3月 | K12: 4月 | L12: 5月 | M12: 6月 | N12: 7月 | O12: 8月 | P12: 合計
C13: ①目標 | D13: 21000 | E13: =D13+E5 -> 49000 | F13: =E13+F5 -> 77000 | G13: =F13+G5 -> 105000 | H13: =G13+H5 -> 129500 | I13: =H13+I5 -> 157500 | J13: =I13+J5 -> 192500 | K13: =J13+K5 -> 224000 | L13: =K13+L5 -> 255500 | ... O13: =N13+O5 -> 350000 | P13: =O13 -> 350000
B14: 成立＋A | C14: ②実績 | D14: =D6 -> 21320 | E14: =D14+E6 -> 45281 | F14: =E14+F6 -> 66781 | G14: =F14+G6 -> 85963 | H14: =G14+H6 -> 100863 | I14: =H14+I6 -> 121963 | J14: =I14+J6 -> 139313 | K14: =J14+K6 -> 146963 | L14: =K14+L6 -> 154613 | ... O14: =N14+O6 -> 167613 | P14: =O14 -> 167613
C15: ③GAP（②-①） | D15: =D14-D13 -> 320 | E15: =E14-E13 -> -3719 | F15: =F14-F13 -> -10219 | G15: =G14-G13 -> -19037 | H15: =H14-H13 -> -28637 | I15: =I14-I13 -> -35537 | J15: =J14-J13 -> -53187 | K15: =K14-K13 -> -77037 | ... P15: =P14-P13 -> -182387
B16: 確度換算 | C16: ④実績 | D16: =D8 -> 21320 | E16: =D16+E8 -> 46281 | F16: =E16+F8 -> 68781 | G16: =F16+G8 -> 88963 | H16: =G16+H8 -> 104263 | I16: =H16+I8 -> 126163 | J16: =I16+J8 -> 146103 | K16: =J16+K8 -> 158295 | L16: =K16+L8 -> 171057 | ... O16: =N16+O8 -> 196701 | P16: =O16 -> 196701
C17: ⑤GAP（④-①） | D17: =D16-D13 -> 320 | E17: =E16-E13 -> -2719 | F17: =F16-F13 -> -8219 | G17: =G16-G13 -> -16037 | H17: =H16-H13 -> -25237 | I17: =I16-I13 -> -31337 | J17: =J16-J13 -> -46397 | K17: =K16-K13 -> -65705 | ... P17: =P16-P13 -> -153299
B19: ＜対前年度比較：成立＋A＞
D20: 9月 | E20: 10月 | F20: 11月 | G20: 12月 | H20: 1月 | I20: 2月 | J20: 3月 | K20: 4月 | L20: 5月 | M20: 6月 | N20: 7月 | O20: 8月 | P20: 合計
B21: 8期実績 | C21: ①8期売上（単月） | D21: 10170 | E21: 14160 | F21: 13560 | G21: 11410 | H21: 10620 | I21: 12510 | J21: 16400 | K21: 10630 | L21: 17050 | M21: 19150 | N21: 20310 | O21: 13530 | P21: =SUM(D21:O21) -> 169500
C22: ②8期売上（累積） | D22: =D21 -> 10170 | E22: =D22+E21 -> 24330 | F22: =E22+F21 -> 37890 | G22: =F22+G21 -> 49300 | H22: =G22+H21 -> 59920 | I22: =H22+I21 -> 72430 | J22: =I22+J21 -> 88830 | K22: =J22+K21 -> 99460 | L22: =K22+L21 -> 116510 | ... O22: =N22+O21 -> 169500 | P22: =O22 -> 169500
B23: 単月 | C23: ③9期実績 | D23: =D6 -> 21320 | E23: =E6 -> 23961 | F23: =F6 -> 21500 | G23: =G6 -> 19182 | H23: =H6 -> 14900 | I23: =I6 -> 21100 | J23: =J6 -> 17350 | K23: =K6 -> 7650 | ... P23: =P6 -> 167613
C24: ④GAP（③-①） | D24: =D23-D21 -> 11150 | E24: =E23-E21 -> 9801 | F24: =F23-F21 -> 7940 | G24: =G23-G21 -> 7772 | H24: =H23-H21 -> 4280 | I24: =I23-I21 -> 8590 | J24: =J23-J21 -> 950 | K24: =K23-K21 -> -2980 | ... P24: =P23-P21 -> -1887
B25: 累積 | C25: ⑤9期実績 | D25: =D14 -> 21320 | E25: =E14 -> 45281 | F25: =F14 -> 66781 | G25: =G14 -> 85963 | H25: =H14 -> 100863 | I25: =I14 -> 121963 | J25: =J14 -> 139313 | K25: =K14 -> 146963 | ... P25: =P14 -> 167613
C26: ⑥GAP（⑤-①） | D26: =D25-D22 -> 11150 | E26: =E25-E22 -> 20951 | F26: =F25-F22 -> 28891 | G26: =G25-G22 -> 36663 | H26: =H25-H22 -> 40943 | I26: =I25-I22 -> 49533 | J26: =J25-J22 -> 50483 | K26: =K25-K22 -> 47503 | ... P26: =P25-P22 -> -1887
B30: ＜確度別金額・単月（千円）＞※換算前
D31: 9月 | E31: 10月 | F31: 11月 | G31: 12月 | H31: 1月 | I31: 2月 | J31: 3月 | K31: 4月 | L31: 5月 | M31: 6月 | N31: 7月 | O31: 8月 | P31: 合計
C32: 合計 | D32: =SUM(D33:D37) -> 21320 | E32: =SUM(E33:E37) -> 27961 | F32: =SUM(F33:F37) -> 25500 | G32: =SUM(G33:G37) -> 23182 | H32: =SUM(H33:H37) -> 16900 | I32: =SUM(I33:I37) -> 25100 | J32: =SUM(J33:J37) -> 24550 | K32: =SUM(K33:K37) -> 23310 | ... O32: =SUM(O33:O37) -> 13360 | P32: =SUM(D32:O32) -> 269553
C33: 成立 | D33: =SUMIF('【入力用②】案件ごと売上（D案件以上）'!$G$5:$G$1048576,【表示用】9期売上!$C33,'【入力用②】案件ごと売上（D案件以上）'!N$5:N$1048576) -> 19320 | E33: =SUMIF('【入力用②】案件ごと売上（D案件以上）'!$G$5:$G$1048576,【表示用】9期売上!$C33,'【入力用②】案件ごと売上（D案件以上）'!O$5:O$1048576) -> 21961 | F33: =SUMIF('【入力用②】案件ごと売上（D案件以上）'!$G$5:$G$1048576,【表示用】9期売上!$C33,'【入力用②】案件ごと売上（D案件以上）'!P$5:P$1048576) -> 19500 | G33: =SUMIF('【入力用②】案件ごと売上（D案件以上）'!$G$5:$G$1048576,【表示用】9期売上!$C33,'【入力用②】案件ごと売上（D案件以上）'!Q$5:Q$1048576) -> 16182 | H33: =SUMIF('【入力用②】案件ごと売上（D案件以上）'!$G$5:$G$1048576,【表示用】9期売上!$C33,'【入力用②】案件ごと売上（D案件以上）'!R$5:R$1048576) -> 11700 | I33: =SUMIF('【入力用②】案件ごと売上（D案件以上）'!$G$5:$G$1048576,【表示用】9期売上!$C33,'【入力用②】案件ごと売上（D案件以上）'!S$5:S$1048576) -> 16200 | J33: =SUMIF('【入力用②】案件ごと売上（D案件以上）'!$G$5:$G$1048576,【表示用】9期売上!$C33,'【入力用②】案件ごと売上（D案件以上）'!T$5:T$1048576) -> 11150 | K33: =SUMIF('【入力用②】案件ごと売上（D案件以上）'!$G$5:$G$1048576,【表示用】9期売上!$C33,'【入力用②】案件ごと売上（D案件以上）'!U$5:U$1048576) -> 5450 | ... O33: =SUMIF('【入力用②】案件ごと売上（D案件以上）'!$G$5:$G$1048576,【表示用】9期売上!$C33,'【入力用②】案件ごと売上（D案件以上）'!Y$5:Y$1048576) -> 0 | P33: =SUM(D33:O33) -> 137813
C34: A | D34: =SUMIF('【入力用②】案件ごと売上（D案件以上）'!$G$5:$G$1048576,【表示用】9期売上!$C34,'【入力用②】案件ごと売上（D案件以上）'!N$5:N$1048576) -> 2000 | E34: =SUMIF('【入力用②】案件ごと売上（D案件以上）'!$G$5:$G$1048576,【表示用】9期売上!$C34,'【入力用②】案件ごと売上（D案件以上）'!O$5:O$1048576) -> 2000 | F34: =SUMIF('【入力用②】案件ごと売上（D案件以上）'!$G$5:$G$1048576,【表示用】9期売上!$C34,'【入力用②】案件ごと売上（D案件以上）'!P$5:P$1048576) -> 2000 | G34: =SUMIF('【入力用②】案件ごと売上（D案件以上）'!$G$5:$G$1048576,【表示用】9期売上!$C34,'【入力用②】案件ごと売上（D案件以上）'!Q$5:Q$1048576) -> 3000 | H34: =SUMIF('【入力用②】案件ごと売上（D案件以上）'!$G$5:$G$1048576,【表示用】9期売上!$C34,'【入力用②】案件ごと売上（D案件以上）'!R$5:R$1048576) -> 3200 | I34: =SUMIF('【入力用②】案件ごと売上（D案件以上）'!$G$5:$G$1048576,【表示用】9期売上!$C34,'【入力用②】案件ごと売上（D案件以上）'!S$5:S$1048576) -> 4900 | J34: =SUMIF('【入力用②】案件ごと売上（D案件以上）'!$G$5:$G$1048576,【表示用】9期売上!$C34,'【入力用②】案件ごと売上（D案件以上）'!T$5:T$1048576) -> 6200 | K34: =SUMIF('【入力用②】案件ごと売上（D案件以上）'!$G$5:$G$1048576,【表示用】9期売上!$C34,'【入力用②】案件ごと売上（D案件以上）'!U$5:U$1048576) -> 2200 | ... O34: =SUMIF('【入力用②】案件ごと売上（D案件以上）'!$G$5:$G$1048576,【表示用】9期売上!$C34,'【入力用②】案件ごと売上（D案件以上）'!Y$5:Y$1048576) -> 700 | P34: =SUM(D34:O34) -> 29800
C35: B | D35: =SUMIF('【入力用②】案件ごと売上（D案件以上）'!$G$5:$G$1048576,【表示用】9期売上!$C35,'【入力用②】案件ごと売上（D案件以上）'!N$5:N$1048576) -> 0 | E35: =SUMIF('【入力用②】案件ごと売上（D案件以上）'!$G$5:$G$1048576,【表示用】9期売上!$C35,'【入力用②】案件ごと売上（D案件以上）'!O$5:O$1048576) -> 0 | F35: =SUMIF('【入力用②】案件ごと売上（D案件以上）'!$G$5:$G$1048576,【表示用】9期売上!$C35,'【入力用②】案件ごと売上（D案件以上）'!P$5:P$1048576) -> 0 | G35: =SUMIF('【入力用②】案件ごと売上（D案件以上）'!$G$5:$G$1048576,【表示用】9期売上!$C35,'【入力用②】案件ごと売上（D案件以上）'!Q$5:Q$1048576) -> 0 | H35: =SUMIF('【入力用②】案件ごと売上（D案件以上）'!$G$5:$G$1048576,【表示用】9期売上!$C35,'【入力用②】案件ごと売上（D案件以上）'!R$5:R$1048576) -> 0 | I35: =SUMIF('【入力用②】案件ごと売上（D案件以上）'!$G$5:$G$1048576,【表示用】9期売上!$C35,'【入力用②】案件ごと売上（D案件以上）'!S$5:S$1048576) -> 0 | J35: =SUMIF('【入力用②】案件ごと売上（D案件以上）'!$G$5:$G$1048576,【表示用】9期売上!$C35,'【入力用②】案件ごと売上（D案件以上）'!T$5:T$1048576) -> 2000 | K35: =SUMIF('【入力用②】案件ごと売上（D案件以上）'!$G$5:$G$1048576,【表示用】9期売上!$C35,'【入力用②】案件ごと売上（D案件以上）'!U$5:U$1048576) -> 2160 | ... O35: =SUMIF('【入力用②】案件ごと売上（D案件以上）'!$G$5:$G$1048576,【表示用】9期売上!$C35,'【入力用②】案件ごと売上（D案件以上）'!Y$5:Y$1048576) -> 2160 | P35: =SUM(D35:O35) -> 12840
C36: C | D36: =SUMIF('【入力用②】案件ごと売上（D案件以上）'!$G$5:$G$1048576,【表示用】9期売上!$C36,'【入力用②】案件ごと売上（D案件以上）'!N$5:N$1048576) -> 0 | E36: =SUMIF('【入力用②】案件ごと売上（D案件以上）'!$G$5:$G$1048576,【表示用】9期売上!$C36,'【入力用②】案件ごと売上（D案件以上）'!O$5:O$1048576) -> 2000 | F36: =SUMIF('【入力用②】案件ごと売上（D案件以上）'!$G$5:$G$1048576,【表示用】9期売上!$C36,'【入力用②】案件ごと売上（D案件以上）'!P$5:P$1048576) -> 2000 | G36: =SUMIF('【入力用②】案件ごと売上（D案件以上）'!$G$5:$G$1048576,【表示用】9期売上!$C36,'【入力用②】案件ごと売上（D案件以上）'!Q$5:Q$1048576) -> 2000 | H36: =SUMIF('【入力用②】案件ごと売上（D案件以上）'!$G$5:$G$1048576,【表示用】9期売上!$C36,'【入力用②】案件ごと売上（D案件以上）'!R$5:R$1048576) -> 0 | I36: =SUMIF('【入力用②】案件ごと売上（D案件以上）'!$G$5:$G$1048576,【表示用】9期売上!$C36,'【入力用②】案件ごと売上（D案件以上）'!S$5:S$1048576) -> 0 | J36: =SUMIF('【入力用②】案件ごと売上（D案件以上）'!$G$5:$G$1048576,【表示用】9期売上!$C36,'【入力用②】案件ごと売上（D案件以上）'!T$5:T$1048576) -> 1500 | K36: =SUMIF('【入力用②】案件ごと売上（D案件以上）'!$G$5:$G$1048576,【表示用】9期売上!$C36,'【入力用②】案件ごと売上（D案件以上）'!U$5:U$1048576) -> 3300 | ... O36: =SUMIF('【入力用②】案件ごと売上（D案件以上）'!$G$5:$G$1048576,【表示用】9期売上!$C36,'【入力用②】案件ごと売上（D案件以上）'!Y$5:Y$1048576) -> 2000 | P36: =SUM(D36:O36) -> 22800
C37: D | D37: =SUMIF('【入力用②】案件ごと売上（D案件以上）'!$G$5:$G$1048576,【表示用】9期売上!$C37,'【入力用②】案件ごと売上（D案件以上）'!N$5:N$1048576) -> 0 | E37: =SUMIF('【入力用②】案件ごと売上（D案件以上）'!$G$5:$G$1048576,【表示用】9期売上!$C37,'【入力用②】案件ごと売上（D案件以上）'!O$5:O$1048576) -> 2000 | F37: =SUMIF('【入力用②】案件ごと売上（D案件以上）'!$G$5:$G$1048576,【表示用】9期売上!$C37,'【入力用②】案件ごと売上（D案件以上）'!P$5:P$1048576) -> 2000 | G37: =SUMIF('【入力用②】案件ごと売上（D案件以上）'!$G$5:$G$1048576,【表示用】9期売上!$C37,'【入力用②】案件ごと売上（D案件以上）'!Q$5:Q$1048576) -> 2000 | H37: =SUMIF('【入力用②】案件ごと売上（D案件以上）'!$G$5:$G$1048576,【表示用】9期売上!$C37,'【入力用②】案件ごと売上（D案件以上）'!R$5:R$1048576) -> 2000 | I37: =SUMIF('【入力用②】案件ごと売上（D案件以上）'!$G$5:$G$1048576,【表示用】9期売上!$C37,'【入力用②】案件ごと売上（D案件以上）'!S$5:S$1048576) -> 4000 | J37: =SUMIF('【入力用②】案件ごと売上（D案件以上）'!$G$5:$G$1048576,【表示用】9期売上!$C37,'【入力用②】案件ごと売上（D案件以上）'!T$5:T$1048576) -> 3700 | K37: =SUMIF('【入力用②】案件ごと売上（D案件以上）'!$G$5:$G$1048576,【表示用】9期売上!$C37,'【入力用②】案件ごと売上（D案件以上）'!U$5:U$1048576) -> 10200 | ... O37: =SUMIF('【入力用②】案件ごと売上（D案件以上）'!$G$5:$G$1048576,【表示用】9期売上!$C37,'【入力用②】案件ごと売上（D案件以上）'!Y$5:Y$1048576) -> 8500 | P37: =SUM(D37:O37) -> 66300
B39: ＜確度別金額・単月（千円）＞※換算後
D40: 9月 | E40: 10月 | F40: 11月 | G40: 12月 | H40: 1月 | I40: 2月 | J40: 3月 | K40: 4月 | L40: 5月 | M40: 6月 | N40: 7月 | O40: 8月 | P40: 合計
C41: 合計 | D41: =SUM(D42:D46) -> 21320 | E41: =SUM(E42:E46) -> 24961 | F41: =SUM(F42:F46) -> 22500 | G41: =SUM(G42:G46) -> 20182 | H41: =SUM(H42:H46) -> 15300 | I41: =SUM(I42:I46) -> 21900 | J41: =SUM(J42:J46) -> 19940 | K41: =SUM(K42:K46) -> 12192 | ... O41: =SUM(O42:O46) -> 4512 | P41: =SUM(D41:O41) -> 196701
B42: 1 | C42: 成立 | D42: =D33*$B42 -> 19320 | E42: =E33*$B42 -> 21961 | F42: =F33*$B42 -> 19500 | G42: =G33*$B42 -> 16182 | H42: =H33*$B42 -> 11700 | I42: =I33*$B42 -> 16200 | J42: =J33*$B42 -> 11150 | K42: =K33*$B42 -> 5450 | ... O42: =O33*$B42 -> 0 | P42: =SUM(D42:O42) -> 137813
B43: 1 | C43: A | D43: =D34*$B43 -> 2000 | E43: =E34*$B43 -> 2000 | F43: =F34*$B43 -> 2000 | G43: =G34*$B43 -> 3000 | H43: =H34*$B43 -> 3200 | I43: =I34*$B43 -> 4900 | J43: =J34*$B43 -> 6200 | K43: =K34*$B43 -> 2200 | ... O43: =O34*$B43 -> 700 | P43: =SUM(D43:O43) -> 29800
B44: 0.7 | C44: B | D44: =D35*$B44 -> 0 | E44: =E35*$B44 -> 0 | F44: =F35*$B44 -> 0 | G44: =G35*$B44 -> 0 | H44: =H35*$B44 -> 0 | I44: =I35*$B44 -> 0 | J44: =J35*$B44 -> 1400 | K44: =K35*$B44 -> 1512 | ... O44: =O35*$B44 -> 1512 | P44: =SUM(D44:O44) -> 8988
B45: 0.3 | C45: C | D45: =D36*$B45 -> 0 | E45: =E36*$B45 -> 600 | F45: =F36*$B45 -> 600 | G45: =G36*$B45 -> 600 | H45: =H36*$B45 -> 0 | I45: =I36*$B45 -> 0 | J45: =J36*$B45 -> 450 | K45: =K36*$B45 -> 990 | ... O45: =O36*$B45 -> 600 | P45: =SUM(D45:O45) -> 6840
B46: 0.2 | C46: D | D46: =D37*$B46 -> 0 | E46: =E37*$B46 -> 400 | F46: =F37*$B46 -> 400 | G46: =G37*$B46 -> 400 | H46: =H37*$B46 -> 400 | I46: =I37*$B46 -> 800 | J46: =J37*$B46 -> 740 | K46: =K37*$B46 -> 2040 | ... O46: =O37*$B46 -> 1700 | P46: =SUM(D46:O46) -> 13260

Sheet 【表示用】案件ごと売上
A1: 確度 | B1: (複数のアイテム)
A3: 行ラベル | B3: 合計 / 9期分 | C3: 合計 / 9月 | D3: 合計 / 10月 | E3: 合計 / 11月 | F3: 合計 / 12月 | G3: 合計 / 1月 | H3: 合計 / 2月 | I3: 合計 / 3月 | J3: 合計 / 4月 | K3: 合計 / 5月 | L3: 合計 / 6月 | M3: 合計 / 7月 | N3: 合計 / 8月
A4: 01_伊藤ハム米久ホールディングス_エンゲージメント向上PJT | B4: 550 | C4: 550
A5: 02_パラドックス_森の歩き方実装支援 | B5: 300 | C5: 300
A6: 03_日本総研_キャリア入社者課題分析 | B6: 600 | C6: 600
A7: 05_YAMAGATA_新事業立ち上げ支援 | B7: 14500 | C7: 3700 | D7: 3600 | E7: 3600 | F7: 3600
A8: 07_豊田通商_メタルプラス | B8: 6750 | D8: 2250 | E8: 2250 | F8: 2250
A9: 08_OKI_人材面を主とした組織診断 | B9: 4000 | C9: 2000 | D9: 2000
A10: 09_宮﨑製鋼_エンゲージメントサーベイ | B10: 500 | C10: 140 | D10: 360
A11: 10_オムロンエキスパートエンジニアリング_データ分析 | B11: 2000 | D11: 500 | E11: 500 | F11: 1000
A12: 11_MSプライマリー_エンゲージメントサーベイ | B12: 7000 | C12: 2000 | D12: 1500 | E12: 1500 | F12: 2000
A13: 12_アートプレスト_2025年上期人事施策実行支援 | B13: 6700 | C13: 6700
A14: 13_アートプレスト_2025年下期人事施策実行支援 | B14: 37900 | D14: 8000 | E14: 7800 | F14: 5900 | G14: 6100 | H14: 5800 | I14: 4300
A15: 14_アートプレスト_経営層候補者向け研修実行支援 | B15: 250 | E15: 250
A16: 15_アートプレスト_役員研修 | B16: 100 | D16: 100
A17: 16_JALUX_ビジネス変革Community | B17: 750 | D17: 750
A18: 17_JALUX_業務効率化 | B18: 2300 | C18: 480 | D18: 440
A19: 18_パラマウントベッド_管理職WS＆部門幹部ディスカッション | B19: 4470 | D19: 1881 | F19: 800
A20: 19_asics_HRBP支援 | B20: 400 | C20: 400
A21: 20_コメダ_FC対応力向上 | B21: 2000 | C21: 600 | D21: 600 | E21: 800
A22: 21_ローソンエンタテインメント_人事制度・育成概要設計 | B22: 12300 | C22: 2050 | D22: 2050 | E22: 2050 | F22: 2050 | G22: 2050 | H22: 2050
A23: 22_オーネスト_MVV浸透支援Phase3 | B23: 1300 | C23: 1300
A24: 25_パラマウントベッド_女性社員交流会 企画支援 | B24: 500 | C24: 500
A25: 29_パラマウントベッド_女性社員交流会 キックオフイベント支援 | B25: 700 | D25: 280
A26: 30_パラマウントベッド_女性社員交流会_女性キャリア研修 | B26: 1246 | E26: 117 | F26: 132
A27: 31_パーソルクロステクノロジー_社内広報業務支援 | B27: 2250
A28: 33_田島ルーフィング_推せる職場診断 | B28: 3100 | D28: 1000 | E28: 1000 | F28: 300 | G28: 300 | H28: 500
A29: 36_パラドックス_森の歩き方実装支援（10月以降） | B29: 1650 | D29: 150 | E29: 300 | F29: 300 | G29: 300 | H29: 300 | I29: 300
A30: 40_三井情報_人材マネジメントアドバイザリー | B30: 3500 | E30: 700 | F30: 700 | G30: 700 | H30: 700 | I30: 700
A31: 総計 | B31: 117616 | C31: 21320 | D31: 25461 | E31: 20867 | F31: 19032 | G31: 9450 | H31: 9350 | I31: 5300

Sheet 【入力用①】パイプライン
B2: No | C2: クライアント | D2: 案件 | E2: テーマ（分類） | F2: 流入ルート | G2: 金額（万円） | H2: 期間（月） | I2: 期間補足 | J2: 営業担当 | K2: 確度 | L2: 与信新規申請 | M2: 与信限度額 超過申請 | N2: MM/DD | O2: 攻略作戦 | P2: 45958 | Q2: 45944 | R2: 45937 | S2: 45902 | T2: 45895
B3: =ROW(A3)-2 -> 1 | C3: JFEエンジニアリング | D3: タレマネ活用 | E3: ⑥人材育成コンサル | F3: HRPトスアップ | J3: 弓本、小川 | S3: タレマネツールの導入について、先方DX推進室で候補選定中。別途人事担当者様にアプローチ予定。 | U3: e
B4: =ROW(A4)-2 -> 2 | C4: PHCホールディングス | D4: オンボーディング環境整備 | E4: ②採用・オンボーディング | F4: HRPトスアップ | J4: 弓本、小川 | O4: 担当部長を起点に人事担当役員にアプローチ 当面は若手社員の流出防止目的のキャリア研修で信頼関係構築。２年後採用倍増計画に合わせ受け入れ態勢整備の案件を提案（来年４月以降プロジェクト） | S4: 先方担当（横山様）と小川さんで会話済み。コンサル側はすぐの受注ではなさそう。 | U4: e
B5: =ROW(A5)-2 -> 3 | C5: テプコ・ソリューション・アドバンス | D5: MVV浸透 | E5: ⑦その他 | F5: HRPトスアップ（新） | J5: 小川 | U5: e
B6: =ROW(A6)-2 -> 4 | C6: ユニリタ | U6: e
B7: =ROW(A7)-2 -> 5 | C7: コメダ | D7: 大学充実化 | E7: ⑥人材育成コンサル | F7: HRPトスアップ | J7: 森田、小川 | O7: 人事担当役員向けに大学のタレマネ機能拡充の提案 館越経由 | U7: e
B8: =ROW(A8)-2 -> 6 | C8: ENEOS | D8: マネジメント層強化 | E8: ⑥人材育成コンサル | F8: HRPトスアップ | J8: 小川 | O8: 部長研修の延長線上で、管理職のマネジメント力強化につながる施策として推せる職場づくりを人事担当役員に提案 | U8: e
B9: =ROW(A9)-2 -> 7 | C9: デジタルガレージ | D9: 人的資本経営 | E9: ⑥人材育成コンサル | F9: HP、セミナー経由 | J9: 小川 | U9: e
B10: =ROW(A10)-2 -> 8 | C10: メイテック | U10: e
B11: =ROW(A11)-2 -> 9 | C11: 帝人 | U11: e
B12: =ROW(A12)-2 -> 10 | C12: BeeX | D12: キャリアパス設計 | F12: EXPO | G12: 450～600万円 | H12: 3 | J12: 小川・啓亮 | K12: D | S12: 他社の事業戦略～人材ポートフォリオの調査及び自社の人材像とあるべき人材ポートフォリオの検討に興味を持っている。先方人事部長のほうで方向性を整理し、再度スコープをすり合わせる打ち合わせを打診する | T12: 8/29先方人事部長・マネージャーと打ち合わせ予定 | U12: e
B13: =ROW(A13)-2 -> 11 | C13: 千葉県 | D13: サーベイ活用 | F13: EXPO | J13: 啓亮、小川 | U13: e
B14: =ROW(A14)-2 -> 12 | C14: イオン | U14: e
B15: =ROW(A15)-2 -> 13 | C15: 安部日鋼工業 | D15: 経営WS | F15: HRPトスアップ（新） | J15: 啓亮、小川 | U15: e
B16: =ROW(A16)-2 -> 14 | C16: SUBARU | D16: タレマネ | J16: 小川 | U16: e
B17: =ROW(A17)-2 -> 15 | C17: 安田工業 | D17: 推せる職場づくり | E17: ①推せる職場づくり | F17: HRPトスアップ（新） | J17: 弓本、小川 | O17: エンゲージメント向上にむけた３か年計画を伴走支援 人事部長⇒社長の説得を支援 | S17: 先方とは2回接点を持っており、先方希望の資料を提供済み。池本くんで状況確認中。 | U17: e
B18: =ROW(A18)-2 -> 16 | C18: 西武HD | D18: オンボーディング | E18: ②採用・オンボーディング | J18: 弓本 | K18: C | U18: e
B19: =ROW(A19)-2 -> 17 | C19: キューピー | U19: e
B20: =ROW(A20)-2 -> 18 | C20: サラヤ | U20: e
B21: =ROW(A21)-2 -> 19 | C21: 昭和産業 | D21: MVV浸透 | E21: ⑦その他 | F21: HRPトスアップ（新） | J21: 小川 | U21: e
B22: =ROW(A22)-2 -> 20 | C22: 三菱UFJニコス | D22: 育成方針策定 | E22: ⑥人材育成コンサル | F22: HRPトスアップ | J22: 啓亮、小川 | U22: e
B23: =ROW(A23)-2 -> 21 | C23: アサヒクオリティアンドイノベーションズ | D23: スキルマップ | E23: ⑥人材育成コンサル | F23: WHI経由 | J23: 啓亮、小川 | U23: e
B24: =ROW(A24)-2 -> 22 | C24: オーネスト | D24: 評価制度設計 | E24: ⑤人事制度改革 | F24: クロス | J24: 小川 | U24: e
B25: =ROW(A25)-2 -> 23 | C25: クレオテック | D25: キャリア形成支援 | E25: ⑥人材育成コンサル | F25: HRPトスアップ | J25: 小川 | U25: e
B26: =ROW(A26)-2 -> 24 | C26: インテージテクノスフィア | F26: HP、セミナー経由 | J26: 弓本、小川 | S26: 感謝会に参加後、PANAIサーベイのトライアルと先方から懇親会希望の連絡あり。 | U26: e
B27: =ROW(A27)-2 -> 25 | C27: 兼松 | D27: 育成体系整備 | E27: ⑥人材育成コンサル | J27: 小川 | U27: e
B28: =ROW(A28)-2 -> 26 | C28: オムロンエキスパートエンジニアリング | D28: エンゲージメントサーベイ | F28: カオナビ | G28: 100～250万 | H28: 3 | I28: 202510～12末 | J28: 芹澤 | T28: 提案書・追加資料提出済み。当社でほぼ確定のご連絡を頂いた。 | U28: e
B29: =ROW(A29)-2 -> 27 | C29: 北九州市役所 | F29: HRPトスアップ | G29: 200万円 | H29: 2 | J29: 啓亮 | P29: サーベイ分析＆動画・ガイド作成＆研修設計・実施で400万円（4か月）。提案・契約工数と金額が見合わないため辞退 | Q29: 10月中旬に公告予定 | R29: 10月中旬に公告予定 | S29: エンゲージメントサーベイの簡易分析と説明用動画作成で200万円程度。入札参加資格獲得の工数や公共提案の工数を踏まえた際に、やるべきかどうか相談 | U29: e
B30: =ROW(A30)-2 -> 28 | C30: 社会医療法人友愛会 | U30: e
B31: =ROW(A31)-2 -> 29 | C31: 水戸済生会総合病院 | U31: e
B32: =ROW(A32)-2 -> 30 | C32: 日本毛織 | U32: e
B33: =ROW(A33)-2 -> 31 | C33: 人事院 | D33: キャリア形成支援、オンボーディング | E33: ⑥人材育成コンサル | F33: HP、セミナー経由 | G33: 250万円 ※来年度 | J33: 小川 | U33: e
B34: =ROW(A34)-2 -> 32 | C34: 東京消防庁 | D34: 育成体系整備 | E34: ⑥人材育成コンサル | F34: HP、セミナー経由 | J34: 小川 | U34: e
B35: =ROW(A35)-2 -> 33 | C35: アイシン | D35: 育成体系整備 | E35: ⑥人材育成コンサル | F35: HRPトスアップ | J35: 森田 | U35: e
B36: =ROW(A36)-2 -> 34 | C36: アントステラ | D36: 人材戦略アドバイザリー | E36: ⑤人事制度改革 | F36: HRPトスアップ | J36: 小川 | U36: e
B37: =ROW(A37)-2 -> 35 | C37: ひらまつ | D37: キャリアパス＆育成体系 | F37: 紹介（パラドックス） | G37: 1200万円 | H37: 6 | I37: 10月～3月 | J37: 小川・啓亮 | P37: パラドックス高田さんとCOOの方で11月までにスコープを定めるとのこと。スタートするとしても12月以降となりそう。 | Q37: 今週中に連絡なければ、来週頭に一度連絡 | R37: パラドックス担当→COOへ提案書展開。ひきつづきパラドックス担当と連携して進める | S37: 8/29パラドックスと提案内容すり合わせMTG→9/5先方現地訪問予定 | T37: 8/29パラドックスと提案内容すり合わせMTG→9/5先方現地訪問予定 | U37: e
B38: =ROW(A38)-2 -> 36 | C38: アールビーコントロールズ | F38: HRPトスアップ（新） | J38: 小川 | U38: e
B39: =ROW(A39)-2 -> 37 | C39: アルプスアルパイン | F39: HRPトスアップ（新） | J39: 小川
B40: =ROW(A40)-2 -> 38 | C40: デンソーソリューション | F40: HRPトスアップ | J40: 小川
B41: =ROW(A41)-2 -> 39 | C41: ブラザー工業 | D41: サーベイ活用 | J41: 小川
B42: =ROW(A42)-2 -> 40 | C42: 三井情報 | D42: キャリア形成支援 | E42: ⑥人材育成コンサル | F42: HRPトスアップ（新） | G42: 3500 | I42: 11月～3月 | J42: 小川、啓亮 | K42: A | P42: 受注 | Q42: 16日に打ち合わせ。既にNEWONEに依頼する意向であり、16日はその条件のすり合わせ。オンボーディングや室長の役割・業務定義などに関するアドバイザリー。
B43: =ROW(A43)-2 -> 41 | C43: スマートドライブ | D43: 人材戦略 | E43: ⑤人事制度改革 | F43: アトラエ紹介 | J43: 小川 | O43: CHROとコンタクト中 経営メンバーのWSを提案。人事戦略の方向性を合意形成し、それを踏まえた各種人事施策の実行支援を実施
B44: =ROW(A44)-2 -> 42 | C44: エレメントルール | D44: キャリア形成支援 | E44: ⑥人材育成コンサル | F44: HRPトスアップ（新） | J44: 小川
B45: =ROW(A45)-2 -> 43 | C45: 朝日生命 | D45: エンゲージメント向上 | E45: ①推せる職場づくり | F45: HRPトスアップ | J45: 啓亮 | P45: 10/30に企業内大学に関する打ち合わせ予定 | R45: 10/8オンライン打ち合わせ予定。情報提供後、当分動かなさそうであればHRPに任せる | S45: エンゲージメントサーベイ（Wevox）の更なる分析と課題の特定に関心があるそう。9/2打ち合わせ予定 | T45: エンゲージメントサーベイ（Wevox）の更なる分析と課題の特定に関心があるそう。9/2打ち合わせ予定
B46: =ROW(A46)-2 -> 44 | C46: 伊藤ハム | D46: 社長座談会＆エンゲージメント向上伴走支援 | F46: クロス | J46: 葛西・啓亮 | P46: 懇親会セットせねば | R46: 懇親会セット | S46: 最終報告にて後続施策提案に向けて動いている所。今のところWS系で且つHRPとの連携も見据えているので単価としてはそこまで上がらないか… | T46: 最終報告にて後続施策提案に向けて動いている所。今のところWS系で且つHRPとの連携も見据えているので単価としてはそこまで上がらないか…
B47: =ROW(A47)-2 -> 45 | C47: 信和HD | D47: 昇格試験の設計 | E47: ⑤人事制度改革 | F47: HRPトスアップ | J47: 小川・弓本 | K47: D | S47: 9/17に訪問予定。（初回はHRP＆小川さん）
B48: =ROW(A48)-2 -> 46 | C48: 日清医療食品 | D48: サーベイ分析 | E48: ①推せる職場づくり | F48: HRPトスアップ | J48: 小川 | O48: 経営幹部WS、社長・人事担当役員との相談会を実施中 現場ヒヤリングを調整中。課題仮説を設定し、人的資本経営に向けた会社施策を提案
B49: =ROW(A49)-2 -> 47 | C49: アイジーコンサル | D49: シニア活性化 | E49: ⑦その他 | F49: HRPトスアップ | J49: 小川
B50: =ROW(A50)-2 -> 48 | C50: DAIKO XTECH | D50: キャリア形成支援 | E50: ⑥人材育成コンサル | F50: HRPトスアップ | J50: 小川
B51: =ROW(A51)-2 -> 49 | C51: 福岡国際空港 | D51: 育成体系整備 | E51: ⑥人材育成コンサル | F51: HRPトスアップ | J51: 小川
B52: =ROW(A52)-2 -> 50 | C52: 名古屋鉄道 | D52: キャリア支援 | E52: ⑦その他 | F52: HRPトスアップ | J52: 小川、弓本 | K52: N | S52: 9/12に訪問予定。
B53: =ROW(A53)-2 -> 51 | C53: かんぽ生命 | D53: 育成効果測定 | E53: ⑥人材育成コンサル | F53: HRPトスアップ（新） | J53: 小川
B54: =ROW(A54)-2 -> 52 | C54: ニコンプロダクトサポート | D54: 人事制度・育成体系 | E54: ⑤人事制度改革 | F54: HRPトスアップ（新） | J54: 小川
B55: =ROW(A55)-2 -> 53 | C55: レスター | D55: 推せる職場づくり | E55: ①推せる職場づくり | F55: HRPトスアップ（新） | J55: 小川
B56: =ROW(A56)-2 -> 54 | C56: ギガプライズ | D56: サーベイデータ活用 | E56: ⑦その他 | F56: HRPトスアップ（新） | J56: 芹澤
B57: =ROW(A57)-2 -> 55 | C57: 山星屋 | D57: 推せる職場づくり | E57: ①推せる職場づくり | F57: HRPトスアップ（新） | J57: 小川
B58: =ROW(A58)-2 -> 56 | C58: 日本カストディ銀行 | D58: 推せる職場づくり | E58: ①推せる職場づくり | F58: HRPトスアップ（新） | J58: 小川
B59: =ROW(A59)-2 -> 57 | C59: パーソルクロステクノロジー | D59: 社内広報施策支援 | E59: ⑦その他 | F59: 前職クライアント | G59: 285 | H59: 3 | J59: 丸田 | K59: D
B60: =ROW(A60)-2 -> 58 | C60: 田島ルーフィング | D60: 推せる職場診断 | E60: ①推せる職場づくり | F60: 既存顧客 | G60: 200万円 | J60: 啓亮 | K60: 成立 | P60: 受注・デリバリー中 | R60: やる前提ではあるが、10月中に正式決定予定
B61: =ROW(A61)-2 -> 59 | C61: ファーマライズHD | D61: 推せる職場づくり | E61: ①推せる職場づくり | F61: HRPトスアップ（新） | J61: 小川
B62: =ROW(A62)-2 -> 60 | C62: しげる工業 | J62: 小川
B63: =ROW(A63)-2 -> 61 | C63: 日本カストディ銀行 | J63: 小川
B64: =ROW(A64)-2 -> 62 | C64: コメダ | D64: 昇格制度 | E64: ⑤人事制度改革 | F64: クロス | J64: 森田、小川
B65: =ROW(A65)-2 -> 63 | C65: 穴吹ハウジングサービス | D65: 推せる職場づくり、リテンション | E65: ①推せる職場づくり | F65: HRPトスアップ（新） | J65: 小川
B66: =ROW(A66)-2 -> 64 | C66: ポピンズシッター | D66: エンゲージメント向上 | E66: ①推せる職場づくり | F66: HRPトスアップ（新） | J66: 啓亮 | R66: 10/7打ち合わせ予定 →業務委託のシッターの定着についての相談。年内に先方でヒアリング＋アンケートをすることに。今後施策設計・実行やアドバイザリーなどで支援ニーズありそう。継続して追いかける。
B67: =ROW(A67)-2 -> 65 | C67: 中島董商店 | D67: 人材像定義～浸透 | E67: ⑥人材育成コンサル | F67: HRPトスアップ（新） | J67: 啓亮 | P67: 案件ニーズなし、HRPにナーチャリング任せる | R67: 10/3打ち合わせ。予算がなく、且つ研修以外使う想定が無いとのことで見込み薄。
B68: =ROW(A68)-2 -> 66 | C68: ピアス | J68: 啓亮 | P68: 行動指針みたいなものを浸透させるための総合的な施策を提案。次回11/6打ち合わせ予定 | R68: 10/20打ち合わせ予定
B69: =ROW(A69)-2 -> 67 | C69: 本田技術研究所 | D69: 女性研究職の定着支援 | E69: ①推せる職場づくり | G69: 300万円 | J69: 啓亮 | P69: 失注 | Q69: PROFFITにて提案提出済み。 | R69: PROFFIT案件。10/9までに提案書提出
B70: =ROW(A70)-2 -> 68 | C70: 荏原製作所 | D70: 企業内大学 | E70: ⑥人材育成コンサル | F70: HRPトスアップ | J70: 小川・啓亮 | P70: 情報収集メインで案件化のにおいが薄い… | Q70: 先週打ち合わせ済み。26年4月の制度リリースへ向けて引き続きディスカッション。しかし、先方の中でまだ正式にPJT化していないとのことで外部委託の予算をどれだけもっているか怪しい。先方は外部を使う必要性を感じているので、一緒に予算を獲得できる様進めていく。 | R70: 先週打ち合わせ済み。26年4月の制度リリースへ向けて引き続きディスカッション。しかし、先方の中でまだ正式にPJT化していないとのことで外部委託の予算をどれだけもっているか怪しい。先方は外部を使う必要性を感じているので、一緒に予算を獲得できる様進めていく。
B71: =ROW(A71)-2 -> 69 | C71: asics | D71: 管理職向けエンゲージメント向上施策 | E71: ①推せる職場づくり | F71: 既存顧客 | J71: 森田
B72: =ROW(A72)-2 -> 70 | C72: YAMAGATA | D72: PoC営業支援 | E72: ⑦その他 | F72: 既存顧客 | G72: 120万円 | J72: 波多野 | K72: D
B73: =ROW(A73)-2 -> 71 | C73: トヨタコネクティッド | D73: オンボーディングプログラム設計 | G73: 600万円 | J73: 小川、啓亮 | K73: A | P73: 10/30提案予定
B74: =ROW(A74)-2 -> 72 | C74: 一条工務店 | D74: 工事課での育成体系設計 | J74: 葛西・啓亮 | P74: 10/30打ち合わせ予定。スコープ等確認
B75: =ROW(A75)-2 -> 73 | C75: トーシンパートナーズホールディングス | D75: 育成体系設計 | E75: ⑥人材育成コンサル | F75: キリコミ(過去接触先) | J75: 波多野、森田
B76: =ROW(A76)-2 -> 74 | C76: 塩野義製薬 | D76: エンゲージメント向上に向けたKPI設計 | E76: ⑦その他 | F76: キリコミ(過去接触先) | G76: 1000万円 | J76: 芹澤 | P76: まずは研修をやっていくとのこと
B77: 75 | C77: パラマウントベッド | D77: DEI推進支援2026 | E77: ⑦その他 | F77: 既存顧客 | J77: 丸田 | K77: D
B78: =ROW(A78)-2 -> 76 | C78: ナリコマホールディングス | D78: 管理職育成体系設計 | E78: ⑥人材育成コンサル | F78: キリコミ(過去接触先) | J78: 波多野 | U78: e
B79: e | C79: e | D79: e | E79: e | F79: e | G79: e | H79: e | J79: e | K79: e | L79: e | M79: e | T79: e | U79: e | V79: e | W79: e | X79: e

Sheet 【入力用②】案件ごと売上（D案件以上）
A1: ※黄色セルは手動入力、行挿入はNG（案件Noが変わってしまうため）
I3: =SUM(I5:I44) -> 178654 | J3: ※計算用 | N3: ◆月別売上
A4: 継続 | B4: 案件No | C4: クライアント名 | D4: 案件名 | E4: PIVOT用_PJ管理 | F4: 案件種類 | G4: 確度 | H4: PIC | I4: 9期分 PJ全体売上 （千円） | J4: 月別売上合計 （千円） | K4: 差額 | L4: 期間 (月) | M4: 月単価 (千円) | N4: 9月 | O4: 10月 | P4: 11月 | Q4: 12月 | R4: 1月 | S4: 2月 | T4: 3月 | U4: 4月 | V4: 5月 | W4: 6月 | X4: 7月 | Y4: 8月 | Z4: *
B5: =ROW(A5)-4 -> 1 | C5: 伊藤ハム米久ホールディングス | D5: エンゲージメント向上PJT | E5: ="0"&B5&"_"&C5&"_"&D5 -> 01_伊藤ハム米久ホールディングス_エンゲージメント向上PJT | F5: 組織開発 | G5: 成立 | H5: 啓亮 | I5: 550 | J5: =SUM(N5:Y5) -> 550 | K5: =I5-J5 -> 0 | L5: 1 | M5: =IFERROR(I5/L5,"-") -> 550 | N5: 550 | Z5: *
B6: =ROW(A6)-4 -> 2 | C6: パラドックス | D6: 森の歩き方実装支援 | E6: ="0"&B6&"_"&C6&"_"&D6 -> 02_パラドックス_森の歩き方実装支援 | F6: 人材育成 | G6: 成立 | H6: 啓亮 | I6: 300 | J6: =SUM(N6:Y6) -> 300 | K6: =I6-J6 -> 0 | L6: 1 | M6: =IFERROR(I6/L6,"-") -> 300 | N6: 300 | Z6: *
B7: =ROW(A7)-4 -> 3 | C7: 日本総研 | D7: キャリア入社者課題分析 | E7: ="0"&B7&"_"&C7&"_"&D7 -> 03_日本総研_キャリア入社者課題分析 | F7: 人材育成 | G7: 成立 | H7: 啓亮 | I7: 600 | J7: =SUM(N7:Y7) -> 600 | K7: =I7-J7 -> 0 | L7: 1 | M7: =IFERROR(I7/L7,"-") -> 600 | N7: 600 | Z7: *
B8: =ROW(A8)-4 -> 4 | C8: 田島ルーフィング | D8: 推せる職場診断 | E8: ="0"&B8&"_"&C8&"_"&D8 -> 04_田島ルーフィング_推せる職場診断 | F8: 組織開発 | G8: D | H8: 啓亮 | J8: =SUM(N8:Y8) -> 0 | K8: =I8-J8 -> 0 | M8: =IFERROR(I8/L8,"-") -> - | Z8: *
B9: =ROW(A9)-4 -> 5 | C9: YAMAGATA | D9: 新事業立ち上げ支援 | E9: ="0"&B9&"_"&C9&"_"&D9 -> 05_YAMAGATA_新事業立ち上げ支援 | F9: その他 | G9: 成立 | H9: 丸田 | I9: 14500 | J9: =SUM(N9:Y9) -> 14500 | K9: =I9-J9 -> 0 | L9: 4 | M9: =IFERROR(I9/L9,"-") -> 3625 | N9: 3700 | O9: 3600 | P9: 3600 | Q9: 3600 | Z9: *
B10: =ROW(A10)-4 -> 6 | C10: 豊田通商 | D10: 人事KPI | E10: ="0"&B10&"_"&C10&"_"&D10 -> 06_豊田通商_人事KPI | F10: その他 | G10: 失注 | H10: 波多野 | I10: 6000 | J10: =SUM(N10:Y10) -> 6000 | K10: =I10-J10 -> 0 | L10: 3 | M10: =IFERROR(I10/L10,"-") -> 2000 | N10: 2000 | O10: 2000 | P10: 2000 | Z10: *
B11: =ROW(A11)-4 -> 7 | C11: 豊田通商 | D11: メタルプラス | E11: ="0"&B11&"_"&C11&"_"&D11 -> 07_豊田通商_メタルプラス | F11: その他 | G11: 成立 | H11: 波多野 | I11: 6750 | J11: =SUM(N11:Y11) -> 6750 | K11: =I11-J11 -> 0 | L11: 3 | M11: =IFERROR(I11/L11,"-") -> 2250 | P11: 2250 | Q11: 2250 | R11: 2250 | Z11: *
B12: =ROW(A12)-4 -> 8 | C12: OKI | D12: 人材面を主とした組織診断 | E12: ="0"&B12&"_"&C12&"_"&D12 -> 08_OKI_人材面を主とした組織診断 | F12: その他 | G12: 成立 | H12: 芹澤 | I12: 4000 | J12: =SUM(N12:Y12) -> 4000 | K12: =I12-J12 -> 0 | L12: 3.5 | M12: =IFERROR(I12/L12,"-") -> 1142.8571 | N12: 2000 | O12: 2000 | Z12: *
B13: =ROW(A13)-4 -> 9 | C13: 宮﨑製鋼 | D13: エンゲージメントサーベイ | E13: ="0"&B13&"_"&C13&"_"&D13 -> 09_宮﨑製鋼_エンゲージメントサーベイ | F13: その他 | G13: 成立 | H13: 芹澤 | I13: 500 | J13: =SUM(N13:Y13) -> 500 | K13: =I13-J13 -> 0 | L13: 3 | M13: =IFERROR(I13/L13,"-") -> 166.66667 | N13: 140 | O13: 360 | Z13: *
B14: =ROW(A14)-4 -> 10 | C14: オムロンエキスパートエンジニアリング | D14: データ分析 | E14: =B14&"_"&C14&"_"&D14 -> 10_オムロンエキスパートエンジニアリング_データ分析 | F14: その他 | G14: A | H14: 芹澤 | I14: 2000 | J14: =SUM(N14:Y14) -> 2000 | K14: =I14-J14 -> 0 | L14: 3 | M14: =IFERROR(I14/L14,"-") -> 666.66667 | O14: 500 | P14: 500 | Q14: 1000 | Z14: *
B15: =ROW(A15)-4 -> 11 | C15: MSプライマリー | D15: エンゲージメントサーベイ | E15: =B15&"_"&C15&"_"&D15 -> 11_MSプライマリー_エンゲージメントサーベイ | F15: その他 | G15: A | H15: 芹澤 | I15: 7000 | J15: =SUM(N15:Y15) -> 7000 | K15: =I15-J15 -> 0 | L15: 4 | M15: =IFERROR(I15/L15,"-") -> 1750 | N15: 2000 | O15: 1500 | P15: 1500 | Q15: 2000 | Z15: *
B16: =ROW(A16)-4 -> 12 | C16: アートプレスト | D16: 2025年上期人事施策実行支援 | E16: =B16&"_"&C16&"_"&D16 -> 12_アートプレスト_2025年上期人事施策実行支援 | F16: その他 | G16: 成立 | H16: 友祐 | I16: 6700 | J16: =SUM(N16:Y16) -> 6700 | K16: =I16-J16 -> 0 | L16: 1 | M16: =IFERROR(I16/L16,"-") -> 6700 | N16: 6700 | Z16: *
B17: =ROW(A17)-4 -> 13 | C17: アートプレスト | D17: 2025年下期人事施策実行支援 | E17: =B17&"_"&C17&"_"&D17 -> 13_アートプレスト_2025年下期人事施策実行支援 | F17: その他 | G17: 成立 | H17: 友祐 | I17: 37900 | J17: =SUM(N17:Y17) -> 37900 | K17: =I17-J17 -> 0 | L17: 6 | M17: =IFERROR(I17/L17,"-") -> 6316.6667 | O17: 8000 | P17: 7800 | Q17: 5100 | R17: 6100 | S17: 6200 | T17: 4700 | Z17: *
B18: =ROW(A18)-4 -> 14 | C18: アートプレスト | D18: 経営層候補者向け研修実行支援 | E18: =B18&"_"&C18&"_"&D18 -> 14_アートプレスト_経営層候補者向け研修実行支援 | F18: 人材育成 | G18: 成立 | H18: 友祐 | I18: 250 | J18: =SUM(N18:Y18) -> 250 | K18: =I18-J18 -> 0 | L18: 1 | M18: =IFERROR(I18/L18,"-") -> 250 | P18: 250 | Z18: *
B19: =ROW(A19)-4 -> 15 | C19: アートプレスト | D19: 役員研修 | E19: =B19&"_"&C19&"_"&D19 -> 15_アートプレスト_役員研修 | F19: 人材育成 | G19: 成立 | H19: 友祐 | I19: 100 | J19: =SUM(N19:Y19) -> 100 | K19: =I19-J19 -> 0 | L19: 1 | M19: =IFERROR(I19/L19,"-") -> 100 | O19: 100 | Z19: *
B20: =ROW(A20)-4 -> 16 | C20: JALUX | D20: ビジネス変革Community | E20: =B20&"_"&C20&"_"&D20 -> 16_JALUX_ビジネス変革Community | F20: その他 | G20: 成立 | H20: 森田 | I20: 750 | J20: =SUM(N20:Y20) -> 750 | K20: =I20-J20 -> 0 | L20: 1 | M20: =IFERROR(I20/L20,"-") -> 750 | O20: 750 | Z20: *
B21: =ROW(A21)-4 -> 17 | C21: JALUX | D21: 業務効率化 | E21: =B21&"_"&C21&"_"&D21 -> 17_JALUX_業務効率化 | F21: その他 | G21: 成立 | H21: 森田 | I21: 920 | J21: =SUM(N21:Y21) -> 920 | K21: =I21-J21 -> 0 | L21: 2 | M21: =IFERROR(I21/L21,"-") -> 460 | N21: 480 | O21: 440 | Z21: *
B22: =ROW(A22)-4 -> 18 | C22: パラマウントベッド | D22: 管理職WS＆部門幹部ディスカッション | E22: =B22&"_"&C22&"_"&D22 -> 18_パラマウントベッド_管理職WS＆部門幹部ディスカッション | F22: その他 | G22: 成立 | H22: 丸田 | I22: 4470 | J22: =SUM(N22:Y22) -> 2681 | K22: =I22-J22 -> 1789 | L22: 4 | M22: =IFERROR(I22/L22,"-") -> 1117.5 | O22: 1881 | Q22: 800 | Z22: *
B23: =ROW(A23)-4 -> 19 | C23: asics | D23: HRBP支援 | E23: =B23&"_"&C23&"_"&D23 -> 19_asics_HRBP支援 | F23: 組織開発 | G23: 成立 | H23: 森田 | I23: 400 | J23: =SUM(N23:Y23) -> 400 | K23: =I23-J23 -> 0 | L23: 1 | M23: =IFERROR(I23/L23,"-") -> 400 | N23: 400 | Z23: *
B24: =ROW(A24)-4 -> 20 | C24: コメダ | D24: FC対応力向上 | E24: =B24&"_"&C24&"_"&D24 -> 20_コメダ_FC対応力向上 | F24: 人材育成 | G24: 成立 | H24: 森田 | I24: 2000 | J24: =SUM(N24:Y24) -> 2000 | K24: =I24-J24 -> 0 | L24: 3 | M24: =IFERROR(I24/L24,"-") -> 666.66667 | N24: 600 | O24: 600 | P24: 800 | Z24: *
B25: =ROW(A25)-4 -> 21 | C25: ローソンエンタテインメント | D25: 人事制度・育成概要設計 | E25: =B25&"_"&C25&"_"&D25 -> 21_ローソンエンタテインメント_人事制度・育成概要設計 | F25: その他 | G25: 成立 | H25: 小川 | I25: 12300 | J25: =SUM(N25:Y25) -> 12300 | K25: =I25-J25 -> 0 | L25: 6 | M25: =IFERROR(I25/L25,"-") -> 2050 | N25: 2050 | O25: 2050 | P25: 2050 | Q25: 2050 | R25: 2050 | S25: 2050 | Z25: *
B26: =ROW(A26)-4 -> 22 | C26: オーネスト | D26: MVV浸透支援Phase3 | E26: =B26&"_"&C26&"_"&D26 -> 22_オーネスト_MVV浸透支援Phase3 | F26: 組織開発 | G26: 成立 | H26: 森田 | I26: 1300 | J26: =SUM(N26:Y26) -> 1300 | K26: =I26-J26 -> 0 | L26: 1 | M26: =IFERROR(I26/L26,"-") -> 1300 | N26: 1300 | Z26: *
B27: =ROW(A27)-4 -> 23 | C27: BeeX | D27: Aプロジェクト | E27: =B27&"_"&C27&"_"&D27 -> 23_BeeX_Aプロジェクト | F27: 人材育成 | G27: 失注 | H27: 啓亮 | I27: 4500 | J27: =SUM(N27:Y27) -> 4500 | K27: =I27-J27 -> 0 | L27: 3 | M27: =IFERROR(I27/L27,"-") -> 1500 | O27: 1500 | P27: 1500 | Q27: 1500 | Z27: *
B28: =ROW(A28)-4 -> 24 | C28: ひらまつ | D28: 育成体系設計 | E28: =B28&"_"&C28&"_"&D28 -> 24_ひらまつ_育成体系設計 | F28: 人材育成 | G28: A | H28: 啓亮 | I28: 3600 | J28: =SUM(N28:Y28) -> 3600 | K28: =I28-J28 -> 0 | L28: 3 | M28: =IFERROR(I28/L28,"-") -> 1200 | R28: 1200 | S28: 1200 | T28: 1200 | Z28: *
B29: =ROW(A29)-4 -> 25 | C29: パラマウントベッド | D29: 女性社員交流会 企画支援 | E29: =B29&"_"&C29&"_"&D29 -> 25_パラマウントベッド_女性社員交流会 企画支援 | F29: その他 | G29: 成立 | H29: 丸田 | I29: 500 | J29: =SUM(N29:Y29) -> 500 | K29: =I29-J29 -> 0 | L29: 1 | M29: =IFERROR(I29/L29,"-") -> 500 | N29: 500 | Z29: *
B30: =ROW(A30)-4 -> 26 | C30: 西武HD | D30: オンボーディング・OJT企画 | E30: =B30&"_"&C30&"_"&D30 -> 26_西武HD_オンボーディング・OJT企画 | F30: その他 | G30: 失注 | H30: 小川 | I30: 2000 | J30: =SUM(N30:Y30) -> 2000 | K30: =I30-J30 -> 0 | L30: 3 | M30: =IFERROR(I30/L30,"-") -> 666.66667 | O30: 1000 | P30: 1000 | Z30: *
B31: =ROW(A31)-4 -> 27 | C31: PHCホールディングス | D31: オンボ・採用支援（中長期含） | E31: =B31&"_"&C31&"_"&D31 -> 27_PHCホールディングス_オンボ・採用支援（中長期含） | F31: その他 | G31: C | H31: 小川 | I31: 6000 | J31: =SUM(N31:Y31) -> 6000 | K31: =I31-J31 -> 0 | L31: 3 | M31: =IFERROR(I31/L31,"-") -> 2000 | O31: 2000 | P31: 2000 | Q31: 2000 | Z31: *
B32: =ROW(A32)-4 -> 28 | C32: 安田工業 | D32: 人事戦略検討 | E32: =B32&"_"&C32&"_"&D32 -> 28_安田工業_人事戦略検討 | F32: その他 | G32: D | H32: 小川 | I32: 12000 | J32: =SUM(N32:Y32) -> 12000 | K32: =I32-J32 -> 0 | L32: 6 | M32: =IFERROR(I32/L32,"-") -> 2000 | O32: 2000 | P32: 2000 | Q32: 2000 | R32: 2000 | S32: 2000 | T32: 2000 | Z32: *
B33: =ROW(A33)-4 -> 29 | C33: パラマウントベッド | D33: 女性社員交流会 キックオフイベント支援 | E33: =B33&"_"&C33&"_"&D33 -> 29_パラマウントベッド_女性社員交流会 キックオフイベント支援 | F33: その他 | G33: 成立 | H33: 丸田 | I33: 700 | J33: =SUM(N33:Y33) -> 280 | K33: =I33-J33 -> 420 | L33: 1 | M33: =IFERROR(I33/L33,"-") -> 700 | O33: 280 | Z33: *
B34: =ROW(A34)-4 -> 30 | C34: パラマウントベッド | D34: 女性社員交流会_女性キャリア研修 | E34: =B34&"_"&C34&"_"&D34 -> 30_パラマウントベッド_女性社員交流会_女性キャリア研修 | F34: その他 | G34: 成立 | H34: 丸田 | I34: 1164 | J34: =SUM(N34:Y34) -> 232 | K34: =I34-J34 -> 932 | L34: 2 | M34: =IFERROR(I34/L34,"-") -> 582 | Q34: 232 | Z34: *
B35: 31 | C35: パーソルクロステクノロジー | D35: 社内広報業務支援 | E35: =B35&"_"&C35&"_"&D35 -> 31_パーソルクロステクノロジー_社内広報業務支援 | F35: 組織開発 | G35: 成立 | H35: 丸田 | I35: 2250 | J35: =SUM(N35:Y35) -> 2250 | K35: =I35-J35 -> 0 | L35: 3 | M35: =IFERROR(I35/L35,"-") -> 750 | O35: 750 | P35: 750 | Q35: 750 | Z35: *
B36: 32 | C36: ソフトバンク | D36: スキルマップ作成 | E36: =B36&"_"&C36&"_"&D36 -> 32_ソフトバンク_スキルマップ作成 | F36: 人材育成 | G36: 失注 | H36: 啓亮 | I36: 4500 | J36: =SUM(N36:Y36) -> 4500 | K36: =I36-J36 -> 0 | L36: 3 | M36: =IFERROR(I36/L36,"-") -> 1500 | R36: 1500 | S36: 1500 | T36: 1500 | Z36: *
B37: 33 | C37: 田島ルーフィング | D37: 推せる職場診断 | E37: =B37&"_"&C37&"_"&D37 -> 33_田島ルーフィング_推せる職場診断 | F37: 組織開発 | G37: 成立 | H37: 啓亮 | I37: 3100 | J37: 3100 | K37: =I37-J37 -> 0 | L37: 5 | M37: =IFERROR(I37/L37,"-") -> 620 | O37: 1000 | P37: 1000 | Q37: 300 | R37: 300 | S37: 500 | Z37: *
B38: 34 | C38: インテージテクノスフィア | D38: 経営層向けレポート作成支援_Phase1 | E38: =B38&"_"&C38&"_"&D38 -> 34_インテージテクノスフィア_経営層向けレポート作成支援_Phase1 | F38: その他 | G38: 失注 | H38: 弓本 | I38: 900 | J38: =SUM(N38:Y38) -> 900 | K38: =I38-J38 -> 0 | L38: 1 | M38: =IFERROR(I38/L38,"-") -> 900 | O38: 900 | Z38: *
B39: 35 | C39: ソフトバンク | D39: スキルマップ作成 | E39: =B39&"_"&C39&"_"&D39 -> 35_ソフトバンク_スキルマップ作成 | F39: 人材育成 | G39: 失注 | H39: 啓亮 | I39: 15000 | J39: =SUM(N39:Y39) -> 15000 | K39: =I39-J39 -> 0 | L39: 5 | M39: =IFERROR(I39/L39,"-") -> 3000 | O39: 1000 | P39: 2500 | Q39: 2500 | R39: 3000 | S39: 3000 | T39: 3000 | Z39: *
B40: 36 | C40: パラドックス | D40: 森の歩き方実装支援（10月以降） | E40: =B40&"_"&C40&"_"&D40 -> 36_パラドックス_森の歩き方実装支援（10月以降） | F40: 人材育成 | G40: 成立 | H40: 啓亮 | I40: 1650 | J40: =SUM(N40:Y40) -> 1650 | K40: =I40-J40 -> 0 | L40: 6 | M40: =IFERROR(I40/L40,"-") -> 275 | O40: 150 | P40: 300 | Q40: 300 | R40: 300 | S40: 300 | T40: 300 | Z40: *
B41: 37 | C41: リンクシェア・ジャパン | D41: 早期戦力化へのオンボーディングプログラム設計 | E41: =B41&"_"&C41&"_"&D41 -> 37_リンクシェア・ジャパン_早期戦力化へのオンボーディングプログラム設計 | F41: 人材育成 | G41: 失注 | H41: 啓亮 | I41: 5000 | J41: =SUM(N41:Y41) -> 5000 | K41: =I41-J41 -> 0 | L41: 3 | M41: =IFERROR(I41/L41,"-") -> 1666.6667 | U41: 1000 | V41: 2000 | W41: 2000 | Z41: *
B42: 38 | C42: 本田技術研究所 | D42: 女性研究職社員の定着へ向けた課題分析・施策立案 | E42: =B42&"_"&C42&"_"&D42 -> 38_本田技術研究所_女性研究職社員の定着へ向けた課題分析・施策立案 | F42: 組織開発 | G42: 失注 | H42: 啓亮 | I42: 3000 | J42: =SUM(N42:Y42) -> 3000 | K42: =I42-J42 -> 0 | L42: 3 | M42: =IFERROR(I42/L42,"-") -> 1000 | P42: 1000 | Q42: 1000 | R42: 1000 | Z42: *
B43: 39 | C43: asics | D43: 製造現場の業務効率化 | E43: =B43&"_"&C43&"_"&D43 -> 39_asics_製造現場の業務効率化 | F43: その他 | G43: D | H43: 森田 | J43: =SUM(N43:Y43) -> 0 | K43: =I43-J43 -> 0 | M43: =IFERROR(I43/L43,"-") -> - | Z43: *
B44: 40 | C44: 三井情報 | D44: 人材マネジメントアドバイザリー | E44: =B44&"_"&C44&"_"&D44 -> 40_三井情報_人材マネジメントアドバイザリー | F44: 人材育成 | G44: 成立 | H44: 啓亮 | I44: 3500 | J44: =SUM(N44:Y44) -> 3500 | K44: =I44-J44 -> 0 | L44: 5 | M44: =IFERROR(I44/L44,"-") -> 700 | P44: 700 | Q44: 700 | R44: 700 | S44: 700 | T44: 700 | Z44: *
B45: 41 | C45: トヨタコネクティッド | D45: オンボーディング施策設計 | E45: =B45&"_"&C45&"_"&D45 -> 41_トヨタコネクティッド_オンボーディング施策設計 | F45: 組織開発 | G45: A | H45: 啓亮 | I45: 6000 | J45: =SUM(N45:Y45) -> 6000 | K45: =I45-J45 -> 0 | L45: 3 | M45: =IFERROR(I45/L45,"-") -> 2000 | R45: 2000 | S45: 2000 | T45: 2000 | Z45: *
B46: 42 | C46: オーネスト | D46: マネジメント力定義 | E46: =B46&"_"&C46&"_"&D46 -> 42_オーネスト_マネジメント力定義 | F46: 組織開発 | G46: D | H46: 森田 | I46: 4500 | J46: =SUM(N46:Y46) -> 4500 | K46: =I46-J46 -> 0 | L46: 3 | M46: =IFERROR(I46/L46,"-") -> 1500 | U46: 1500 | V46: 1500 | W46: 1500 | Z46: *
B47: 43 | C47: 一条工務店 | D47: 育成体系 | E47: =B47&"_"&C47&"_"&D47 -> 43_一条工務店_育成体系 | F47: 人材育成 | G47: 失注 | H47: 啓亮 | I47: 4000 | J47: =SUM(N47:Y47) -> 4000 | K47: =I47-J47 -> 0 | L47: 2 | M47: =IFERROR(I47/L47,"-") -> 2000 | Q47: 2000 | R47: 2000 | Z47: *
B48: 44 | C48: YAMAGATA | D48: PoC営業支援 | E48: =B48&"_"&C48&"_"&D48 -> 44_YAMAGATA_PoC営業支援 | F48: その他 | G48: D | H48: 波多野 | I48: 1200 | J48: =SUM(N48:Y48) -> 0 | K48: =I48-J48 -> 1200 | M48: =IFERROR(I48/L48,"-") -> - | Z48: *
B49: 45 | C49: asics | D49: 役員合宿 | E49: =B49&"_"&C49&"_"&D49 -> 45_asics_役員合宿 | F49: 組織開発 | G49: D | H49: 森田 | I49: 2000 | J49: =SUM(N49:Y49) -> 2000 | K49: =I49-J49 -> 0 | L49: 1 | M49: =IFERROR(I49/L49,"-") -> 2000 | S49: 2000 | Z49: *
B50: 46 | C50: オーネスト | D50: 人事・評価制度見直し | E50: =B50&"_"&C50&"_"&D50 -> 46_オーネスト_人事・評価制度見直し | F50: 人材育成 | G50: D | H50: 小川 | I50: 6000 | J50: =SUM(N50:Y50) -> 6000 | K50: =I50-J50 -> 0 | L50: 5 | M50: =IFERROR(I50/L50,"-") -> 1200 | V50: 1500 | W50: 1500 | X50: 1500 | Y50: 1500 | Z50: *
B51: 47 | C51: 朝日生命 | D51: 社内大学設立への現状調査 | E51: =B51&"_"&C51&"_"&D51 -> 47_朝日生命_社内大学設立への現状調査 | F51: 人材育成 | G51: A | H51: 啓亮 | I51: 3200 | J51: =SUM(N51:Y51) -> 3200 | K51: =I51-J51 -> 0 | L51: 1.5 | M51: =IFERROR(I51/L51,"-") -> 2133.3333 | S51: 1200 | T51: 2000 | Z51: *
B52: 48 | C52: アートプレスト | D52: 評価者研修（期末評価） | E52: =B52&"_"&C52&"_"&D52 -> 48_アートプレスト_評価者研修（期末評価） | F52: 人材育成 | G52: 成立 | H52: 友祐 | I52: 100 | J52: =SUM(N52:Y52) -> 100 | K52: =I52-J52 -> 0 | L52: 1 | M52: =IFERROR(I52/L52,"-") -> 100 | S52: 100 | Z52: *
B53: 49 | C53: アートプレスト | D53: 2026年上期人事施策実行支援 | E53: =B53&"_"&C53&"_"&D53 -> 49_アートプレスト_2026年上期人事施策実行支援 | F53: その他 | G53: D | H53: 友祐 | I53: 25000 | J53: =SUM(N53:Y53) -> 25000 | K53: =I53-J53 -> 0 | L53: 5 | M53: =IFERROR(I53/L53,"-") -> 5000 | U53: 5000 | V53: 5000 | W53: 5000 | X53: 5000 | Y53: 5000 | Z53: *
B54: 50 | C54: 宮﨑精鋼 | D54: 部課長FB | E54: =B54&"_"&C54&"_"&D54 -> 50_宮﨑精鋼_部課長FB | F54: HRアナリティクス | G54: 成立 | H54: 芹澤 | I54: 100 | J54: =SUM(N54:Y54) -> 100 | L54: 0.5 | M54: =IFERROR(I54/L54,"-") -> 200 | Q54: 100 | Z54: *
B55: 51 | C55: コメダ | D55: コメダ大学目的・スコープ再設計 | E55: =B55&"_"&C55&"_"&D55 -> 51_コメダ_コメダ大学目的・スコープ再設計 | F55: 人材育成 | G55: D | H55: 啓亮 | I55: 3000 | J55: =SUM(N55:Y55) -> 2000 | L55: 1 | M55: =IFERROR(I55/L55,"-") -> 3000 | U55: 2000 | Z55: *
B56: 52 | C56: OKIクロステック | D56: エンゲージメント向上支援 | E56: =B56&"_"&C56&"_"&D56 -> 52_OKIクロステック_エンゲージメント向上支援 | F56: HRアナリティクス | G56: 失注 | H56: 芹澤 | I56: 13000 | J56: =SUM(N56:Y56) -> 13000 | L56: 5 | M56: =IFERROR(I56/L56,"-") -> 2600 | U56: 2600 | V56: 2600 | W56: 2600 | X56: 2600 | Y56: 2600 | Z56: *
B57: =ROW(A57)-4 -> 53 | C57: YAMAGATA | D57: S1および制作部門変革支援（フェーズ4） | E57: ="0"&B57&"_"&C57&"_"&D57 -> 053_YAMAGATA_S1および制作部門変革支援（フェーズ4） | F57: その他 | G57: 成立 | H57: 丸田 | I57: 33000 | J57: =SUM(N57:Y57) -> 33000 | L57: 6 | M57: =IFERROR(I57/L57,"-") -> 5500 | S57: 6250 | T57: 5350 | U57: 5350 | V57: 5350 | W57: 5350 | X57: 5350 | Z57: *
B58: 54 | C58: トーシンパートナーズホールディングス | D58: 育成体系設計 | E58: =B58&"_"&C58&"_"&D58 -> 54_トーシンパートナーズホールディングス_育成体系設計 | F58: 人材育成 | G58: 失注 | H58: 波多野 | I58: 5500 | J58: =SUM(N58:Y58) -> 5500 | L58: 2 | M58: =IFERROR(I58/L58,"-") -> 2750 | R58: 1500 | S58: 2000 | T58: 2000 | Z58: *
B59: 55 | C59: OKI | D59: 採用＆オンボーディング支援_Ph.1基礎調査 | E59: =B59&"_"&C59&"_"&D59 -> 55_OKI_採用＆オンボーディング支援_Ph.1基礎調査 | F59: その他 | G59: B | H59: 芹澤 | I59: 2000 | J59: =SUM(N59:Y59) -> 2000 | L59: 1 | M59: =IFERROR(I59/L59,"-") -> 2000 | T59: 2000 | Z59: *
B60: 56 | C60: オニカナ | D60: 採用支援 | E60: =B60&"_"&C60&"_"&D60 -> 56_オニカナ_採用支援 | F60: その他 | G60: C | H60: 波多野 | I60: 3000 | J60: =SUM(N60:Y60) -> 3000 | L60: 2 | M60: =IFERROR(I60/L60,"-") -> 1500 | T60: 1500 | U60: 1500 | Z60: *
B61: 57 | C61: トーシンパートナーズホールディングス | D61: マネージャークラスのスキル診断・研修伴走 | E61: =B61&"_"&C61&"_"&D61 -> 57_トーシンパートナーズホールディングス_マネージャークラスのスキル診断・研修伴走 | F61: 人材育成 | G61: C | H61: 波多野 | I61: 8000 | J61: =SUM(N61:Y61) -> 8000 | L61: 4 | M61: =IFERROR(I61/L61,"-") -> 2000 | V61: 2000 | W61: 2000 | X61: 2000 | Y61: 2000 | Z61: *
B62: 58 | C62: パラマウントベッド | D62: DEI事務局 伴走支援 フェーズ1 | E62: =B62&"_"&C62&"_"&D62 -> 58_パラマウントベッド_DEI事務局 伴走支援 フェーズ1 | F62: その他 | G62: C | H62: 丸田 | I62: 5400 | J62: =SUM(N62:Y62) -> 5400 | L62: 3 | M62: =IFERROR(I62/L62,"-") -> 1800 | U62: 1800 | V62: 1800 | W62: 1800 | Z62: *
B63: 59 | C63: パラマウントベッド | D63: 管理職向け研修（コンサル分のみ） | E63: =B63&"_"&C63&"_"&D63 -> 59_パラマウントベッド_管理職向け研修（コンサル分のみ） | F63: 人材育成 | G63: C | H63: 丸田 | I63: 600 | J63: =SUM(N63:Y63) -> 400 | L63: 5 | M63: =IFERROR(I63/L63,"-") -> 120 | V63: 400 | Z63: *
B64: 60 | C64: 三井情報 | D64: 人材マネジメントアドバイザリーPhase2 | E64: =B64&"_"&C64&"_"&D64 -> 60_三井情報_人材マネジメントアドバイザリーPhase2 | F64: 人材育成 | G64: A | H64: 啓亮 | I64: 3500 | J64: =SUM(N64:Y64) -> 3500 | L64: 5 | M64: =IFERROR(I64/L64,"-") -> 700 | U64: 700 | V64: 700 | W64: 700 | X64: 700 | Y64: 700 | Z64: *
B65: 61 | C65: Beyonge | D65: AP様向け新卒採用支援販売手数料 | E65: =B65&"_"&C65&"_"&D65 -> 61_Beyonge_AP様向け新卒採用支援販売手数料 | F65: その他 | G65: 成立 | H65: 友祐 | I65: 600 | J65: =SUM(N65:Y65) -> 600 | L65: 6 | M65: =IFERROR(I65/L65,"-") -> 100 | S65: 100 | T65: 100 | U65: 100 | V65: 100 | W65: 100 | X65: 100 | Z65: *
B66: 62 | C66: 防衛省統合幕僚監部 | D66: エンゲージメントサーベイ | E66: =B66&"_"&C66&"_"&D66 -> 62_防衛省統合幕僚監部_エンゲージメントサーベイ | F66: HRアナリティクス | G66: C | H66: 芹澤 | I66: 4000 | M66: =IFERROR(I66/L66,"-") -> - | Z66: *
B67: 63 | C67: 三井情報 | D67: キャリア支援ガイドライン設計 | E67: =B67&"_"&C67&"_"&D67 -> 63_三井情報_キャリア支援ガイドライン設計 | F67: 人材育成 | G67: A | H67: 啓亮 | I67: 3000 | L67: 2 | M67: =IFERROR(I67/L67,"-") -> 1500 | U67: 1500 | V67: 1500 | Z67: *
B68: 64 | C68: 日立ハイテク | D68: 人事データ分析 | E68: =B68&"_"&C68&"_"&D68 -> 64_日立ハイテク_人事データ分析 | F68: HRアナリティクス | G68: A | H68: 芹澤 | I68: 1500 | L68: 1 | M68: =IFERROR(I68/L68,"-") -> 1500 | S68: 500 | T68: 1000 | Z68: *
B69: 65 | C69: OKI | D69: 採用＆オンボーディング支援_Ph.2 | E69: =B69&"_"&C69&"_"&D69 -> 65_OKI_採用＆オンボーディング支援_Ph.2 | F69: その他 | G69: B | H69: 芹澤 | I69: 13000 | M69: =IFERROR(I69/L69,"-") -> - | U69: 2160 | V69: 2160 | W69: 2200 | X69: 2160 | Y69: 2160 | Z69: *
B70: 66 | C70: ローソンエンタテインメント | D70: 戦略人事室立ち上げ支援 | E70: =B70&"_"&C70&"_"&D70 -> 66_ローソンエンタテインメント_戦略人事室立ち上げ支援 | F70: その他 | G70: D | H70: 芹澤 | I70: 6000 | L70: 3.5 | M70: =IFERROR(I70/L70,"-") -> 1714.2857 | T70: 1700 | U70: 1700 | V70: 1700 | W70: 1700 | Z70: *
B71: 67 | C71: ひらまつ | D71: 育成ガイドライン設計支援Phase2 | E71: =B71&"_"&C71&"_"&D71 -> 67_ひらまつ_育成ガイドライン設計支援Phase2 | F71: 人材育成 | G71: D | H71: 啓亮 | I71: 8000 | L71: 4 | M71: =IFERROR(I71/L71,"-") -> 2000 | V71: 2000 | W71: 2000 | X71: 2000 | Y71: 2000 | Z71: *
E72: =B72&"_"&C72&"_"&D72 -> __ | M72: =IFERROR(I72/L72,"-") -> - | Z72: *
E73: =B73&"_"&C73&"_"&D73 -> __ | M73: =IFERROR(I73/L73,"-") -> - | Z73: *
E74: =B74&"_"&C74&"_"&D74 -> __ | M74: =IFERROR(I74/L74,"-") -> - | Z74: *
E75: =B75&"_"&C75&"_"&D75 -> __ | M75: =IFERROR(I75/L75,"-") -> - | Z75: *
E76: =B76&"_"&C76&"_"&D76 -> __ | M76: =IFERROR(I76/L76,"-") -> - | Z76: *
E77: =B77&"_"&C77&"_"&D77 -> __ | M77: =IFERROR(I77/L77,"-") -> - | Z77: *
E78: =B78&"_"&C78&"_"&D78 -> __ | M78: =IFERROR(I78/L78,"-") -> - | Z78: *
E79: =B79&"_"&C79&"_"&D79 -> __ | M79: =IFERROR(I79/L79,"-") -> - | Z79: *
E80: =B80&"_"&C80&"_"&D80 -> __ | M80: =IFERROR(I80/L80,"-") -> - | Z80: *
E81: =B81&"_"&C81&"_"&D81 -> __ | M81: =IFERROR(I81/L81,"-") -> - | Z81: *
E82: =B82&"_"&C82&"_"&D82 -> __ | M82: =IFERROR(I82/L82,"-") -> - | Z82: *
E83: =B83&"_"&C83&"_"&D83 -> __ | M83: =IFERROR(I83/L83,"-") -> - | Z83: *
... E102: =B102&"_"&C102&"_"&D102 -> __ | M102: =IFERROR(I102/L102,"-") -> - | Z102: *
B103: * | C103: * | D103: * | E103: * | F103: * | G103: * | H103: * | I103: * | J103: * | K103: * | L103: * | M103: * | N103: * | O103: * | P103: * | Q103: * | R103: * | S103: * | T103: * | U103: * | V103: * | W103: * | X103: * | Y103: * | Z103: *

Sheet 【入力用③】案件ごとCH（D案件以上）
A1: ※黄色セルは手動入力
N2: ※BPなどは「外部」と入力（【管理用】BRシートの担当名称）
C3: ◆PJ基本情報（全体） | H3: ◆PJ売上情報（全体） | J3: ※自動 | K3: ※0に近づける | O3: ◆月別CH_個人別 | AA3: ◆月別売上_個人別（千円）
B4: No | C4: 案件No | D4: クライアント名 | E4: 案件名 | F4: PIVOT用_PJ管理 | G4: 案件種類 | H4: 確度 | I4: PJ全体売上 （千円） ※②シートより | J4: 月別売上合計 （千円） | K4: 自動計算との差分 （千円） | L4: 期間 (月) | M4: 月単価 (千円) | N4: 担当 | O4: 9月 | P4: 10月 | Q4: 11月 | R4: 12月 | S4: 1月 | T4: 2月 | U4: 3月 | V4: 4月 | W4: 5月 | X4: 6月 | Y4: 7月 | Z4: 8月 | AA4: 9月 | AB4: 10月 | AC4: 11月 | AD4: 12月 | AE4: 1月 | AF4: 2月 | AG4: 3月 | AH4: 4月 | AI4: 5月 | AJ4: 6月 | AK4: 7月 | AL4: 8月 | AM4: 合計 | AN4: *
B5: =ROW(A5)-4 -> 1 | C5: 1 | D5: =IFERROR(VLOOKUP($C5,'【入力用②】案件ごと売上（D案件以上）'!$B$4:$Y$1048576,2,FALSE),"-") -> 伊藤ハム米久ホールディングス | E5: =IFERROR(VLOOKUP($C5,'【入力用②】案件ごと売上（D案件以上）'!$B$4:$Y$1048576,3,FALSE),"-") -> エンゲージメント向上PJT | F5: =IFERROR(VLOOKUP($C5,'【入力用②】案件ごと売上（D案件以上）'!$B$4:$Y$1048576,4,FALSE),"-") -> 01_伊藤ハム米久ホールディングス_エンゲージメント向上PJT | G5: =IFERROR(VLOOKUP($C5,'【入力用②】案件ごと売上（D案件以上）'!$B$4:$Y$1048576,5,FALSE),"-") -> 組織開発 | H5: =IFERROR(VLOOKUP($C5,'【入力用②】案件ごと売上（D案件以上）'!$B$4:$Y$1048576,6,FALSE),"-") -> 成立 | I5: =IFERROR(VLOOKUP($C5,'【入力用②】案件ごと売上（D案件以上）'!$B$4:$Y$1048576,8,FALSE),"-") -> 550 | J5: =SUMIF($C$5:$C$1048576,C5,$AM$5:$AM$1048576) -> 549.8 | K5: =IFERROR(I5-J5,"-") -> 0.2 | L5: =IFERROR(VLOOKUP($C5,'【入力用②】案件ごと売上（D案件以上）'!$B$4:$Y$1048576,11,FALSE),"-") -> 1 | M5: =IFERROR(I5/L5,"-") -> 550 | N5: 啓亮 | O5: 0.196 | AA5: =IFERROR(VLOOKUP($N5,【管理用】BR_260204!$B$3:$D$20,3,FALSE)*O5,"-") -> 499.8 | AB5: =IFERROR(VLOOKUP($N5,【管理用】BR_260204!$B$3:$D$20,3,FALSE)*P5,"-") -> 0 | AC5: =IFERROR(VLOOKUP($N5,【管理用】BR_260204!$B$3:$D$20,3,FALSE)*Q5,"-") -> 0 | AD5: =IFERROR(VLOOKUP($N5,【管理用】BR_260204!$B$3:$D$20,3,FALSE)*R5,"-") -> 0 | AE5: =IFERROR(VLOOKUP($N5,【管理用】BR_260204!$B$3:$D$20,3,FALSE)*S5,"-") -> 0 | AF5: =IFERROR(VLOOKUP($N5,【管理用】BR_260204!$B$3:$D$20,3,FALSE)*T5,"-") -> 0 | AG5: =IFERROR(VLOOKUP($N5,【管理用】BR_260204!$B$3:$D$20,3,FALSE)*U5,"-") -> 0 | AH5: =IFERROR(VLOOKUP($N5,【管理用】BR_260204!$B$3:$D$20,3,FALSE)*V5,"-") -> 0 | ... AL5: =IFERROR(VLOOKUP($N5,【管理用】BR_260204!$B$3:$D$20,3,FALSE)*Z5,"-") -> 0 | AM5: =SUM(AA5:AL5) -> 499.8 | AN5: *
B6: =ROW(A6)-4 -> 2 | C6: 1 | D6: =IFERROR(VLOOKUP($C6,'【入力用②】案件ごと売上（D案件以上）'!$B$4:$Y$1048576,2,FALSE),"-") -> 伊藤ハム米久ホールディングス | E6: =IFERROR(VLOOKUP($C6,'【入力用②】案件ごと売上（D案件以上）'!$B$4:$Y$1048576,3,FALSE),"-") -> エンゲージメント向上PJT | F6: =IFERROR(VLOOKUP($C6,'【入力用②】案件ごと売上（D案件以上）'!$B$4:$Y$1048576,4,FALSE),"-") -> 01_伊藤ハム米久ホールディングス_エンゲージメント向上PJT | G6: =IFERROR(VLOOKUP($C6,'【入力用②】案件ごと売上（D案件以上）'!$B$4:$Y$1048576,5,FALSE),"-") -> 組織開発 | H6: =IFERROR(VLOOKUP($C6,'【入力用②】案件ごと売上（D案件以上）'!$B$4:$Y$1048576,6,FALSE),"-") -> 成立 | I6: =IFERROR(VLOOKUP($C6,'【入力用②】案件ごと売上（D案件以上）'!$B$4:$Y$1048576,8,FALSE),"-") -> 550 | J6: =SUMIF($C$5:$C$1048576,C6,$AM$5:$AM$1048576) -> 549.8 | K6: =IFERROR(I6-J6,"-") -> 0.2 | L6: =IFERROR(VLOOKUP($C6,'【入力用②】案件ごと売上（D案件以上）'!$B$4:$Y$1048576,11,FALSE),"-") -> 1 | M6: =IFERROR(I6/L6,"-") -> 550 | N6: 外部 | O6: 0.05 | AA6: =IFERROR(VLOOKUP($N6,【管理用】BR_260204!$B$3:$D$20,3,FALSE)*O6,"-") -> 50 | AB6: =IFERROR(VLOOKUP($N6,【管理用】BR_260204!$B$3:$D$20,3,FALSE)*P6,"-") -> 0 | AC6: =IFERROR(VLOOKUP($N6,【管理用】BR_260204!$B$3:$D$20,3,FALSE)*Q6,"-") -> 0 | AD6: =IFERROR(VLOOKUP($N6,【管理用】BR_260204!$B$3:$D$20,3,FALSE)*R6,"-") -> 0 | AE6: =IFERROR(VLOOKUP($N6,【管理用】BR_260204!$B$3:$D$20,3,FALSE)*S6,"-") -> 0 | AF6: =IFERROR(VLOOKUP($N6,【管理用】BR_260204!$B$3:$D$20,3,FALSE)*T6,"-") -> 0 | AG6: =IFERROR(VLOOKUP($N6,【管理用】BR_260204!$B$3:$D$20,3,FALSE)*U6,"-") -> 0 | AH6: =IFERROR(VLOOKUP($N6,【管理用】BR_260204!$B$3:$D$20,3,FALSE)*V6,"-") -> 0 | ... AL6: =IFERROR(VLOOKUP($N6,【管理用】BR_260204!$B$3:$D$20,3,FALSE)*Z6,"-") -> 0 | AM6: =SUM(AA6:AL6) -> 50 | AN6: *
B7: =ROW(A7)-4 -> 3 | C7: 2 | D7: =IFERROR(VLOOKUP($C7,'【入力用②】案件ごと売上（D案件以上）'!$B$4:$Y$1048576,2,FALSE),"-") -> パラドックス | E7: =IFERROR(VLOOKUP($C7,'【入力用②】案件ごと売上（D案件以上）'!$B$4:$Y$1048576,3,FALSE),"-") -> 森の歩き方実装支援 | F7: =IFERROR(VLOOKUP($C7,'【入力用②】案件ごと売上（D案件以上）'!$B$4:$Y$1048576,4,FALSE),"-") -> 02_パラドックス_森の歩き方実装支援 | G7: =IFERROR(VLOOKUP($C7,'【入力用②】案件ごと売上（D案件以上）'!$B$4:$Y$1048576,5,FALSE),"-") -> 人材育成 | H7: =IFERROR(VLOOKUP($C7,'【入力用②】案件ごと売上（D案件以上）'!$B$4:$Y$1048576,6,FALSE),"-") -> 成立 | I7: =IFERROR(VLOOKUP($C7,'【入力用②】案件ごと売上（D案件以上）'!$B$4:$Y$1048576,8,FALSE),"-") -> 300 | J7: =SUMIF($C$5:$C$1048576,C7,$AM$5:$AM$1048576) -> 300.025 | K7: =IFERROR(I7-J7,"-") -> -0.025 | L7: =IFERROR(VLOOKUP($C7,'【入力用②】案件ごと売上（D案件以上）'!$B$4:$Y$1048576,11,FALSE),"-") -> 1 | M7: =IFERROR(I7/L7,"-") -> 300 | N7: 啓亮 | O7: 0.0935 | AA7: =IFERROR(VLOOKUP($N7,【管理用】BR_260204!$B$3:$D$20,3,FALSE)*O7,"-") -> 238.425 | AB7: =IFERROR(VLOOKUP($N7,【管理用】BR_260204!$B$3:$D$20,3,FALSE)*P7,"-") -> 0 | AC7: =IFERROR(VLOOKUP($N7,【管理用】BR_260204!$B$3:$D$20,3,FALSE)*Q7,"-") -> 0 | AD7: =IFERROR(VLOOKUP($N7,【管理用】BR_260204!$B$3:$D$20,3,FALSE)*R7,"-") -> 0 | AE7: =IFERROR(VLOOKUP($N7,【管理用】BR_260204!$B$3:$D$20,3,FALSE)*S7,"-") -> 0 | AF7: =IFERROR(VLOOKUP($N7,【管理用】BR_260204!$B$3:$D$20,3,FALSE)*T7,"-") -> 0 | AG7: =IFERROR(VLOOKUP($N7,【管理用】BR_260204!$B$3:$D$20,3,FALSE)*U7,"-") -> 0 | AH7: =IFERROR(VLOOKUP($N7,【管理用】BR_260204!$B$3:$D$20,3,FALSE)*V7,"-") -> 0 | ... AL7: =IFERROR(VLOOKUP($N7,【管理用】BR_260204!$B$3:$D$20,3,FALSE)*Z7,"-") -> 0 | AM7: =SUM(AA7:AL7) -> 238.425 | AN7: *
B8: =ROW(A8)-4 -> 4 | C8: 2 | D8: =IFERROR(VLOOKUP($C8,'【入力用②】案件ごと売上（D案件以上）'!$B$4:$Y$1048576,2,FALSE),"-") -> パラドックス | E8: =IFERROR(VLOOKUP($C8,'【入力用②】案件ごと売上（D案件以上）'!$B$4:$Y$1048576,3,FALSE),"-") -> 森の歩き方実装支援 | F8: =IFERROR(VLOOKUP($C8,'【入力用②】案件ごと売上（D案件以上）'!$B$4:$Y$1048576,4,FALSE),"-") -> 02_パラドックス_森の歩き方実装支援 | G8: =IFERROR(VLOOKUP($C8,'【入力用②】案件ごと売上（D案件以上）'!$B$4:$Y$1048576,5,FALSE),"-") -> 人材育成 | H8: =IFERROR(VLOOKUP($C8,'【入力用②】案件ごと売上（D案件以上）'!$B$4:$Y$1048576,6,FALSE),"-") -> 成立 | I8: =IFERROR(VLOOKUP($C8,'【入力用②】案件ごと売上（D案件以上）'!$B$4:$Y$1048576,8,FALSE),"-") -> 300 | J8: =SUMIF($C$5:$C$1048576,C8,$AM$5:$AM$1048576) -> 300.025 | K8: =IFERROR(I8-J8,"-") -> -0.025 | L8: =IFERROR(VLOOKUP($C8,'【入力用②】案件ごと売上（D案件以上）'!$B$4:$Y$1048576,11,FALSE),"-") -> 1 | M8: =IFERROR(I8/L8,"-") -> 300 | N8: 小川 | O8: 0.01 | AA8: =IFERROR(VLOOKUP($N8,【管理用】BR_260204!$B$3:$D$20,3,FALSE)*O8,"-") -> 61.6 | AB8: =IFERROR(VLOOKUP($N8,【管理用】BR_260204!$B$3:$D$20,3,FALSE)*P8,"-") -> 0 | AC8: =IFERROR(VLOOKUP($N8,【管理用】BR_260204!$B$3:$D$20,3,FALSE)*Q8,"-") -> 0 | AD8: =IFERROR(VLOOKUP($N8,【管理用】BR_260204!$B$3:$D$20,3,FALSE)*R8,"-") -> 0 | AE8: =IFERROR(VLOOKUP($N8,【管理用】BR_260204!$B$3:$D$20,3,FALSE)*S8,"-") -> 0 | AF8: =IFERROR(VLOOKUP($N8,【管理用】BR_260204!$B$3:$D$20,3,FALSE)*T8,"-") -> 0 | AG8: =IFERROR(VLOOKUP($N8,【管理用】BR_260204!$B$3:$D$20,3,FALSE)*U8,"-") -> 0 | AH8: =IFERROR(VLOOKUP($N8,【管理用】BR_260204!$B$3:$D$20,3,FALSE)*V8,"-") -> 0 | ... AL8: =IFERROR(VLOOKUP($N8,【管理用】BR_260204!$B$3:$D$20,3,FALSE)*Z8,"-") -> 0 | AM8: =SUM(AA8:AL8) -> 61.6 | AN8: *
B9: =ROW(A9)-4 -> 5 | C9: 3 | D9: =IFERROR(VLOOKUP($C9,'【入力用②】案件ごと売上（D案件以上）'!$B$4:$Y$1048576,2,FALSE),"-") -> 日本総研 | E9: =IFERROR(VLOOKUP($C9,'【入力用②】案件ごと売上（D案件以上）'!$B$4:$Y$1048576,3,FALSE),"-") -> キャリア入社者課題分析 | F9: =IFERROR(VLOOKUP($C9,'【入力用②】案件ごと売上（D案件以上）'!$B$4:$Y$1048576,4,FALSE),"-") -> 03_日本総研_キャリア入社者課題分析 | G9: =IFERROR(VLOOKUP($C9,'【入力用②】案件ごと売上（D案件以上）'!$B$4:$Y$1048576,5,FALSE),"-") -> 人材育成 | H9: =IFERROR(VLOOKUP($C9,'【入力用②】案件ごと売上（D案件以上）'!$B$4:$Y$1048576,6,FALSE),"-") -> 成立 | I9: =IFERROR(VLOOKUP($C9,'【入力用②】案件ごと売上（D案件以上）'!$B$4:$Y$1048576,8,FALSE),"-") -> 600 | J9: =SUMIF($C$5:$C$1048576,C9,$AM$5:$AM$1048576) -> 599.505 | K9: =IFERROR(I9-J9,"-") -> 0.495 | L9: =IFERROR(VLOOKUP($C9,'【入力用②】案件ごと売上（D案件以上）'!$B$4:$Y$1048576,11,FALSE),"-") -> 1 | M9: =IFERROR(I9/L9,"-") -> 600 | N9: 啓亮 | O9: 0.2351 | AA9: =IFERROR(VLOOKUP($N9,【管理用】BR_260204!$B$3:$D$20,3,FALSE)*O9,"-") -> 599.505 | AB9: =IFERROR(VLOOKUP($N9,【管理用】BR_260204!$B$3:$D$20,3,FALSE)*P9,"-") -> 0 | AC9: =IFERROR(VLOOKUP($N9,【管理用】BR_260204!$B$3:$D$20,3,FALSE)*Q9,"-") -> 0 | AD9: =IFERROR(VLOOKUP($N9,【管理用】BR_260204!$B$3:$D$20,3,FALSE)*R9,"-") -> 0 | AE9: =IFERROR(VLOOKUP($N9,【管理用】BR_260204!$B$3:$D$20,3,FALSE)*S9,"-") -> 0 | AF9: =IFERROR(VLOOKUP($N9,【管理用】BR_260204!$B$3:$D$20,3,FALSE)*T9,"-") -> 0 | AG9: =IFERROR(VLOOKUP($N9,【管理用】BR_260204!$B$3:$D$20,3,FALSE)*U9,"-") -> 0 | AH9: =IFERROR(VLOOKUP($N9,【管理用】BR_260204!$B$3:$D$20,3,FALSE)*V9,"-") -> 0 | ... AL9: =IFERROR(VLOOKUP($N9,【管理用】BR_260204!$B$3:$D$20,3,FALSE)*Z9,"-") -> 0 | AM9: =SUM(AA9:AL9) -> 599.505 | AN9: *
B10: =ROW(A10)-4 -> 6 | C10: 4 | D10: =IFERROR(VLOOKUP($C10,'【入力用②】案件ごと売上（D案件以上）'!$B$4:$Y$1048576,2,FALSE),"-") -> 田島ルーフィング | E10: =IFERROR(VLOOKUP($C10,'【入力用②】案件ごと売上（D案件以上）'!$B$4:$Y$1048576,3,FALSE),"-") -> 推せる職場診断 | F10: =IFERROR(VLOOKUP($C10,'【入力用②】案件ごと売上（D案件以上）'!$B$4:$Y$1048576,4,FALSE),"-") -> 04_田島ルーフィング_推せる職場診断 | G10: =IFERROR(VLOOKUP($C10,'【入力用②】案件ごと売上（D案件以上）'!$B$4:$Y$1048576,5,FALSE),"-") -> 組織開発 | H10: =IFERROR(VLOOKUP($C10,'【入力用②】案件ごと売上（D案件以上）'!$B$4:$Y$1048576,6,FALSE),"-") -> D | I10: =IFERROR(VLOOKUP($C10,'【入力用②】案件ごと売上（D案件以上）'!$B$4:$Y$1048576,8,FALSE),"-") -> 0 | J10: =SUMIF($C$5:$C$1048576,C10,$AM$5:$AM$1048576) -> 1963.5 | K10: =IFERROR(I10-J10,"-") -> -1963.5 | L10: =IFERROR(VLOOKUP($C10,'【入力用②】案件ごと売上（D案件以上）'!$B$4:$Y$1048576,11,FALSE),"-") -> 0 | M10: =IFERROR(I10/L10,"-") -> - | N10: 啓亮 | P10: 0.77 | AA10: =IFERROR(VLOOKUP($N10,【管理用】BR_260204!$B$3:$D$20,3,FALSE)*O10,"-") -> 0 | AB10: =IFERROR(VLOOKUP($N10,【管理用】BR_260204!$B$3:$D$20,3,FALSE)*P10,"-") -> 1963.5 | AC10: =IFERROR(VLOOKUP($N10,【管理用】BR_260204!$B$3:$D$20,3,FALSE)*Q10,"-") -> 0 | AD10: =IFERROR(VLOOKUP($N10,【管理用】BR_260204!$B$3:$D$20,3,FALSE)*R10,"-") -> 0 | AE10: =IFERROR(VLOOKUP($N10,【管理用】BR_260204!$B$3:$D$20,3,FALSE)*S10,"-") -> 0 | AF10: =IFERROR(VLOOKUP($N10,【管理用】BR_260204!$B$3:$D$20,3,FALSE)*T10,"-") -> 0 | AG10: =IFERROR(VLOOKUP($N10,【管理用】BR_260204!$B$3:$D$20,3,FALSE)*U10,"-") -> 0 | AH10: =IFERROR(VLOOKUP($N10,【管理用】BR_260204!$B$3:$D$20,3,FALSE)*V10,"-") -> 0 | ... AL10: =IFERROR(VLOOKUP($N10,【管理用】BR_260204!$B$3:$D$20,3,FALSE)*Z10,"-") -> 0 | AM10: =SUM(AA10:AL10) -> 1963.5 | AN10: *
B11: =ROW(A11)-4 -> 7 | C11: 5 | D11: =IFERROR(VLOOKUP($C11,'【入力用②】案件ごと売上（D案件以上）'!$B$4:$Y$1048576,2,FALSE),"-") -> YAMAGATA | E11: =IFERROR(VLOOKUP($C11,'【入力用②】案件ごと売上（D案件以上）'!$B$4:$Y$1048576,3,FALSE),"-") -> 新事業立ち上げ支援 | F11: =IFERROR(VLOOKUP($C11,'【入力用②】案件ごと売上（D案件以上）'!$B$4:$Y$1048576,4,FALSE),"-") -> 05_YAMAGATA_新事業立ち上げ支援 | G11: =IFERROR(VLOOKUP($C11,'【入力用②】案件ごと売上（D案件以上）'!$B$4:$Y$1048576,5,FALSE),"-") -> その他 | H11: =IFERROR(VLOOKUP($C11,'【入力用②】案件ごと売上（D案件以上）'!$B$4:$Y$1048576,6,FALSE),"-") -> 成立 | I11: =IFERROR(VLOOKUP($C11,'【入力用②】案件ごと売上（D案件以上）'!$B$4:$Y$1048576,8,FALSE),"-") -> 14500 | J11: =SUMIF($C$5:$C$1048576,C11,$AM$5:$AM$1048576) -> 13528 | K11: =IFERROR(I11-J11,"-") -> 972 | L11: =IFERROR(VLOOKUP($C11,'【入力用②】案件ごと売上（D案件以上）'!$B$4:$Y$1048576,11,FALSE),"-") -> 4 | M11: =IFERROR(I11/L11,"-") -> 3625 | N11: 波多野 | O11: 0.18 | P11: 0.18 | Q11: 0.18 | R11: 0.18 | AA11: =IFERROR(VLOOKUP($N11,【管理用】BR_260204!$B$3:$D$20,3,FALSE)*O11,"-") -> 1530 | AB11: =IFERROR(VLOOKUP($N11,【管理用】BR_260204!$B$3:$D$20,3,FALSE)*P11,"-") -> 1530 | AC11: =IFERROR(VLOOKUP($N11,【管理用】BR_260204!$B$3:$D$20,3,FALSE)*Q11,"-") -> 1530 | AD11: =IFERROR(VLOOKUP($N11,【管理用】BR_260204!$B$3:$D$20,3,FALSE)*R11,"-") -> 1530 | AE11: =IFERROR(VLOOKUP($N11,【管理用】BR_260204!$B$3:$D$20,3,FALSE)*S11,"-") -> 0 | AF11: =IFERROR(VLOOKUP($N11,【管理用】BR_260204!$B$3:$D$20,3,FALSE)*T11,"-") -> 0 | AG11: =IFERROR(VLOOKUP($N11,【管理用】BR_260204!$B$3:$D$20,3,FALSE)*U11,"-") -> 0 | AH11: =IFERROR(VLOOKUP($N11,【管理用】BR_260204!$B$3:$D$20,3,FALSE)*V11,"-") -> 0 | ... AL11: =IFERROR(VLOOKUP($N11,【管理用】BR_260204!$B$3:$D$20,3,FALSE)*Z11,"-") -> 0 | AM11: =SUM(AA11:AL11) -> 6120 | AN11: *
B12: =ROW(A12)-4 -> 8 | C12: 5 | D12: =IFERROR(VLOOKUP($C12,'【入力用②】案件ごと売上（D案件以上）'!$B$4:$Y$1048576,2,FALSE),"-") -> YAMAGATA | E12: =IFERROR(VLOOKUP($C12,'【入力用②】案件ごと売上（D案件以上）'!$B$4:$Y$1048576,3,FALSE),"-") -> 新事業立ち上げ支援 | F12: =IFERROR(VLOOKUP($C12,'【入力用②】案件ごと売上（D案件以上）'!$B$4:$Y$1048576,4,FALSE),"-") -> 05_YAMAGATA_新事業立ち上げ支援 | G12: =IFERROR(VLOOKUP($C12,'【入力用②】案件ごと売上（D案件以上）'!$B$4:$Y$1048576,5,FALSE),"-") -> その他 | H12: =IFERROR(VLOOKUP($C12,'【入力用②】案件ごと売上（D案件以上）'!$B$4:$Y$1048576,6,FALSE),"-") -> 成立 | I12: =IFERROR(VLOOKUP($C12,'【入力用②】案件ごと売上（D案件以上）'!$B$4:$Y$1048576,8,FALSE),"-") -> 14500 | J12: =SUMIF($C$5:$C$1048576,C12,$AM$5:$AM$1048576) -> 13528 | K12: =IFERROR(I12-J12,"-") -> 972 | L12: =IFERROR(VLOOKUP($C12,'【入力用②】案件ごと売上（D案件以上）'!$B$4:$Y$1048576,11,FALSE),"-") -> 4 | M12: =IFERROR(I12/L12,"-") -> 3625 | N12: 丸田 | O12: 0.4 | P12: 0.4 | Q12: 0.4 | R12: 0.4 | AA12: =IFERROR(VLOOKUP($N12,【管理用】BR_260204!$B$3:$D$20,3,FALSE)*O12,"-") -> 752 | AB12: =IFERROR(VLOOKUP($N12,【管理用】BR_260204!$B$3:$D$20,3,FALSE)*P12,"-") -> 752 | AC12: =IFERROR(VLOOKUP($N12,【管理用】BR_260204!$B$3:$D$20,3,FALSE)*Q12,"-") -> 752 | AD12: =IFERROR(VLOOKUP($N12,【管理用】BR_260204!$B$3:$D$20,3,FALSE)*R12,"-") -> 752 | AE12: =IFERROR(VLOOKUP($N12,【管理用】BR_260204!$B$3:$D$20,3,FALSE)*S12,"-") -> 0 | AF12: =IFERROR(VLOOKUP($N12,【管理用】BR_260204!$B$3:$D$20,3,FALSE)*T12,"-") -> 0 | AG12: =IFERROR(VLOOKUP($N12,【管理用】BR_260204!$B$3:$D$20,3,FALSE)*U12,"-") -> 0 | AH12: =IFERROR(VLOOKUP($N12,【管理用】BR_260204!$B$3:$D$20,3,FALSE)*V12,"-") -> 0 | ... AL12: =IFERROR(VLOOKUP($N12,【管理用】BR_260204!$B$3:$D$20,3,FALSE)*Z12,"-") -> 0 | AM12: =SUM(AA12:AL12) -> 3008 | AN12: *
B13: =ROW(A13)-4 -> 9 | C13: 5 | D13: =IFERROR(VLOOKUP($C13,'【入力用②】案件ごと売上（D案件以上）'!$B$4:$Y$1048576,2,FALSE),"-") -> YAMAGATA | E13: =IFERROR(VLOOKUP($C13,'【入力用②】案件ごと売上（D案件以上）'!$B$4:$Y$1048576,3,FALSE),"-") -> 新事業立ち上げ支援 | F13: =IFERROR(VLOOKUP($C13,'【入力用②】案件ごと売上（D案件以上）'!$B$4:$Y$1048576,4,FALSE),"-") -> 05_YAMAGATA_新事業立ち上げ支援 | G13: =IFERROR(VLOOKUP($C13,'【入力用②】案件ごと売上（D案件以上）'!$B$4:$Y$1048576,5,FALSE),"-") -> その他 | H13: =IFERROR(VLOOKUP($C13,'【入力用②】案件ごと売上（D案件以上）'!$B$4:$Y$1048576,6,FALSE),"-") -> 成立 | I13: =IFERROR(VLOOKUP($C13,'【入力用②】案件ごと売上（D案件以上）'!$B$4:$Y$1048576,8,FALSE),"-") -> 14500 | J13: =SUMIF($C$5:$C$1048576,C13,$AM$5:$AM$1048576) -> 13528 | K13: =IFERROR(I13-J13,"-") -> 972 | L13: =IFERROR(VLOOKUP($C13,'【入力用②】案件ごと売上（D案件以上）'!$B$4:$Y$1048576,11,FALSE),"-") -> 4 | M13: =IFERROR(I13/L13,"-") -> 3625 | N13: 加藤 | O13: 0.4 | P13: 0.4 | Q13: 0.4 | R13: 0.4 | AA13: =IFERROR(VLOOKUP($N13,【管理用】BR_260204!$B$3:$D$20,3,FALSE)*O13,"-") -> 700 | AB13: =IFERROR(VLOOKUP($N13,【管理用】BR_260204!$B$3:$D$20,3,FALSE)*P13,"-") -> 700 | AC13: =IFERROR(VLOOKUP($N13,【管理用】BR_260204!$B$3:$D$20,3,FALSE)*Q13,"-") -> 700 | AD13: =IFERROR(VLOOKUP($N13,【管理用】BR_260204!$B$3:$D$20,3,FALSE)*R13,"-") -> 700 | AE13: =IFERROR(VLOOKUP($N13,【管理用】BR_260204!$B$3:$D$20,3,FALSE)*S13,"-") -> 0 | AF13: =IFERROR(VLOOKUP($N13,【管理用】BR_260204!$B$3:$D$20,3,FALSE)*T13,"-") -> 0 | AG13: =IFERROR(VLOOKUP($N13,【管理用】BR_260204!$B$3:$D$20,3,FALSE)*U13,"-") -> 0 | AH13: =IFERROR(VLOOKUP($N13,【管理用】BR_260204!$B$3:$D$20,3,FALSE)*V13,"-") -> 0 | ... AL13: =IFERROR(VLOOKUP($N13,【管理用】BR_260204!$B$3:$D$20,3,FALSE)*Z13,"-") -> 0 | AM13: =SUM(AA13:AL13) -> 2800 | AN13: *
B14: =ROW(A14)-4 -> 10 | C14: 6 | D14: =IFERROR(VLOOKUP($C14,'【入力用②】案件ごと売上（D案件以上）'!$B$4:$Y$1048576,2,FALSE),"-") -> 豊田通商 | E14: =IFERROR(VLOOKUP($C14,'【入力用②】案件ごと売上（D案件以上）'!$B$4:$Y$1048576,3,FALSE),"-") -> 人事KPI | F14: =IFERROR(VLOOKUP($C14,'【入力用②】案件ごと売上（D案件以上）'!$B$4:$Y$1048576,4,FALSE),"-") -> 06_豊田通商_人事KPI | G14: =IFERROR(VLOOKUP($C14,'【入力用②】案件ごと売上（D案件以上）'!$B$4:$Y$1048576,5,FALSE),"-") -> その他 | H14: =IFERROR(VLOOKUP($C14,'【入力用②】案件ごと売上（D案件以上）'!$B$4:$Y$1048576,6,FALSE),"-") -> 失注 | I14: =IFERROR(VLOOKUP($C14,'【入力用②】案件ごと売上（D案件以上）'!$B$4:$Y$1048576,8,FALSE),"-") -> 6000 | J14: =SUMIF($C$5:$C$1048576,C14,$AM$5:$AM$1048576) -> 5764.5 | K14: =IFERROR(I14-J14,"-") -> 235.5 | L14: =IFERROR(VLOOKUP($C14,'【入力用②】案件ごと売上（D案件以上）'!$B$4:$Y$1048576,11,FALSE),"-") -> 3 | M14: =IFERROR(I14/L14,"-") -> 2000 | N14: 芹澤 | O14: 0.45 | P14: 0.45 | Q14: 0.45 | AA14: =IFERROR(VLOOKUP($N14,【管理用】BR_260204!$B$3:$D$20,3,FALSE)*O14,"-") -> 990 | AB14: =IFERROR(VLOOKUP($N14,【管理用】BR_260204!$B$3:$D$20,3,FALSE)*P14,"-") -> 990 | AC14: =IFERROR(VLOOKUP($N14,【管理用】BR_260204!$B$3:$D$20,3,FALSE)*Q14,"-") -> 990 | AD14: =IFERROR(VLOOKUP($N14,【管理用】BR_260204!$B$3:$D$20,3,FALSE)*R14,"-") -> 0 | AE14: =IFERROR(VLOOKUP($N14,【管理用】BR_260204!$B$3:$D$20,3,FALSE)*S14,"-") -> 0 | AF14: =IFERROR(VLOOKUP($N14,【管理用】BR_260204!$B$3:$D$20,3,FALSE)*T14,"-") -> 0 | AG14: =IFERROR(VLOOKUP($N14,【管理用】BR_260204!$B$3:$D$20,3,FALSE)*U14,"-") -> 0 | AH14: =IFERROR(VLOOKUP($N14,【管理用】BR_260204!$B$3:$D$20,3,FALSE)*V14,"-") -> 0 | ... AL14: =IFERROR(VLOOKUP($N14,【管理用】BR_260204!$B$3:$D$20,3,FALSE)*Z14,"-") -> 0 | AM14: =SUM(AA14:AL14) -> 2970 | AN14: *
B15: =ROW(A15)-4 -> 11 | C15: 6 | D15: =IFERROR(VLOOKUP($C15,'【入力用②】案件ごと売上（D案件以上）'!$B$4:$Y$1048576,2,FALSE),"-") -> 豊田通商 | E15: =IFERROR(VLOOKUP($C15,'【入力用②】案件ごと売上（D案件以上）'!$B$4:$Y$1048576,3,FALSE),"-") -> 人事KPI | F15: =IFERROR(VLOOKUP($C15,'【入力用②】案件ごと売上（D案件以上）'!$B$4:$Y$1048576,4,FALSE),"-") -> 06_豊田通商_人事KPI | G15: =IFERROR(VLOOKUP($C15,'【入力用②】案件ごと売上（D案件以上）'!$B$4:$Y$1048576,5,FALSE),"-") -> その他 | H15: =IFERROR(VLOOKUP($C15,'【入力用②】案件ごと売上（D案件以上）'!$B$4:$Y$1048576,6,FALSE),"-") -> 失注 | I15: =IFERROR(VLOOKUP($C15,'【入力用②】案件ごと売上（D案件以上）'!$B$4:$Y$1048576,8,FALSE),"-") -> 6000 | J15: =SUMIF($C$5:$C$1048576,C15,$AM$5:$AM$1048576) -> 5764.5 | K15: =IFERROR(I15-J15,"-") -> 235.5 | L15: =IFERROR(VLOOKUP($C15,'【入力用②】案件ごと売上（D案件以上）'!$B$4:$Y$1048576,11,FALSE),"-") -> 3 | M15: =IFERROR(I15/L15,"-") -> 2000 | N15: 弓本 | O15: 0.45 | P15: 0.45 | Q15: 0.45 | AA15: =IFERROR(VLOOKUP($N15,【管理用】BR_260204!$B$3:$D$20,3,FALSE)*O15,"-") -> 931.5 | AB15: =IFERROR(VLOOKUP($N15,【管理用】BR_260204!$B$3:$D$20,3,FALSE)*P15,"-") -> 931.5 | AC15: =IFERROR(VLOOKUP($N15,【管理用】BR_260204!$B$3:$D$20,3,FALSE)*Q15,"-") -> 931.5 | AD15: =IFERROR(VLOOKUP($N15,【管理用】BR_260204!$B$3:$D$20,3,FALSE)*R15,"-") -> 0 | AE15: =IFERROR(VLOOKUP($N15,【管理用】BR_260204!$B$3:$D$20,3,FALSE)*S15,"-") -> 0 | AF15: =IFERROR(VLOOKUP($N15,【管理用】BR_260204!$B$3:$D$20,3,FALSE)*T15,"-") -> 0 | AG15: =IFERROR(VLOOKUP($N15,【管理用】BR_260204!$B$3:$D$20,3,FALSE)*U15,"-") -> 0 | AH15: =IFERROR(VLOOKUP($N15,【管理用】BR_260204!$B$3:$D$20,3,FALSE)*V15,"-") -> 0 | ... AL15: =IFERROR(VLOOKUP($N15,【管理用】BR_260204!$B$3:$D$20,3,FALSE)*Z15,"-") -> 0 | AM15: =SUM(AA15:AL15) -> 2794.5 | AN15: *
B16: =ROW(A16)-4 -> 12 | C16: 7 | D16: =IFERROR(VLOOKUP($C16,'【入力用②】案件ごと売上（D案件以上）'!$B$4:$Y$1048576,2,FALSE),"-") -> 豊田通商 | E16: =IFERROR(VLOOKUP($C16,'【入力用②】案件ごと売上（D案件以上）'!$B$4:$Y$1048576,3,FALSE),"-") -> メタルプラス | F16: =IFERROR(VLOOKUP($C16,'【入力用②】案件ごと売上（D案件以上）'!$B$4:$Y$1048576,4,FALSE),"-") -> 07_豊田通商_メタルプラス | G16: =IFERROR(VLOOKUP($C16,'【入力用②】案件ごと売上（D案件以上）'!$B$4:$Y$1048576,5,FALSE),"-") -> その他 | H16: =IFERROR(VLOOKUP($C16,'【入力用②】案件ごと売上（D案件以上）'!$B$4:$Y$1048576,6,FALSE),"-") -> 成立 | I16: =IFERROR(VLOOKUP($C16,'【入力用②】案件ごと売上（D案件以上）'!$B$4:$Y$1048576,8,FALSE),"-") -> 6750 | J16: =SUMIF($C$5:$C$1048576,C16,$AM$5:$AM$1048576) -> 6730.5 | K16: =IFERROR(I16-J16,"-") -> 19.5 | L16: =IFERROR(VLOOKUP($C16,'【入力用②】案件ごと売上（D案件以上）'!$B$4:$Y$1048576,11,FALSE),"-") -> 3 | M16: =IFERROR(I16/L16,"-") -> 2250 | N16: 波多野 | Q16: 0.13 | R16: 0.13 | S16: 0.13 | AA16: =IFERROR(VLOOKUP($N16,【管理用】BR_260204!$B$3:$D$20,3,FALSE)*O16,"-") -> 0 | AB16: =IFERROR(VLOOKUP($N16,【管理用】BR_260204!$B$3:$D$20,3,FALSE)*P16,"-") -> 0 | AC16: =IFERROR(VLOOKUP($N16,【管理用】BR_260204!$B$3:$D$20,3,FALSE)*Q16,"-") -> 1105 | AD16: =IFERROR(VLOOKUP($N16,【管理用】BR_260204!$B$3:$D$20,3,FALSE)*R16,"-") -> 1105 | AE16: =IFERROR(VLOOKUP($N16,【管理用】BR_260204!$B$3:$D$20,3,FALSE)*S16,"-") -> 1105 | AF16: =IFERROR(VLOOKUP($N16,【管理用】BR_260204!$B$3:$D$20,3,FALSE)*T16,"-") -> 0 | AG16: =IFERROR(VLOOKUP($N16,【管理用】BR_260204!$B$3:$D$20,3,FALSE)*U16,"-") -> 0 | AH16: =IFERROR(VLOOKUP($N16,【管理用】BR_260204!$B$3:$D$20,3,FALSE)*V16,"-") -> 0 | ... AL16: =IFERROR(VLOOKUP($N16,【管理用】BR_260204!$B$3:$D$20,3,FALSE)*Z16,"-") -> 0 | AM16: =SUM(AA16:AL16) -> 3315 | AN16: *
B17: =ROW(A17)-4 -> 13 | C17: 7 | D17: =IFERROR(VLOOKUP($C17,'【入力用②】案件ごと売上（D案件以上）'!$B$4:$Y$1048576,2,FALSE),"-") -> 豊田通商 | E17: =IFERROR(VLOOKUP($C17,'【入力用②】案件ごと売上（D案件以上）'!$B$4:$Y$1048576,3,FALSE),"-") -> メタルプラス | F17: =IFERROR(VLOOKUP($C17,'【入力用②】案件ごと売上（D案件以上）'!$B$4:$Y$1048576,4,FALSE),"-") -> 07_豊田通商_メタルプラス | G17: =IFERROR(VLOOKUP($C17,'【入力用②】案件ごと売上（D案件以上）'!$B$4:$Y$1048576,5,FALSE),"-") -> その他 | H17: =IFERROR(VLOOKUP($C17,'【入力用②】案件ごと売上（D案件以上）'!$B$4:$Y$1048576,6,FALSE),"-") -> 成立 | I17: =IFERROR(VLOOKUP($C17,'【入力用②】案件ごと売上（D案件以上）'!$B$4:$Y$1048576,8,FALSE),"-") -> 6750 | J17: =SUMIF($C$5:$C$1048576,C17,$AM$5:$AM$1048576) -> 6730.5 | K17: =IFERROR(I17-J17,"-") -> 19.5 | L17: =IFERROR(VLOOKUP($C17,'【入力用②】案件ごと売上（D案件以上）'!$B$4:$Y$1048576,11,FALSE),"-") -> 3 | M17: =IFERROR(I17/L17,"-") -> 2250 | N17: 弓本 | Q17: 0.55 | R17: 0.55 | S17: 0.55 | AA17: =IFERROR(VLOOKUP($N17,【管理用】BR_260204!$B$3:$D$20,3,FALSE)*O17,"-") -> 0 | AB17: =IFERROR(VLOOKUP($N17,【管理用】BR_260204!$B$3:$D$20,3,FALSE)*P17,"-") -> 0 | AC17: =IFERROR(VLOOKUP($N17,【管理用】BR_260204!$B$3:$D$20,3,FALSE)*Q17,"-") -> 1138.5 | AD17: =IFERROR(VLOOKUP($N17,【管理用】BR_260204!$B$3:$D$20,3,FALSE)*R17,"-") -> 1138.5 | AE17: =IFERROR(VLOOKUP($N17,【管理用】BR_260204!$B$3:$D$20,3,FALSE)*S17,"-") -> 1138.5 | AF17: =IFERROR(VLOOKUP($N17,【管理用】BR_260204!$B$3:$D$20,3,FALSE)*T17,"-") -> 0 | AG17: =IFERROR(VLOOKUP($N17,【管理用】BR_260204!$B$3:$D$20,3,FALSE)*U17,"-") -> 0 | AH17: =IFERROR(VLOOKUP($N17,【管理用】BR_260204!$B$3:$D$20,3,FALSE)*V17,"-") -> 0 | ... AL17: =IFERROR(VLOOKUP($N17,【管理用】BR_260204!$B$3:$D$20,3,FALSE)*Z17,"-") -> 0 | AM17: =SUM(AA17:AL17) -> 3415.5
B18: =ROW(A18)-4 -> 14 | C18: 8 | D18: =IFERROR(VLOOKUP($C18,'【入力用②】案件ごと売上（D案件以上）'!$B$4:$Y$1048576,2,FALSE),"-") -> OKI | E18: =IFERROR(VLOOKUP($C18,'【入力用②】案件ごと売上（D案件以上）'!$B$4:$Y$1048576,3,FALSE),"-") -> 人材面を主とした組織診断 | F18: =IFERROR(VLOOKUP($C18,'【入力用②】案件ごと売上（D案件以上）'!$B$4:$Y$1048576,4,FALSE),"-") -> 08_OKI_人材面を主とした組織診断 | G18: =IFERROR(VLOOKUP($C18,'【入力用②】案件ごと売上（D案件以上）'!$B$4:$Y$1048576,5,FALSE),"-") -> その他 | H18: =IFERROR(VLOOKUP($C18,'【入力用②】案件ごと売上（D案件以上）'!$B$4:$Y$1048576,6,FALSE),"-") -> 成立 | I18: =IFERROR(VLOOKUP($C18,'【入力用②】案件ごと売上（D案件以上）'!$B$4:$Y$1048576,8,FALSE),"-") -> 4000 | J18: =SUMIF($C$5:$C$1048576,C18,$AM$5:$AM$1048576) -> 4000 | K18: =IFERROR(I18-J18,"-") -> 0 | L18: =IFERROR(VLOOKUP($C18,'【入力用②】案件ごと売上（D案件以上）'!$B$4:$Y$1048576,11,FALSE),"-") -> 3.5 | M18: =IFERROR(I18/L18,"-") -> 1142.8571 | N18: 波多野 | O18: 0.1 | P18: 0.1 | AA18: =IFERROR(VLOOKUP($N18,【管理用】BR_260204!$B$3:$D$20,3,FALSE)*O18,"-") -> 850 | AB18: =IFERROR(VLOOKUP($N18,【管理用】BR_260204!$B$3:$D$20,3,FALSE)*P18,"-") -> 850 | AC18: =IFERROR(VLOOKUP($N18,【管理用】BR_260204!$B$3:$D$20,3,FALSE)*Q18,"-") -> 0 | AD18: =IFERROR(VLOOKUP($N18,【管理用】BR_260204!$B$3:$D$20,3,FALSE)*R18,"-") -> 0 | AE18: =IFERROR(VLOOKUP($N18,【管理用】BR_260204!$B$3:$D$20,3,FALSE)*S18,"-") -> 0 | AF18: =IFERROR(VLOOKUP($N18,【管理用】BR_260204!$B$3:$D$20,3,FALSE)*T18,"-") -> 0 | AG18: =IFERROR(VLOOKUP($N18,【管理用】BR_260204!$B$3:$D$20,3,FALSE)*U18,"-") -> 0 | AH18: =IFERROR(VLOOKUP($N18,【管理用】BR_260204!$B$3:$D$20,3,FALSE)*V18,"-") -> 0 | ... AL18: =IFERROR(VLOOKUP($N18,【管理用】BR_260204!$B$3:$D$20,3,FALSE)*Z18,"-") -> 0 | AM18: =SUM(AA18:AL18) -> 1700 | AN18: *
B19: =ROW(A19)-4 -> 15 | C19: 8 | D19: =IFERROR(VLOOKUP($C19,'【入力用②】案件ごと売上（D案件以上）'!$B$4:$Y$1048576,2,FALSE),"-") -> OKI | E19: =IFERROR(VLOOKUP($C19,'【入力用②】案件ごと売上（D案件以上）'!$B$4:$Y$1048576,3,FALSE),"-") -> 人材面を主とした組織診断 | F19: =IFERROR(VLOOKUP($C19,'【入力用②】案件ごと売上（D案件以上）'!$B$4:$Y$1048576,4,FALSE),"-") -> 08_OKI_人材面を主とした組織診断 | G19: =IFERROR(VLOOKUP($C19,'【入力用②】案件ごと売上（D案件以上）'!$B$4:$Y$1048576,5,FALSE),"-") -> その他 | H19: =IFERROR(VLOOKUP($C19,'【入力用②】案件ごと売上（D案件以上）'!$B$4:$Y$1048576,6,FALSE),"-") -> 成立 | I19: =IFERROR(VLOOKUP($C19,'【入力用②】案件ごと売上（D案件以上）'!$B$4:$Y$1048576,8,FALSE),"-") -> 4000 | J19: =SUMIF($C$5:$C$1048576,C19,$AM$5:$AM$1048576) -> 4000 | K19: =IFERROR(I19-J19,"-") -> 0 | L19: =IFERROR(VLOOKUP($C19,'【入力用②】案件ごと売上（D案件以上）'!$B$4:$Y$1048576,11,FALSE),"-") -> 3.5 | M19: =IFERROR(I19/L19,"-") -> 1142.8571 | N19: 芹澤 | O19: 0.3 | P19: 0.3 | AA19: =IFERROR(VLOOKUP($N19,【管理用】BR_260204!$B$3:$D$20,3,FALSE)*O19,"-") -> 660 | AB19: =IFERROR(VLOOKUP($N19,【管理用】BR_260204!$B$3:$D$20,3,FALSE)*P19,"-") -> 660 | AC19: =IFERROR(VLOOKUP($N19,【管理用】BR_260204!$B$3:$D$20,3,FALSE)*Q19,"-") -> 0 | AD19: =IFERROR(VLOOKUP($N19,【管理用】BR_260204!$B$3:$D$20,3,FALSE)*R19,"-") -> 0 | AE19: =IFERROR(VLOOKUP($N19,【管理用】BR_260204!$B$3:$D$20,3,FALSE)*S19,"-") -> 0 | AF19: =IFERROR(VLOOKUP($N19,【管理用】BR_260204!$B$3:$D$20,3,FALSE)*T19,"-") -> 0 | AG19: =IFERROR(VLOOKUP($N19,【管理用】BR_260204!$B$3:$D$20,3,FALSE)*U19,"-") -> 0 | AH19: =IFERROR(VLOOKUP($N19,【管理用】BR_260204!$B$3:$D$20,3,FALSE)*V19,"-") -> 0 | ... AL19: =IFERROR(VLOOKUP($N19,【管理用】BR_260204!$B$3:$D$20,3,FALSE)*Z19,"-") -> 0 | AM19: =SUM(AA19:AL19) -> 1320 | AN19: *
B20: =ROW(A20)-4 -> 16 | C20: 8 | D20: =IFERROR(VLOOKUP($C20,'【入力用②】案件ごと売上（D案件以上）'!$B$4:$Y$1048576,2,FALSE),"-") -> OKI | E20: =IFERROR(VLOOKUP($C20,'【入力用②】案件ごと売上（D案件以上）'!$B$4:$Y$1048576,3,FALSE),"-") -> 人材面を主とした組織診断 | F20: =IFERROR(VLOOKUP($C20,'【入力用②】案件ごと売上（D案件以上）'!$B$4:$Y$1048576,4,FALSE),"-") -> 08_OKI_人材面を主とした組織診断 | G20: =IFERROR(VLOOKUP($C20,'【入力用②】案件ごと売上（D案件以上）'!$B$4:$Y$1048576,5,FALSE),"-") -> その他 | H20: =IFERROR(VLOOKUP($C20,'【入力用②】案件ごと売上（D案件以上）'!$B$4:$Y$1048576,6,FALSE),"-") -> 成立 | I20: =IFERROR(VLOOKUP($C20,'【入力用②】案件ごと売上（D案件以上）'!$B$4:$Y$1048576,8,FALSE),"-") -> 4000 | J20: =SUMIF($C$5:$C$1048576,C20,$AM$5:$AM$1048576) -> 4000 | K20: =IFERROR(I20-J20,"-") -> 0 | L20: =IFERROR(VLOOKUP($C20,'【入力用②】案件ごと売上（D案件以上）'!$B$4:$Y$1048576,11,FALSE),"-") -> 3.5 | M20: =IFERROR(I20/L20,"-") -> 1142.8571 | N20: 加藤 | O20: 0.3 | P20: 0.26 | AA20: =IFERROR(VLOOKUP($N20,【管理用】BR_260204!$B$3:$D$20,3,FALSE)*O20,"-") -> 525 | AB20: =IFERROR(VLOOKUP($N20,【管理用】BR_260204!$B$3:$D$20,3,FALSE)*P20,"-") -> 455 | AC20: =IFERROR(VLOOKUP($N20,【管理用】BR_260204!$B$3:$D$20,3,FALSE)*Q20,"-") -> 0 | AD20: =IFERROR(VLOOKUP($N20,【管理用】BR_260204!$B$3:$D$20,3,FALSE)*R20,"-") -> 0 | AE20: =IFERROR(VLOOKUP($N20,【管理用】BR_260204!$B$3:$D$20,3,FALSE)*S20,"-") -> 0 | AF20: =IFERROR(VLOOKUP($N20,【管理用】BR_260204!$B$3:$D$20,3,FALSE)*T20,"-") -> 0 | AG20: =IFERROR(VLOOKUP($N20,【管理用】BR_260204!$B$3:$D$20,3,FALSE)*U20,"-") -> 0 | AH20: =IFERROR(VLOOKUP($N20,【管理用】BR_260204!$B$3:$D$20,3,FALSE)*V20,"-") -> 0 | ... AL20: =IFERROR(VLOOKUP($N20,【管理用】BR_260204!$B$3:$D$20,3,FALSE)*Z20,"-") -> 0 | AM20: =SUM(AA20:AL20) -> 980 | AN20: *
B21: =ROW(A21)-4 -> 17 | C21: 9 | D21: =IFERROR(VLOOKUP($C21,'【入力用②】案件ごと売上（D案件以上）'!$B$4:$Y$1048576,2,FALSE),"-") -> 宮﨑製鋼 | E21: =IFERROR(VLOOKUP($C21,'【入力用②】案件ごと売上（D案件以上）'!$B$4:$Y$1048576,3,FALSE),"-") -> エンゲージメントサーベイ | F21: =IFERROR(VLOOKUP($C21,'【入力用②】案件ごと売上（D案件以上）'!$B$4:$Y$1048576,4,FALSE),"-") -> 09_宮﨑製鋼_エンゲージメントサーベイ | G21: =IFERROR(VLOOKUP($C21,'【入力用②】案件ごと売上（D案件以上）'!$B$4:$Y$1048576,5,FALSE),"-") -> その他 | H21: =IFERROR(VLOOKUP($C21,'【入力用②】案件ごと売上（D案件以上）'!$B$4:$Y$1048576,6,FALSE),"-") -> 成立 | I21: =IFERROR(VLOOKUP($C21,'【入力用②】案件ごと売上（D案件以上）'!$B$4:$Y$1048576,8,FALSE),"-") -> 500 | J21: =SUMIF($C$5:$C$1048576,C21,$AM$5:$AM$1048576) -> 499.5 | K21: =IFERROR(I21-J21,"-") -> 0.5 | L21: =IFERROR(VLOOKUP($C21,'【入力用②】案件ごと売上（D案件以上）'!$B$4:$Y$1048576,11,FALSE),"-") -> 3 | M21: =IFERROR(I21/L21,"-") -> 166.66667 | N21: 芹澤 | O21: 0.03 | P21: 0.03 | AA21: =IFERROR(VLOOKUP($N21,【管理用】BR_260204!$B$3:$D$20,3,FALSE)*O21,"-") -> 66 | AB21: =IFERROR(VLOOKUP($N21,【管理用】BR_260204!$B$3:$D$20,3,FALSE)*P21,"-") -> 66 | AC21: =IFERROR(VLOOKUP($N21,【管理用】BR_260204!$B$3:$D$20,3,FALSE)*Q21,"-") -> 0 | AD21: =IFERROR(VLOOKUP($N21,【管理用】BR_260204!$B$3:$D$20,3,FALSE)*R21,"-") -> 0 | AE21: =IFERROR(VLOOKUP($N21,【管理用】BR_260204!$B$3:$D$20,3,FALSE)*S21,"-") -> 0 | AF21: =IFERROR(VLOOKUP($N21,【管理用】BR_260204!$B$3:$D$20,3,FALSE)*T21,"-") -> 0 | AG21: =IFERROR(VLOOKUP($N21,【管理用】BR_260204!$B$3:$D$20,3,FALSE)*U21,"-") -> 0 | AH21: =IFERROR(VLOOKUP($N21,【管理用】BR_260204!$B$3:$D$20,3,FALSE)*V21,"-") -> 0 | ... AL21: =IFERROR(VLOOKUP($N21,【管理用】BR_260204!$B$3:$D$20,3,FALSE)*Z21,"-") -> 0 | AM21: =SUM(AA21:AL21) -> 132 | AN21: *
B22: =ROW(A22)-4 -> 18 | C22: 9 | D22: =IFERROR(VLOOKUP($C22,'【入力用②】案件ごと売上（D案件以上）'!$B$4:$Y$1048576,2,FALSE),"-") -> 宮﨑製鋼 | E22: =IFERROR(VLOOKUP($C22,'【入力用②】案件ごと売上（D案件以上）'!$B$4:$Y$1048576,3,FALSE),"-") -> エンゲージメントサーベイ | F22: =IFERROR(VLOOKUP($C22,'【入力用②】案件ごと売上（D案件以上）'!$B$4:$Y$1048576,4,FALSE),"-") -> 09_宮﨑製鋼_エンゲージメントサーベイ | G22: =IFERROR(VLOOKUP($C22,'【入力用②】案件ごと売上（D案件以上）'!$B$4:$Y$1048576,5,FALSE),"-") -> その他 | H22: =IFERROR(VLOOKUP($C22,'【入力用②】案件ごと売上（D案件以上）'!$B$4:$Y$1048576,6,FALSE),"-") -> 成立 | I22: =IFERROR(VLOOKUP($C22,'【入力用②】案件ごと売上（D案件以上）'!$B$4:$Y$1048576,8,FALSE),"-") -> 500 | J22: =SUMIF($C$5:$C$1048576,C22,$AM$5:$AM$1048576) -> 499.5 | K22: =IFERROR(I22-J22,"-") -> 0.5 | L22: =IFERROR(VLOOKUP($C22,'【入力用②】案件ごと売上（D案件以上）'!$B$4:$Y$1048576,11,FALSE),"-") -> 3 | M22: =IFERROR(I22/L22,"-") -> 166.66667 | N22: 加藤 | O22: 0.05 | P22: 0.16 | AA22: =IFERROR(VLOOKUP($N22,【管理用】BR_260204!$B$3:$D$20,3,FALSE)*O22,"-") -> 87.5 | AB22: =IFERROR(VLOOKUP($N22,【管理用】BR_260204!$B$3:$D$20,3,FALSE)*P22,"-") -> 280 | AC22: =IFERROR(VLOOKUP($N22,【管理用】BR_260204!$B$3:$D$20,3,FALSE)*Q22,"-") -> 0 | AD22: =IFERROR(VLOOKUP($N22,【管理用】BR_260204!$B$3:$D$20,3,FALSE)*R22,"-") -> 0 | AE22: =IFERROR(VLOOKUP($N22,【管理用】BR_260204!$B$3:$D$20,3,FALSE)*S22,"-") -> 0 | AF22: =IFERROR(VLOOKUP($N22,【管理用】BR_260204!$B$3:$D$20,3,FALSE)*T22,"-") -> 0 | AG22: =IFERROR(VLOOKUP($N22,【管理用】BR_260204!$B$3:$D$20,3,FALSE)*U22,"-") -> 0 | AH22: =IFERROR(VLOOKUP($N22,【管理用】BR_260204!$B$3:$D$20,3,FALSE)*V22,"-") -> 0 | ... AL22: =IFERROR(VLOOKUP($N22,【管理用】BR_260204!$B$3:$D$20,3,FALSE)*Z22,"-") -> 0 | AM22: =SUM(AA22:AL22) -> 367.5 | AN22: *
B23: =ROW(A23)-4 -> 19 | C23: 10 | D23: =IFERROR(VLOOKUP($C23,'【入力用②】案件ごと売上（D案件以上）'!$B$4:$Y$1048576,2,FALSE),"-") -> オムロンエキスパートエンジニアリング | E23: =IFERROR(VLOOKUP($C23,'【入力用②】案件ごと売上（D案件以上）'!$B$4:$Y$1048576,3,FALSE),"-") -> データ分析 | F23: =IFERROR(VLOOKUP($C23,'【入力用②】案件ごと売上（D案件以上）'!$B$4:$Y$1048576,4,FALSE),"-") -> 10_オムロンエキスパートエンジニアリング_データ分析 | G23: =IFERROR(VLOOKUP($C23,'【入力用②】案件ごと売上（D案件以上）'!$B$4:$Y$1048576,5,FALSE),"-") -> その他 | H23: =IFERROR(VLOOKUP($C23,'【入力用②】案件ごと売上（D案件以上）'!$B$4:$Y$1048576,6,FALSE),"-") -> A | I23: =IFERROR(VLOOKUP($C23,'【入力用②】案件ごと売上（D案件以上）'!$B$4:$Y$1048576,8,FALSE),"-") -> 2000 | J23: =SUMIF($C$5:$C$1048576,C23,$AM$5:$AM$1048576) -> 1999 | K23: =IFERROR(I23-J23,"-") -> 1 | L23: =IFERROR(VLOOKUP($C23,'【入力用②】案件ごと売上（D案件以上）'!$B$4:$Y$1048576,11,FALSE),"-") -> 3 | M23: =IFERROR(I23/L23,"-") -> 666.66667 | N23: 芹澤 | P23: 0.12 | Q23: 0.1 | R23: 0.1 | AA23: =IFERROR(VLOOKUP($N23,【管理用】BR_260204!$B$3:$D$20,3,FALSE)*O23,"-") -> 0 | AB23: =IFERROR(VLOOKUP($N23,【管理用】BR_260204!$B$3:$D$20,3,FALSE)*P23,"-") -> 264 | AC23: =IFERROR(VLOOKUP($N23,【管理用】BR_260204!$B$3:$D$20,3,FALSE)*Q23,"-") -> 220 | AD23: =IFERROR(VLOOKUP($N23,【管理用】BR_260204!$B$3:$D$20,3,FALSE)*R23,"-") -> 220 | AE23: =IFERROR(VLOOKUP($N23,【管理用】BR_260204!$B$3:$D$20,3,FALSE)*S23,"-") -> 0 | AF23: =IFERROR(VLOOKUP($N23,【管理用】BR_260204!$B$3:$D$20,3,FALSE)*T23,"-") -> 0 | AG23: =IFERROR(VLOOKUP($N23,【管理用】BR_260204!$B$3:$D$20,3,FALSE)*U23,"-") -> 0 | AH23: =IFERROR(VLOOKUP($N23,【管理用】BR_260204!$B$3:$D$20,3,FALSE)*V23,"-") -> 0 | ... AL23: =IFERROR(VLOOKUP($N23,【管理用】BR_260204!$B$3:$D$20,3,FALSE)*Z23,"-") -> 0 | AM23: =SUM(AA23:AL23) -> 704 | AN23: *
B24: =ROW(A24)-4 -> 20 | C24: 10 | D24: =IFERROR(VLOOKUP($C24,'【入力用②】案件ごと売上（D案件以上）'!$B$4:$Y$1048576,2,FALSE),"-") -> オムロンエキスパートエンジニアリング | E24: =IFERROR(VLOOKUP($C24,'【入力用②】案件ごと売上（D案件以上）'!$B$4:$Y$1048576,3,FALSE),"-") -> データ分析 | F24: =IFERROR(VLOOKUP($C24,'【入力用②】案件ごと売上（D案件以上）'!$B$4:$Y$1048576,4,FALSE),"-") -> 10_オムロンエキスパートエンジニアリング_データ分析 | G24: =IFERROR(VLOOKUP($C24,'【入力用②】案件ごと売上（D案件以上）'!$B$4:$Y$1048576,5,FALSE),"-") -> その他 | H24: =IFERROR(VLOOKUP($C24,'【入力用②】案件ごと売上（D案件以上）'!$B$4:$Y$1048576,6,FALSE),"-") -> A | I24: =IFERROR(VLOOKUP($C24,'【入力用②】案件ごと売上（D案件以上）'!$B$4:$Y$1048576,8,FALSE),"-") -> 2000 | J24: =SUMIF($C$5:$C$1048576,C24,$AM$5:$AM$1048576) -> 1999 | K24: =IFERROR(I24-J24,"-") -> 1 | L24: =IFERROR(VLOOKUP($C24,'【入力用②】案件ごと売上（D案件以上）'!$B$4:$Y$1048576,11,FALSE),"-") -> 3 | M24: =IFERROR(I24/L24,"-") -> 666.66667 | N24: 加藤 | P24: 0.15 | Q24: 0.29 | R24: 0.3 | AA24: =IFERROR(VLOOKUP($N24,【管理用】BR_260204!$B$3:$D$20,3,FALSE)*O24,"-") -> 0 | AB24: =IFERROR(VLOOKUP($N24,【管理用】BR_260204!$B$3:$D$20,3,FALSE)*P24,"-") -> 262.5 | AC24: =IFERROR(VLOOKUP($N24,【管理用】BR_260204!$B$3:$D$20,3,FALSE)*Q24,"-") -> 507.5 | AD24: =IFERROR(VLOOKUP($N24,【管理用】BR_260204!$B$3:$D$20,3,FALSE)*R24,"-") -> 525 | AE24: =IFERROR(VLOOKUP($N24,【管理用】BR_260204!$B$3:$D$20,3,FALSE)*S24,"-") -> 0 | AF24: =IFERROR(VLOOKUP($N24,【管理用】BR_260204!$B$3:$D$20,3,FALSE)*T24,"-") -> 0 | AG24: =IFERROR(VLOOKUP($N24,【管理用】BR_260204!$B$3:$D$20,3,FALSE)*U24,"-") -> 0 | AH24: =IFERROR(VLOOKUP($N24,【管理用】BR_260204!$B$3:$D$20,3,FALSE)*V24,"-") -> 0 | ... AL24: =IFERROR(VLOOKUP($N24,【管理用】BR_260204!$B$3:$D$20,3,FALSE)*Z24,"-") -> 0 | AM24: =SUM(AA24:AL24) -> 1295 | AN24: *
B25: =ROW(A25)-4 -> 21 | C25: 11 | D25: =IFERROR(VLOOKUP($C25,'【入力用②】案件ごと売上（D案件以上）'!$B$4:$Y$1048576,2,FALSE),"-") -> MSプライマリー | E25: =IFERROR(VLOOKUP($C25,'【入力用②】案件ごと売上（D案件以上）'!$B$4:$Y$1048576,3,FALSE),"-") -> エンゲージメントサーベイ | F25: =IFERROR(VLOOKUP($C25,'【入力用②】案件ごと売上（D案件以上）'!$B$4:$Y$1048576,4,FALSE),"-") -> 11_MSプライマリー_エンゲージメントサーベイ | G25: =IFERROR(VLOOKUP($C25,'【入力用②】案件ごと売上（D案件以上）'!$B$4:$Y$1048576,5,FALSE),"-") -> その他 | H25: =IFERROR(VLOOKUP($C25,'【入力用②】案件ごと売上（D案件以上）'!$B$4:$Y$1048576,6,FALSE),"-") -> A | I25: =IFERROR(VLOOKUP($C25,'【入力用②】案件ごと売上（D案件以上）'!$B$4:$Y$1048576,8,FALSE),"-") -> 7000 | J25: =SUMIF($C$5:$C$1048576,C25,$AM$5:$AM$1048576) -> 6999.6 | K25: =IFERROR(I25-J25,"-") -> 0.4 | L25: =IFERROR(VLOOKUP($C25,'【入力用②】案件ごと売上（D案件以上）'!$B$4:$Y$1048576,11,FALSE),"-") -> 4 | M25: =IFERROR(I25/L25,"-") -> 1750 | N25: 芹澤 | O25: 0.25 | P25: 0.4 | Q25: 0.4 | R25: 0.638 | AA25: =IFERROR(VLOOKUP($N25,【管理用】BR_260204!$B$3:$D$20,3,FALSE)*O25,"-") -> 550 | AB25: =IFERROR(VLOOKUP($N25,【管理用】BR_260204!$B$3:$D$20,3,FALSE)*P25,"-") -> 880 | AC25: =IFERROR(VLOOKUP($N25,【管理用】BR_260204!$B$3:$D$20,3,FALSE)*Q25,"-") -> 880 | AD25: =IFERROR(VLOOKUP($N25,【管理用】BR_260204!$B$3:$D$20,3,FALSE)*R25,"-") -> 1403.6 | AE25: =IFERROR(VLOOKUP($N25,【管理用】BR_260204!$B$3:$D$20,3,FALSE)*S25,"-") -> 0 | AF25: =IFERROR(VLOOKUP($N25,【管理用】BR_260204!$B$3:$D$20,3,FALSE)*T25,"-") -> 0 | AG25: =IFERROR(VLOOKUP($N25,【管理用】BR_260204!$B$3:$D$20,3,FALSE)*U25,"-") -> 0 | AH25: =IFERROR(VLOOKUP($N25,【管理用】BR_260204!$B$3:$D$20,3,FALSE)*V25,"-") -> 0 | ... AL25: =IFERROR(VLOOKUP($N25,【管理用】BR_260204!$B$3:$D$20,3,FALSE)*Z25,"-") -> 0 | AM25: =SUM(AA25:AL25) -> 3713.6 | AN25: *
B26: =ROW(A26)-4 -> 22 | C26: 11 | D26: =IFERROR(VLOOKUP($C26,'【入力用②】案件ごと売上（D案件以上）'!$B$4:$Y$1048576,2,FALSE),"-") -> MSプライマリー | E26: =IFERROR(VLOOKUP($C26,'【入力用②】案件ごと売上（D案件以上）'!$B$4:$Y$1048576,3,FALSE),"-") -> エンゲージメントサーベイ | F26: =IFERROR(VLOOKUP($C26,'【入力用②】案件ごと売上（D案件以上）'!$B$4:$Y$1048576,4,FALSE),"-") -> 11_MSプライマリー_エンゲージメントサーベイ | G26: =IFERROR(VLOOKUP($C26,'【入力用②】案件ごと売上（D案件以上）'!$B$4:$Y$1048576,5,FALSE),"-") -> その他 | H26: =IFERROR(VLOOKUP($C26,'【入力用②】案件ごと売上（D案件以上）'!$B$4:$Y$1048576,6,FALSE),"-") -> A | I26: =IFERROR(VLOOKUP($C26,'【入力用②】案件ごと売上（D案件以上）'!$B$4:$Y$1048576,8,FALSE),"-") -> 7000 | J26: =SUMIF($C$5:$C$1048576,C26,$AM$5:$AM$1048576) -> 6999.6 | K26: =IFERROR(I26-J26,"-") -> 0.4 | L26: =IFERROR(VLOOKUP($C26,'【入力用②】案件ごと売上（D案件以上）'!$B$4:$Y$1048576,11,FALSE),"-") -> 4 | M26: =IFERROR(I26/L26,"-") -> 1750 | N26: 弓本 | O26: 0.45 | P26: 0.25 | Q26: 0.25 | AA26: =IFERROR(VLOOKUP($N26,【管理用】BR_260204!$B$3:$D$20,3,FALSE)*O26,"-") -> 931.5 | AB26: =IFERROR(VLOOKUP($N26,【管理用】BR_260204!$B$3:$D$20,3,FALSE)*P26,"-") -> 517.5 | AC26: =IFERROR(VLOOKUP($N26,【管理用】BR_260204!$B$3:$D$20,3,FALSE)*Q26,"-") -> 517.5 | AD26: =IFERROR(VLOOKUP($N26,【管理用】BR_260204!$B$3:$D$20,3,FALSE)*R26,"-") -> 0 | AE26: =IFERROR(VLOOKUP($N26,【管理用】BR_260204!$B$3:$D$20,3,FALSE)*S26,"-") -> 0 | AF26: =IFERROR(VLOOKUP($N26,【管理用】BR_260204!$B$3:$D$20,3,FALSE)*T26,"-") -> 0 | AG26: =IFERROR(VLOOKUP($N26,【管理用】BR_260204!$B$3:$D$20,3,FALSE)*U26,"-") -> 0 | AH26: =IFERROR(VLOOKUP($N26,【管理用】BR_260204!$B$3:$D$20,3,FALSE)*V26,"-") -> 0 | ... AL26: =IFERROR(VLOOKUP($N26,【管理用】BR_260204!$B$3:$D$20,3,FALSE)*Z26,"-") -> 0 | AM26: =SUM(AA26:AL26) -> 1966.5 | AN26: *
B27: =ROW(A27)-4 -> 23 | C27: 11 | D27: =IFERROR(VLOOKUP($C27,'【入力用②】案件ごと売上（D案件以上）'!$B$4:$Y$1048576,2,FALSE),"-") -> MSプライマリー | E27: =IFERROR(VLOOKUP($C27,'【入力用②】案件ごと売上（D案件以上）'!$B$4:$Y$1048576,3,FALSE),"-") -> エンゲージメントサーベイ | F27: =IFERROR(VLOOKUP($C27,'【入力用②】案件ごと売上（D案件以上）'!$B$4:$Y$1048576,4,FALSE),"-") -> 11_MSプライマリー_エンゲージメントサーベイ | G27: =IFERROR(VLOOKUP($C27,'【入力用②】案件ごと売上（D案件以上）'!$B$4:$Y$1048576,5,FALSE),"-") -> その他 | H27: =IFERROR(VLOOKUP($C27,'【入力用②】案件ごと売上（D案件以上）'!$B$4:$Y$1048576,6,FALSE),"-") -> A | I27: =IFERROR(VLOOKUP($C27,'【入力用②】案件ごと売上（D案件以上）'!$B$4:$Y$1048576,8,FALSE),"-") -> 7000 | J27: =SUMIF($C$5:$C$1048576,C27,$AM$5:$AM$1048576) -> 6999.6 | K27: =IFERROR(I27-J27,"-") -> 0.4 | L27: =IFERROR(VLOOKUP($C27,'【入力用②】案件ごと売上（D案件以上）'!$B$4:$Y$1048576,11,FALSE),"-") -> 4 | M27: =IFERROR(I27/L27,"-") -> 1750 | N27: 小川 | O27: 0.05 | P27: 0.05 | Q27: 0.05 | R27: 0.05 | AA27: =IFERROR(VLOOKUP($N27,【管理用】BR_260204!$B$3:$D$20,3,FALSE)*O27,"-") -> 308 | AB27: =IFERROR(VLOOKUP($N27,【管理用】BR_260204!$B$3:$D$20,3,FALSE)*P27,"-") -> 308 | AC27: =IFERROR(VLOOKUP($N27,【管理用】BR_260204!$B$3:$D$20,3,FALSE)*Q27,"-") -> 308 | AD27: =IFERROR(VLOOKUP($N27,【管理用】BR_260204!$B$3:$D$20,3,FALSE)*R27,"-") -> 308 | AE27: =IFERROR(VLOOKUP($N27,【管理用】BR_260204!$B$3:$D$20,3,FALSE)*S27,"-") -> 0 | AF27: =IFERROR(VLOOKUP($N27,【管理用】BR_260204!$B$3:$D$20,3,FALSE)*T27,"-") -> 0 | AG27: =IFERROR(VLOOKUP($N27,【管理用】BR_260204!$B$3:$D$20,3,FALSE)*U27,"-") -> 0 | AH27: =IFERROR(VLOOKUP($N27,【管理用】BR_260204!$B$3:$D$20,3,FALSE)*V27,"-") -> 0 | ... AL27: =IFERROR(VLOOKUP($N27,【管理用】BR_260204!$B$3:$D$20,3,FALSE)*Z27,"-") -> 0 | AM27: =SUM(AA27:AL27) -> 1232 | AN27: *
B28: =ROW(A28)-4 -> 24 | C28: 12 | D28: =IFERROR(VLOOKUP($C28,'【入力用②】案件ごと売上（D案件以上）'!$B$4:$Y$1048576,2,FALSE),"-") -> アートプレスト | E28: =IFERROR(VLOOKUP($C28,'【入力用②】案件ごと売上（D案件以上）'!$B$4:$Y$1048576,3,FALSE),"-") -> 2025年上期人事施策実行支援 | F28: =IFERROR(VLOOKUP($C28,'【入力用②】案件ごと売上（D案件以上）'!$B$4:$Y$1048576,4,FALSE),"-") -> 12_アートプレスト_2025年上期人事施策実行支援 | G28: =IFERROR(VLOOKUP($C28,'【入力用②】案件ごと売上（D案件以上）'!$B$4:$Y$1048576,5,FALSE),"-") -> その他 | H28: =IFERROR(VLOOKUP($C28,'【入力用②】案件ごと売上（D案件以上）'!$B$4:$Y$1048576,6,FALSE),"-") -> 成立 | I28: =IFERROR(VLOOKUP($C28,'【入力用②】案件ごと売上（D案件以上）'!$B$4:$Y$1048576,8,FALSE),"-") -> 6700 | J28: =SUMIF($C$5:$C$1048576,C28,$AM$5:$AM$1048576) -> 6688.1 | K28: =IFERROR(I28-J28,"-") -> 11.9 | L28: =IFERROR(VLOOKUP($C28,'【入力用②】案件ごと売上（D案件以上）'!$B$4:$Y$1048576,11,FALSE),"-") -> 1 | M28: =IFERROR(I28/L28,"-") -> 6700 | N28: 友祐 | O28: 1.97 | AA28: =IFERROR(VLOOKUP($N28,【管理用】BR_260204!$B$3:$D$20,3,FALSE)*O28,"-") -> 4393.1 | AB28: =IFERROR(VLOOKUP($N28,【管理用】BR_260204!$B$3:$D$20,3,FALSE)*P28,"-") -> 0 | AC28: =IFERROR(VLOOKUP($N28,【管理用】BR_260204!$B$3:$D$20,3,FALSE)*Q28,"-") -> 0 | AD28: =IFERROR(VLOOKUP($N28,【管理用】BR_260204!$B$3:$D$20,3,FALSE)*R28,"-") -> 0 | AE28: =IFERROR(VLOOKUP($N28,【管理用】BR_260204!$B$3:$D$20,3,FALSE)*S28,"-") -> 0 | AF28: =IFERROR(VLOOKUP($N28,【管理用】BR_260204!$B$3:$D$20,3,FALSE)*T28,"-") -> 0 | AG28: =IFERROR(VLOOKUP($N28,【管理用】BR_260204!$B$3:$D$20,3,FALSE)*U28,"-") -> 0 | AH28: =IFERROR(VLOOKUP($N28,【管理用】BR_260204!$B$3:$D$20,3,FALSE)*V28,"-") -> 0 | ... AL28: =IFERROR(VLOOKUP($N28,【管理用】BR_260204!$B$3:$D$20,3,FALSE)*Z28,"-") -> 0 | AM28: =SUM(AA28:AL28) -> 4393.1 | AN28: *
B29: =ROW(A29)-4 -> 25 | C29: 12 | D29: =IFERROR(VLOOKUP($C29,'【入力用②】案件ごと売上（D案件以上）'!$B$4:$Y$1048576,2,FALSE),"-") -> アートプレスト | E29: =IFERROR(VLOOKUP($C29,'【入力用②】案件ごと売上（D案件以上）'!$B$4:$Y$1048576,3,FALSE),"-") -> 2025年上期人事施策実行支援 | F29: =IFERROR(VLOOKUP($C29,'【入力用②】案件ごと売上（D案件以上）'!$B$4:$Y$1048576,4,FALSE),"-") -> 12_アートプレスト_2025年上期人事施策実行支援 | G29: =IFERROR(VLOOKUP($C29,'【入力用②】案件ごと売上（D案件以上）'!$B$4:$Y$1048576,5,FALSE),"-") -> その他 | H29: =IFERROR(VLOOKUP($C29,'【入力用②】案件ごと売上（D案件以上）'!$B$4:$Y$1048576,6,FALSE),"-") -> 成立 | I29: =IFERROR(VLOOKUP($C29,'【入力用②】案件ごと売上（D案件以上）'!$B$4:$Y$1048576,8,FALSE),"-") -> 6700 | J29: =SUMIF($C$5:$C$1048576,C29,$AM$5:$AM$1048576) -> 6688.1 | K29: =IFERROR(I29-J29,"-") -> 11.9 | L29: =IFERROR(VLOOKUP($C29,'【入力用②】案件ごと売上（D案件以上）'!$B$4:$Y$1048576,11,FALSE),"-") -> 1 | M29: =IFERROR(I29/L29,"-") -> 6700 | N29: 森田 | O29: 0.5 | AA29: =IFERROR(VLOOKUP($N29,【管理用】BR_260204!$B$3:$D$20,3,FALSE)*O29,"-") -> 1355 | AB29: =IFERROR(VLOOKUP($N29,【管理用】BR_260204!$B$3:$D$20,3,FALSE)*P29,"-") -> 0 | AC29: =IFERROR(VLOOKUP($N29,【管理用】BR_260204!$B$3:$D$20,3,FALSE)*Q29,"-") -> 0 | AD29: =IFERROR(VLOOKUP($N29,【管理用】BR_260204!$B$3:$D$20,3,FALSE)*R29,"-") -> 0 | AE29: =IFERROR(VLOOKUP($N29,【管理用】BR_260204!$B$3:$D$20,3,FALSE)*S29,"-") -> 0 | AF29: =IFERROR(VLOOKUP($N29,【管理用】BR_260204!$B$3:$D$20,3,FALSE)*T29,"-") -> 0 | AG29: =IFERROR(VLOOKUP($N29,【管理用】BR_260204!$B$3:$D$20,3,FALSE)*U29,"-") -> 0 | AH29: =IFERROR(VLOOKUP($N29,【管理用】BR_260204!$B$3:$D$20,3,FALSE)*V29,"-") -> 0 | ... AL29: =IFERROR(VLOOKUP($N29,【管理用】BR_260204!$B$3:$D$20,3,FALSE)*Z29,"-") -> 0 | AM29: =SUM(AA29:AL29) -> 1355 | AN29: *
B30: =ROW(A30)-4 -> 26 | C30: 12 | D30: =IFERROR(VLOOKUP($C30,'【入力用②】案件ごと売上（D案件以上）'!$B$4:$Y$1048576,2,FALSE),"-") -> アートプレスト | E30: =IFERROR(VLOOKUP($C30,'【入力用②】案件ごと売上（D案件以上）'!$B$4:$Y$1048576,3,FALSE),"-") -> 2025年上期人事施策実行支援 | F30: =IFERROR(VLOOKUP($C30,'【入力用②】案件ごと売上（D案件以上）'!$B$4:$Y$1048576,4,FALSE),"-") -> 12_アートプレスト_2025年上期人事施策実行支援 | G30: =IFERROR(VLOOKUP($C30,'【入力用②】案件ごと売上（D案件以上）'!$B$4:$Y$1048576,5,FALSE),"-") -> その他 | H30: =IFERROR(VLOOKUP($C30,'【入力用②】案件ごと売上（D案件以上）'!$B$4:$Y$1048576,6,FALSE),"-") -> 成立 | I30: =IFERROR(VLOOKUP($C30,'【入力用②】案件ごと売上（D案件以上）'!$B$4:$Y$1048576,8,FALSE),"-") -> 6700 | J30: =SUMIF($C$5:$C$1048576,C30,$AM$5:$AM$1048576) -> 6688.1 | K30: =IFERROR(I30-J30,"-") -> 11.9 | L30: =IFERROR(VLOOKUP($C30,'【入力用②】案件ごと売上（D案件以上）'!$B$4:$Y$1048576,11,FALSE),"-") -> 1 | M30: =IFERROR(I30/L30,"-") -> 6700 | N30: 丸田 | O30: 0.5 | AA30: =IFERROR(VLOOKUP($N30,【管理用】BR_260204!$B$3:$D$20,3,FALSE)*O30,"-") -> 940 | AB30: =IFERROR(VLOOKUP($N30,【管理用】BR_260204!$B$3:$D$20,3,FALSE)*P30,"-") -> 0 | AC30: =IFERROR(VLOOKUP($N30,【管理用】BR_260204!$B$3:$D$20,3,FALSE)*Q30,"-") -> 0 | AD30: =IFERROR(VLOOKUP($N30,【管理用】BR_260204!$B$3:$D$20,3,FALSE)*R30,"-") -> 0 | AE30: =IFERROR(VLOOKUP($N30,【管理用】BR_260204!$B$3:$D$20,3,FALSE)*S30,"-") -> 0 | AF30: =IFERROR(VLOOKUP($N30,【管理用】BR_260204!$B$3:$D$20,3,FALSE)*T30,"-") -> 0 | AG30: =IFERROR(VLOOKUP($N30,【管理用】BR_260204!$B$3:$D$20,3,FALSE)*U30,"-") -> 0 | AH30: =IFERROR(VLOOKUP($N30,【管理用】BR_260204!$B$3:$D$20,3,FALSE)*V30,"-") -> 0 | ... AL30: =IFERROR(VLOOKUP($N30,【管理用】BR_260204!$B$3:$D$20,3,FALSE)*Z30,"-") -> 0 | AM30: =SUM(AA30:AL30) -> 940 | AN30: *
B31: =ROW(A31)-4 -> 27 | C31: 13 | D31: =IFERROR(VLOOKUP($C31,'【入力用②】案件ごと売上（D案件以上）'!$B$4:$Y$1048576,2,FALSE),"-") -> アートプレスト | E31: =IFERROR(VLOOKUP($C31,'【入力用②】案件ごと売上（D案件以上）'!$B$4:$Y$1048576,3,FALSE),"-") -> 2025年下期人事施策実行支援 | F31: =IFERROR(VLOOKUP($C31,'【入力用②】案件ごと売上（D案件以上）'!$B$4:$Y$1048576,4,FALSE),"-") -> 13_アートプレスト_2025年下期人事施策実行支援 | G31: =IFERROR(VLOOKUP($C31,'【入力用②】案件ごと売上（D案件以上）'!$B$4:$Y$1048576,5,FALSE),"-") -> その他 | H31: =IFERROR(VLOOKUP($C31,'【入力用②】案件ごと売上（D案件以上）'!$B$4:$Y$1048576,6,FALSE),"-") -> 成立 | I31: =IFERROR(VLOOKUP($C31,'【入力用②】案件ごと売上（D案件以上）'!$B$4:$Y$1048576,8,FALSE),"-") -> 37900 | J31: =SUMIF($C$5:$C$1048576,C31,$AM$5:$AM$1048576) -> 37782.4 | K31: =IFERROR(I31-J31,"-") -> 117.6 | L31: =IFERROR(VLOOKUP($C31,'【入力用②】案件ごと売上（D案件以上）'!$B$4:$Y$1048576,11,FALSE),"-") -> 6 | M31: =IFERROR(I31/L31,"-") -> 6316.6667 | N31: 友祐 | P31: 2.16 | Q31: 2.09 | R31: 0.9 | S31: 1.46 | T31: 1.18 | U31: 0.59 | AA31: =IFERROR(VLOOKUP($N31,【管理用】BR_260204!$B$3:$D$20,3,FALSE)*O31,"-") -> 0 | AB31: =IFERROR(VLOOKUP($N31,【管理用】BR_260204!$B$3:$D$20,3,FALSE)*P31,"-") -> 4816.8 | AC31: =IFERROR(VLOOKUP($N31,【管理用】BR_260204!$B$3:$D$20,3,FALSE)*Q31,"-") -> 4660.7 | AD31: =IFERROR(VLOOKUP($N31,【管理用】BR_260204!$B$3:$D$20,3,FALSE)*R31,"-") -> 2007 | AE31: =IFERROR(VLOOKUP($N31,【管理用】BR_260204!$B$3:$D$20,3,FALSE)*S31,"-") -> 3255.8 | AF31: =IFERROR(VLOOKUP($N31,【管理用】BR_260204!$B$3:$D$20,3,FALSE)*T31,"-") -> 2631.4 | AG31: =IFERROR(VLOOKUP($N31,【管理用】BR_260204!$B$3:$D$20,3,FALSE)*U31,"-") -> 1315.7 | AH31: =IFERROR(VLOOKUP($N31,【管理用】BR_260204!$B$3:$D$20,3,FALSE)*V31,"-") -> 0 | ... AL31: =IFERROR(VLOOKUP($N31,【管理用】BR_260204!$B$3:$D$20,3,FALSE)*Z31,"-") -> 0 | AM31: =SUM(AA31:AL31) -> 18687.4 | AN31: *
B32: =ROW(A32)-4 -> 28 | C32: 13 | D32: =IFERROR(VLOOKUP($C32,'【入力用②】案件ごと売上（D案件以上）'!$B$4:$Y$1048576,2,FALSE),"-") -> アートプレスト | E32: =IFERROR(VLOOKUP($C32,'【入力用②】案件ごと売上（D案件以上）'!$B$4:$Y$1048576,3,FALSE),"-") -> 2025年下期人事施策実行支援 | F32: =IFERROR(VLOOKUP($C32,'【入力用②】案件ごと売上（D案件以上）'!$B$4:$Y$1048576,4,FALSE),"-") -> 13_アートプレスト_2025年下期人事施策実行支援 | G32: =IFERROR(VLOOKUP($C32,'【入力用②】案件ごと売上（D案件以上）'!$B$4:$Y$1048576,5,FALSE),"-") -> その他 | H32: =IFERROR(VLOOKUP($C32,'【入力用②】案件ごと売上（D案件以上）'!$B$4:$Y$1048576,6,FALSE),"-") -> 成立 | I32: =IFERROR(VLOOKUP($C32,'【入力用②】案件ごと売上（D案件以上）'!$B$4:$Y$1048576,8,FALSE),"-") -> 37900 | J32: =SUMIF($C$5:$C$1048576,C32,$AM$5:$AM$1048576) -> 37782.4 | K32: =IFERROR(I32-J32,"-") -> 117.6 | L32: =IFERROR(VLOOKUP($C32,'【入力用②】案件ごと売上（D案件以上）'!$B$4:$Y$1048576,11,FALSE),"-") -> 6 | M32: =IFERROR(I32/L32,"-") -> 6316.6667 | N32: 森田 | P32: 0.7 | Q32: 0.7 | R32: 0.7 | S32: 0.5 | AA32: =IFERROR(VLOOKUP($N32,【管理用】BR_260204!$B$3:$D$20,3,FALSE)*O32,"-") -> 0 | AB32: =IFERROR(VLOOKUP($N32,【管理用】BR_260204!$B$3:$D$20,3,FALSE)*P32,"-") -> 1897 | AC32: =IFERROR(VLOOKUP($N32,【管理用】BR_260204!$B$3:$D$20,3,FALSE)*Q32,"-") -> 1897 | AD32: =IFERROR(VLOOKUP($N32,【管理用】BR_260204!$B$3:$D$20,3,FALSE)*R32,"-") -> 1897 | AE32: =IFERROR(VLOOKUP($N32,【管理用】BR_260204!$B$3:$D$20,3,FALSE)*S32,"-") -> 1355 | AF32: =IFERROR(VLOOKUP($N32,【管理用】BR_260204!$B$3:$D$20,3,FALSE)*T32,"-") -> 0 | AG32: =IFERROR(VLOOKUP($N32,【管理用】BR_260204!$B$3:$D$20,3,FALSE)*U32,"-") -> 0 | AH32: =IFERROR(VLOOKUP($N32,【管理用】BR_260204!$B$3:$D$20,3,FALSE)*V32,"-") -> 0 | ... AL32: =IFERROR(VLOOKUP($N32,【管理用】BR_260204!$B$3:$D$20,3,FALSE)*Z32,"-") -> 0 | AM32: =SUM(AA32:AL32) -> 7046 | AN32: *
B33: =ROW(A33)-4 -> 29 | C33: 13 | D33: =IFERROR(VLOOKUP($C33,'【入力用②】案件ごと売上（D案件以上）'!$B$4:$Y$1048576,2,FALSE),"-") -> アートプレスト | E33: =IFERROR(VLOOKUP($C33,'【入力用②】案件ごと売上（D案件以上）'!$B$4:$Y$1048576,3,FALSE),"-") -> 2025年下期人事施策実行支援 | F33: =IFERROR(VLOOKUP($C33,'【入力用②】案件ごと売上（D案件以上）'!$B$4:$Y$1048576,4,FALSE),"-") -> 13_アートプレスト_2025年下期人事施策実行支援 | G33: =IFERROR(VLOOKUP($C33,'【入力用②】案件ごと売上（D案件以上）'!$B$4:$Y$1048576,5,FALSE),"-") -> その他 | H33: =IFERROR(VLOOKUP($C33,'【入力用②】案件ごと売上（D案件以上）'!$B$4:$Y$1048576,6,FALSE),"-") -> 成立 | I33: =IFERROR(VLOOKUP($C33,'【入力用②】案件ごと売上（D案件以上）'!$B$4:$Y$1048576,8,FALSE),"-") -> 37900 | J33: =SUMIF($C$5:$C$1048576,C33,$AM$5:$AM$1048576) -> 37782.4 | K33: =IFERROR(I33-J33,"-") -> 117.6 | L33: =IFERROR(VLOOKUP($C33,'【入力用②】案件ごと売上（D案件以上）'!$B$4:$Y$1048576,11,FALSE),"-") -> 6 | M33: =IFERROR(I33/L33,"-") -> 6316.6667 | N33: 丸田 | P33: 0.4 | Q33: 0.4 | R33: 0.3 | S33: 0.4 | T33: 0.4 | U33: 0.4 | AA33: =IFERROR(VLOOKUP($N33,【管理用】BR_260204!$B$3:$D$20,3,FALSE)*O33,"-") -> 0 | AB33: =IFERROR(VLOOKUP($N33,【管理用】BR_260204!$B$3:$D$20,3,FALSE)*P33,"-") -> 752 | AC33: =IFERROR(VLOOKUP($N33,【管理用】BR_260204!$B$3:$D$20,3,FALSE)*Q33,"-") -> 752 | AD33: =IFERROR(VLOOKUP($N33,【管理用】BR_260204!$B$3:$D$20,3,FALSE)*R33,"-") -> 564 | AE33: =IFERROR(VLOOKUP($N33,【管理用】BR_260204!$B$3:$D$20,3,FALSE)*S33,"-") -> 752 | AF33: =IFERROR(VLOOKUP($N33,【管理用】BR_260204!$B$3:$D$20,3,FALSE)*T33,"-") -> 752 | AG33: =IFERROR(VLOOKUP($N33,【管理用】BR_260204!$B$3:$D$20,3,FALSE)*U33,"-") -> 752 | AH33: =IFERROR(VLOOKUP($N33,【管理用】BR_260204!$B$3:$D$20,3,FALSE)*V33,"-") -> 0 | ... AL33: =IFERROR(VLOOKUP($N33,【管理用】BR_260204!$B$3:$D$20,3,FALSE)*Z33,"-") -> 0 | AM33: =SUM(AA33:AL33) -> 4324 | AN33: *
B34: =ROW(A34)-4 -> 30 | C34: 13 | D34: =IFERROR(VLOOKUP($C34,'【入力用②】案件ごと売上（D案件以上）'!$B$4:$Y$1048576,2,FALSE),"-") -> アートプレスト | E34: =IFERROR(VLOOKUP($C34,'【入力用②】案件ごと売上（D案件以上）'!$B$4:$Y$1048576,3,FALSE),"-") -> 2025年下期人事施策実行支援 | F34: =IFERROR(VLOOKUP($C34,'【入力用②】案件ごと売上（D案件以上）'!$B$4:$Y$1048576,4,FALSE),"-") -> 13_アートプレスト_2025年下期人事施策実行支援 | G34: =IFERROR(VLOOKUP($C34,'【入力用②】案件ごと売上（D案件以上）'!$B$4:$Y$1048576,5,FALSE),"-") -> その他 | H34: =IFERROR(VLOOKUP($C34,'【入力用②】案件ごと売上（D案件以上）'!$B$4:$Y$1048576,6,FALSE),"-") -> 成立 | I34: =IFERROR(VLOOKUP($C34,'【入力用②】案件ごと売上（D案件以上）'!$B$4:$Y$1048576,8,FALSE),"-") -> 37900 | J34: =SUMIF($C$5:$C$1048576,C34,$AM$5:$AM$1048576) -> 37782.4 | K34: =IFERROR(I34-J34,"-") -> 117.6 | L34: =IFERROR(VLOOKUP($C34,'【入力用②】案件ごと売上（D案件以上）'!$B$4:$Y$1048576,11,FALSE),"-") -> 6 | M34: =IFERROR(I34/L34,"-") -> 6316.6667 | N34: 外部 | P34: 0.5 | Q34: 0.5 | R34: 0.5 | S34: 0.75 | T34: 0.75 | U34: 0.75 | AA34: =IFERROR(VLOOKUP($N34,【管理用】BR_260204!$B$3:$D$20,3,FALSE)*O34,"-") -> 0 | AB34: =IFERROR(VLOOKUP($N34,【管理用】BR_260204!$B$3:$D$20,3,FALSE)*P34,"-") -> 500 | AC34: =IFERROR(VLOOKUP($N34,【管理用】BR_260204!$B$3:$D$20,3,FALSE)*Q34,"-") -> 500 | AD34: =IFERROR(VLOOKUP($N34,【管理用】BR_260204!$B$3:$D$20,3,FALSE)*R34,"-") -> 500 | AE34: =IFERROR(VLOOKUP($N34,【管理用】BR_260204!$B$3:$D$20,3,FALSE)*S34,"-") -> 750 | AF34: =IFERROR(VLOOKUP($N34,【管理用】BR_260204!$B$3:$D$20,3,FALSE)*T34,"-") -> 750 | AG34: =IFERROR(VLOOKUP($N34,【管理用】BR_260204!$B$3:$D$20,3,FALSE)*U34,"-") -> 750 | AH34: =IFERROR(VLOOKUP($N34,【管理用】BR_260204!$B$3:$D$20,3,FALSE)*V34,"-") -> 0 | ... AL34: =IFERROR(VLOOKUP($N34,【管理用】BR_260204!$B$3:$D$20,3,FALSE)*Z34,"-") -> 0 | AM34: =SUM(AA34:AL34) -> 3750 | AN34: *
B35: =ROW(A35)-4 -> 31 | C35: 13 | D35: =IFERROR(VLOOKUP($C35,'【入力用②】案件ごと売上（D案件以上）'!$B$4:$Y$1048576,2,FALSE),"-") -> アートプレスト | E35: =IFERROR(VLOOKUP($C35,'【入力用②】案件ごと売上（D案件以上）'!$B$4:$Y$1048576,3,FALSE),"-") -> 2025年下期人事施策実行支援 | F35: =IFERROR(VLOOKUP($C35,'【入力用②】案件ごと売上（D案件以上）'!$B$4:$Y$1048576,4,FALSE),"-") -> 13_アートプレスト_2025年下期人事施策実行支援 | G35: =IFERROR(VLOOKUP($C35,'【入力用②】案件ごと売上（D案件以上）'!$B$4:$Y$1048576,5,FALSE),"-") -> その他 | H35: =IFERROR(VLOOKUP($C35,'【入力用②】案件ごと売上（D案件以上）'!$B$4:$Y$1048576,6,FALSE),"-") -> 成立 | I35: =IFERROR(VLOOKUP($C35,'【入力用②】案件ごと売上（D案件以上）'!$B$4:$Y$1048576,8,FALSE),"-") -> 37900 | J35: =SUMIF($C$5:$C$1048576,C35,$AM$5:$AM$1048576) -> 37782.4 | K35: =IFERROR(I35-J35,"-") -> 117.6 | L35: =IFERROR(VLOOKUP($C35,'【入力用②】案件ごと売上（D案件以上）'!$B$4:$Y$1048576,11,FALSE),"-") -> 6 | M35: =IFERROR(I35/L35,"-") -> 6316.6667 | N35: 加藤 | T35: 0.1 | AA35: =IFERROR(VLOOKUP($N35,【管理用】BR_260204!$B$3:$D$20,3,FALSE)*O35,"-") -> 0 | AB35: =IFERROR(VLOOKUP($N35,【管理用】BR_260204!$B$3:$D$20,3,FALSE)*P35,"-") -> 0 | AC35: =IFERROR(VLOOKUP($N35,【管理用】BR_260204!$B$3:$D$20,3,FALSE)*Q35,"-") -> 0 | AD35: =IFERROR(VLOOKUP($N35,【管理用】BR_260204!$B$3:$D$20,3,FALSE)*R35,"-") -> 0 | AE35: =IFERROR(VLOOKUP($N35,【管理用】BR_260204!$B$3:$D$20,3,FALSE)*S35,"-") -> 0 | AF35: =IFERROR(VLOOKUP($N35,【管理用】BR_260204!$B$3:$D$20,3,FALSE)*T35,"-") -> 175 | AG35: =IFERROR(VLOOKUP($N35,【管理用】BR_260204!$B$3:$D$20,3,FALSE)*U35,"-") -> 0 | AH35: =IFERROR(VLOOKUP($N35,【管理用】BR_260204!$B$3:$D$20,3,FALSE)*V35,"-") -> 0 | ... AL35: =IFERROR(VLOOKUP($N35,【管理用】BR_260204!$B$3:$D$20,3,FALSE)*Z35,"-") -> 0 | AM35: =SUM(AA35:AL35) -> 175 | AN35: *
B36: =ROW(A36)-4 -> 32 | C36: 13 | D36: =IFERROR(VLOOKUP($C36,'【入力用②】案件ごと売上（D案件以上）'!$B$4:$Y$1048576,2,FALSE),"-") -> アートプレスト | E36: =IFERROR(VLOOKUP($C36,'【入力用②】案件ごと売上（D案件以上）'!$B$4:$Y$1048576,3,FALSE),"-") -> 2025年下期人事施策実行支援 | F36: =IFERROR(VLOOKUP($C36,'【入力用②】案件ごと売上（D案件以上）'!$B$4:$Y$1048576,4,FALSE),"-") -> 13_アートプレスト_2025年下期人事施策実行支援 | G36: =IFERROR(VLOOKUP($C36,'【入力用②】案件ごと売上（D案件以上）'!$B$4:$Y$1048576,5,FALSE),"-") -> その他 | H36: =IFERROR(VLOOKUP($C36,'【入力用②】案件ごと売上（D案件以上）'!$B$4:$Y$1048576,6,FALSE),"-") -> 成立 | I36: =IFERROR(VLOOKUP($C36,'【入力用②】案件ごと売上（D案件以上）'!$B$4:$Y$1048576,8,FALSE),"-") -> 37900 | J36: =SUMIF($C$5:$C$1048576,C36,$AM$5:$AM$1048576) -> 37782.4 | K36: =IFERROR(I36-J36,"-") -> 117.6 | L36: =IFERROR(VLOOKUP($C36,'【入力用②】案件ごと売上（D案件以上）'!$B$4:$Y$1048576,11,FALSE),"-") -> 6 | M36: =IFERROR(I36/L36,"-") -> 6316.6667 | N36: 古藤 | T36: 0.5 | U36: 0.5 | AA36: =IFERROR(VLOOKUP($N36,【管理用】BR_260204!$B$3:$D$20,3,FALSE)*O36,"-") -> 0 | AB36: =IFERROR(VLOOKUP($N36,【管理用】BR_260204!$B$3:$D$20,3,FALSE)*P36,"-") -> 0 | AC36: =IFERROR(VLOOKUP($N36,【管理用】BR_260204!$B$3:$D$20,3,FALSE)*Q36,"-") -> 0 | AD36: =IFERROR(VLOOKUP($N36,【管理用】BR_260204!$B$3:$D$20,3,FALSE)*R36,"-") -> 0 | AE36: =IFERROR(VLOOKUP($N36,【管理用】BR_260204!$B$3:$D$20,3,FALSE)*S36,"-") -> 0 | AF36: =IFERROR(VLOOKUP($N36,【管理用】BR_260204!$B$3:$D$20,3,FALSE)*T36,"-") -> 1900 | AG36: =IFERROR(VLOOKUP($N36,【管理用】BR_260204!$B$3:$D$20,3,FALSE)*U36,"-") -> 1900 | AH36: =IFERROR(VLOOKUP($N36,【管理用】BR_260204!$B$3:$D$20,3,FALSE)*V36,"-") -> 0 | ... AL36: =IFERROR(VLOOKUP($N36,【管理用】BR_260204!$B$3:$D$20,3,FALSE)*Z36,"-") -> 0 | AM36: =SUM(AA36:AL36) -> 3800 | AN36: *
B37: =ROW(A37)-4 -> 33 | C37: 13 | D37: =IFERROR(VLOOKUP($C37,'【入力用②】案件ごと売上（D案件以上）'!$B$4:$Y$1048576,2,FALSE),"-") -> アートプレスト | E37: =IFERROR(VLOOKUP($C37,'【入力用②】案件ごと売上（D案件以上）'!$B$4:$Y$1048576,3,FALSE),"-") -> 2025年下期人事施策実行支援 | F37: =IFERROR(VLOOKUP($C37,'【入力用②】案件ごと売上（D案件以上）'!$B$4:$Y$1048576,4,FALSE),"-") -> 13_アートプレスト_2025年下期人事施策実行支援 | G37: =IFERROR(VLOOKUP($C37,'【入力用②】案件ごと売上（D案件以上）'!$B$4:$Y$1048576,5,FALSE),"-") -> その他 | H37: =IFERROR(VLOOKUP($C37,'【入力用②】案件ごと売上（D案件以上）'!$B$4:$Y$1048576,6,FALSE),"-") -> 成立 | I37: =IFERROR(VLOOKUP($C37,'【入力用②】案件ごと売上（D案件以上）'!$B$4:$Y$1048576,8,FALSE),"-") -> 37900 | J37: =SUMIF($C$5:$C$1048576,C37,$AM$5:$AM$1048576) -> 37782.4 | K37: =IFERROR(I37-J37,"-") -> 117.6 | L37: =IFERROR(VLOOKUP($C37,'【入力用②】案件ごと売上（D案件以上）'!$B$4:$Y$1048576,11,FALSE),"-") -> 6 | M37: =IFERROR(I37/L37,"-") -> 6316.6667 | N37: 弓本 | AA37: =IFERROR(VLOOKUP($N37,【管理用】BR_260204!$B$3:$D$20,3,FALSE)*O37,"-") -> 0 | AB37: =IFERROR(VLOOKUP($N37,【管理用】BR_260204!$B$3:$D$20,3,FALSE)*P37,"-") -> 0 | AC37: =IFERROR(VLOOKUP($N37,【管理用】BR_260204!$B$3:$D$20,3,FALSE)*Q37,"-") -> 0 | AD37: =IFERROR(VLOOKUP($N37,【管理用】BR_260204!$B$3:$D$20,3,FALSE)*R37,"-") -> 0 | AE37: =IFERROR(VLOOKUP($N37,【管理用】BR_260204!$B$3:$D$20,3,FALSE)*S37,"-") -> 0 | AF37: =IFERROR(VLOOKUP($N37,【管理用】BR_260204!$B$3:$D$20,3,FALSE)*T37,"-") -> 0 | AG37: =IFERROR(VLOOKUP($N37,【管理用】BR_260204!$B$3:$D$20,3,FALSE)*U37,"-") -> 0 | AH37: =IFERROR(VLOOKUP($N37,【管理用】BR_260204!$B$3:$D$20,3,FALSE)*V37,"-") -> 0 | ... AL37: =IFERROR(VLOOKUP($N37,【管理用】BR_260204!$B$3:$D$20,3,FALSE)*Z37,"-") -> 0 | AM37: =SUM(AA37:AL37) -> 0 | AN37: *
B38: =ROW(A38)-4 -> 34 | C38: 14 | D38: =IFERROR(VLOOKUP($C38,'【入力用②】案件ごと売上（D案件以上）'!$B$4:$Y$1048576,2,FALSE),"-") -> アートプレスト | E38: =IFERROR(VLOOKUP($C38,'【入力用②】案件ごと売上（D案件以上）'!$B$4:$Y$1048576,3,FALSE),"-") -> 経営層候補者向け研修実行支援 | F38: =IFERROR(VLOOKUP($C38,'【入力用②】案件ごと売上（D案件以上）'!$B$4:$Y$1048576,4,FALSE),"-") -> 14_アートプレスト_経営層候補者向け研修実行支援 | G38: =IFERROR(VLOOKUP($C38,'【入力用②】案件ごと売上（D案件以上）'!$B$4:$Y$1048576,5,FALSE),"-") -> 人材育成 | H38: =IFERROR(VLOOKUP($C38,'【入力用②】案件ごと売上（D案件以上）'!$B$4:$Y$1048576,6,FALSE),"-") -> 成立 | I38: =IFERROR(VLOOKUP($C38,'【入力用②】案件ごと売上（D案件以上）'!$B$4:$Y$1048576,8,FALSE),"-") -> 250 | J38: =SUMIF($C$5:$C$1048576,C38,$AM$5:$AM$1048576) -> 249.76 | K38: =IFERROR(I38-J38,"-") -> 0.24 | L38: =IFERROR(VLOOKUP($C38,'【入力用②】案件ごと売上（D案件以上）'!$B$4:$Y$1048576,11,FALSE),"-") -> 1 | M38: =IFERROR(I38/L38,"-") -> 250 | N38: 友祐 | Q38: 0.112 | AA38: =IFERROR(VLOOKUP($N38,【管理用】BR_260204!$B$3:$D$20,3,FALSE)*O38,"-") -> 0 | AB38: =IFERROR(VLOOKUP($N38,【管理用】BR_260204!$B$3:$D$20,3,FALSE)*P38,"-") -> 0 | AC38: =IFERROR(VLOOKUP($N38,【管理用】BR_260204!$B$3:$D$20,3,FALSE)*Q38,"-") -> 249.76 | AD38: =IFERROR(VLOOKUP($N38,【管理用】BR_260204!$B$3:$D$20,3,FALSE)*R38,"-") -> 0 | AE38: =IFERROR(VLOOKUP($N38,【管理用】BR_260204!$B$3:$D$20,3,FALSE)*S38,"-") -> 0 | AF38: =IFERROR(VLOOKUP($N38,【管理用】BR_260204!$B$3:$D$20,3,FALSE)*T38,"-") -> 0 | AG38: =IFERROR(VLOOKUP($N38,【管理用】BR_260204!$B$3:$D$20,3,FALSE)*U38,"-") -> 0 | AH38: =IFERROR(VLOOKUP($N38,【管理用】BR_260204!$B$3:$D$20,3,FALSE)*V38,"-") -> 0 | ... AL38: =IFERROR(VLOOKUP($N38,【管理用】BR_260204!$B$3:$D$20,3,FALSE)*Z38,"-") -> 0 | AM38: =SUM(AA38:AL38) -> 249.76 | AN38: *
B39: =ROW(A39)-4 -> 35 | C39: 15 | D39: =IFERROR(VLOOKUP($C39,'【入力用②】案件ごと売上（D案件以上）'!$B$4:$Y$1048576,2,FALSE),"-") -> アートプレスト | E39: =IFERROR(VLOOKUP($C39,'【入力用②】案件ごと売上（D案件以上）'!$B$4:$Y$1048576,3,FALSE),"-") -> 役員研修 | F39: =IFERROR(VLOOKUP($C39,'【入力用②】案件ごと売上（D案件以上）'!$B$4:$Y$1048576,4,FALSE),"-") -> 15_アートプレスト_役員研修 | G39: =IFERROR(VLOOKUP($C39,'【入力用②】案件ごと売上（D案件以上）'!$B$4:$Y$1048576,5,FALSE),"-") -> 人材育成 | H39: =IFERROR(VLOOKUP($C39,'【入力用②】案件ごと売上（D案件以上）'!$B$4:$Y$1048576,6,FALSE),"-") -> 成立 | I39: =IFERROR(VLOOKUP($C39,'【入力用②】案件ごと売上（D案件以上）'!$B$4:$Y$1048576,8,FALSE),"-") -> 100 | J39: =SUMIF($C$5:$C$1048576,C39,$AM$5:$AM$1048576) -> 100.35 | K39: =IFERROR(I39-J39,"-") -> -0.35 | L39: =IFERROR(VLOOKUP($C39,'【入力用②】案件ごと売上（D案件以上）'!$B$4:$Y$1048576,11,FALSE),"-") -> 1 | M39: =IFERROR(I39/L39,"-") -> 100 | N39: 友祐 | P39: 0.045 | AA39: =IFERROR(VLOOKUP($N39,【管理用】BR_260204!$B$3:$D$20,3,FALSE)*O39,"-") -> 0 | AB39: =IFERROR(VLOOKUP($N39,【管理用】BR_260204!$B$3:$D$20,3,FALSE)*P39,"-") -> 100.35 | AC39: =IFERROR(VLOOKUP($N39,【管理用】BR_260204!$B$3:$D$20,3,FALSE)*Q39,"-") -> 0 | AD39: =IFERROR(VLOOKUP($N39,【管理用】BR_260204!$B$3:$D$20,3,FALSE)*R39,"-") -> 0 | AE39: =IFERROR(VLOOKUP($N39,【管理用】BR_260204!$B$3:$D$20,3,FALSE)*S39,"-") -> 0 | AF39: =IFERROR(VLOOKUP($N39,【管理用】BR_260204!$B$3:$D$20,3,FALSE)*T39,"-") -> 0 | AG39: =IFERROR(VLOOKUP($N39,【管理用】BR_260204!$B$3:$D$20,3,FALSE)*U39,"-") -> 0 | AH39: =IFERROR(VLOOKUP($N39,【管理用】BR_260204!$B$3:$D$20,3,FALSE)*V39,"-") -> 0 | ... AL39: =IFERROR(VLOOKUP($N39,【管理用】BR_260204!$B$3:$D$20,3,FALSE)*Z39,"-") -> 0 | AM39: =SUM(AA39:AL39) -> 100.35 | AN39: *
B40: =ROW(A40)-4 -> 36 | C40: 16 | D40: =IFERROR(VLOOKUP($C40,'【入力用②】案件ごと売上（D案件以上）'!$B$4:$Y$1048576,2,FALSE),"-") -> JALUX | E40: =IFERROR(VLOOKUP($C40,'【入力用②】案件ごと売上（D案件以上）'!$B$4:$Y$1048576,3,FALSE),"-") -> ビジネス変革Community | F40: =IFERROR(VLOOKUP($C40,'【入力用②】案件ごと売上（D案件以上）'!$B$4:$Y$1048576,4,FALSE),"-") -> 16_JALUX_ビジネス変革Community | G40: =IFERROR(VLOOKUP($C40,'【入力用②】案件ごと売上（D案件以上）'!$B$4:$Y$1048576,5,FALSE),"-") -> その他 | H40: =IFERROR(VLOOKUP($C40,'【入力用②】案件ごと売上（D案件以上）'!$B$4:$Y$1048576,6,FALSE),"-") -> 成立 | I40: =IFERROR(VLOOKUP($C40,'【入力用②】案件ごと売上（D案件以上）'!$B$4:$Y$1048576,8,FALSE),"-") -> 750 | J40: 750 | K40: =IFERROR(I40-J40,"-") -> 0 | L40: =IFERROR(VLOOKUP($C40,'【入力用②】案件ごと売上（D案件以上）'!$B$4:$Y$1048576,11,FALSE),"-") -> 1 | M40: =IFERROR(I40/L40,"-") -> 750 | N40: 波多野 | P40: 0.05 | AA40: =IFERROR(VLOOKUP($N40,【管理用】BR_260204!$B$3:$D$20,3,FALSE)*O40,"-") -> 0 | AB40: =IFERROR(VLOOKUP($N40,【管理用】BR_260204!$B$3:$D$20,3,FALSE)*P40,"-") -> 425 | AC40: =IFERROR(VLOOKUP($N40,【管理用】BR_260204!$B$3:$D$20,3,FALSE)*Q40,"-") -> 0 | AD40: =IFERROR(VLOOKUP($N40,【管理用】BR_260204!$B$3:$D$20,3,FALSE)*R40,"-") -> 0 | AE40: =IFERROR(VLOOKUP($N40,【管理用】BR_260204!$B$3:$D$20,3,FALSE)*S40,"-") -> 0 | AF40: =IFERROR(VLOOKUP($N40,【管理用】BR_260204!$B$3:$D$20,3,FALSE)*T40,"-") -> 0 | AG40: =IFERROR(VLOOKUP($N40,【管理用】BR_260204!$B$3:$D$20,3,FALSE)*U40,"-") -> 0 | AH40: =IFERROR(VLOOKUP($N40,【管理用】BR_260204!$B$3:$D$20,3,FALSE)*V40,"-") -> 0 | ... AL40: =IFERROR(VLOOKUP($N40,【管理用】BR_260204!$B$3:$D$20,3,FALSE)*Z40,"-") -> 0 | AM40: =SUM(AA40:AL40) -> 425 | AN40: *
B41: =ROW(A41)-4 -> 37 | C41: 16 | D41: =IFERROR(VLOOKUP($C41,'【入力用②】案件ごと売上（D案件以上）'!$B$4:$Y$1048576,2,FALSE),"-") -> JALUX | E41: =IFERROR(VLOOKUP($C41,'【入力用②】案件ごと売上（D案件以上）'!$B$4:$Y$1048576,3,FALSE),"-") -> ビジネス変革Community | F41: =IFERROR(VLOOKUP($C41,'【入力用②】案件ごと売上（D案件以上）'!$B$4:$Y$1048576,4,FALSE),"-") -> 16_JALUX_ビジネス変革Community | G41: =IFERROR(VLOOKUP($C41,'【入力用②】案件ごと売上（D案件以上）'!$B$4:$Y$1048576,5,FALSE),"-") -> その他 | H41: =IFERROR(VLOOKUP($C41,'【入力用②】案件ごと売上（D案件以上）'!$B$4:$Y$1048576,6,FALSE),"-") -> 成立 | I41: =IFERROR(VLOOKUP($C41,'【入力用②】案件ごと売上（D案件以上）'!$B$4:$Y$1048576,8,FALSE),"-") -> 750 | J41: 750 | K41: =IFERROR(I41-J41,"-") -> 0 | L41: =IFERROR(VLOOKUP($C41,'【入力用②】案件ごと売上（D案件以上）'!$B$4:$Y$1048576,11,FALSE),"-") -> 1 | M41: =IFERROR(I41/L41,"-") -> 750 | N41: 森田 | P41: 0.212 | AA41: =IFERROR(VLOOKUP($N41,【管理用】BR_260204!$B$3:$D$20,3,FALSE)*O41,"-") -> 0 | AB41: =IFERROR(VLOOKUP($N41,【管理用】BR_260204!$B$3:$D$20,3,FALSE)*P41,"-") -> 574.52 | AC41: =IFERROR(VLOOKUP($N41,【管理用】BR_260204!$B$3:$D$20,3,FALSE)*Q41,"-") -> 0 | AD41: =IFERROR(VLOOKUP($N41,【管理用】BR_260204!$B$3:$D$20,3,FALSE)*R41,"-") -> 0 | AE41: =IFERROR(VLOOKUP($N41,【管理用】BR_260204!$B$3:$D$20,3,FALSE)*S41,"-") -> 0 | AF41: =IFERROR(VLOOKUP($N41,【管理用】BR_260204!$B$3:$D$20,3,FALSE)*T41,"-") -> 0 | AG41: =IFERROR(VLOOKUP($N41,【管理用】BR_260204!$B$3:$D$20,3,FALSE)*U41,"-") -> 0 | AH41: =IFERROR(VLOOKUP($N41,【管理用】BR_260204!$B$3:$D$20,3,FALSE)*V41,"-") -> 0 | ... AL41: =IFERROR(VLOOKUP($N41,【管理用】BR_260204!$B$3:$D$20,3,FALSE)*Z41,"-") -> 0 | AM41: =SUM(AA41:AL41) -> 574.52 | AN41: *
B42: =ROW(A42)-4 -> 38 | C42: 17 | D42: =IFERROR(VLOOKUP($C42,'【入力用②】案件ごと売上（D案件以上）'!$B$4:$Y$1048576,2,FALSE),"-") -> JALUX | E42: =IFERROR(VLOOKUP($C42,'【入力用②】案件ごと売上（D案件以上）'!$B$4:$Y$1048576,3,FALSE),"-") -> 業務効率化 | F42: =IFERROR(VLOOKUP($C42,'【入力用②】案件ごと売上（D案件以上）'!$B$4:$Y$1048576,4,FALSE),"-") -> 17_JALUX_業務効率化 | G42: =IFERROR(VLOOKUP($C42,'【入力用②】案件ごと売上（D案件以上）'!$B$4:$Y$1048576,5,FALSE),"-") -> その他 | H42: =IFERROR(VLOOKUP($C42,'【入力用②】案件ごと売上（D案件以上）'!$B$4:$Y$1048576,6,FALSE),"-") -> 成立 | I42: =IFERROR(VLOOKUP($C42,'【入力用②】案件ごと売上（D案件以上）'!$B$4:$Y$1048576,8,FALSE),"-") -> 920 | J42: =SUMIF($C$5:$C$1048576,C42,$AM$5:$AM$1048576) -> 271 | K42: =IFERROR(I42-J42,"-") -> 649 | L42: =IFERROR(VLOOKUP($C42,'【入力用②】案件ごと売上（D案件以上）'!$B$4:$Y$1048576,11,FALSE),"-") -> 2 | M42: =IFERROR(I42/L42,"-") -> 460 | N42: 森田 | O42: 0.05 | P42: 0.05 | AA42: =IFERROR(VLOOKUP($N42,【管理用】BR_260204!$B$3:$D$20,3,FALSE)*O42,"-") -> 135.5 | AB42: =IFERROR(VLOOKUP($N42,【管理用】BR_260204!$B$3:$D$20,3,FALSE)*P42,"-") -> 135.5 | AC42: =IFERROR(VLOOKUP($N42,【管理用】BR_260204!$B$3:$D$20,3,FALSE)*Q42,"-") -> 0 | AD42: =IFERROR(VLOOKUP($N42,【管理用】BR_260204!$B$3:$D$20,3,FALSE)*R42,"-") -> 0 | AE42: =IFERROR(VLOOKUP($N42,【管理用】BR_260204!$B$3:$D$20,3,FALSE)*S42,"-") -> 0 | AF42: =IFERROR(VLOOKUP($N42,【管理用】BR_260204!$B$3:$D$20,3,FALSE)*T42,"-") -> 0 | AG42: =IFERROR(VLOOKUP($N42,【管理用】BR_260204!$B$3:$D$20,3,FALSE)*U42,"-") -> 0 | AH42: =IFERROR(VLOOKUP($N42,【管理用】BR_260204!$B$3:$D$20,3,FALSE)*V42,"-") -> 0 | ... AL42: =IFERROR(VLOOKUP($N42,【管理用】BR_260204!$B$3:$D$20,3,FALSE)*Z42,"-") -> 0 | AM42: =SUM(AA42:AL42) -> 271 | AN42: *
B43: =ROW(A43)-4 -> 39 | C43: 18 | D43: =IFERROR(VLOOKUP($C43,'【入力用②】案件ごと売上（D案件以上）'!$B$4:$Y$1048576,2,FALSE),"-") -> パラマウントベッド | E43: =IFERROR(VLOOKUP($C43,'【入力用②】案件ごと売上（D案件以上）'!$B$4:$Y$1048576,3,FALSE),"-") -> 管理職WS＆部門幹部ディスカッション | F43: =IFERROR(VLOOKUP($C43,'【入力用②】案件ごと売上（D案件以上）'!$B$4:$Y$1048576,4,FALSE),"-") -> 18_パラマウントベッド_管理職WS＆部門幹部ディスカッション | G43: =IFERROR(VLOOKUP($C43,'【入力用②】案件ごと売上（D案件以上）'!$B$4:$Y$1048576,5,FALSE),"-") -> その他 | H43: =IFERROR(VLOOKUP($C43,'【入力用②】案件ごと売上（D案件以上）'!$B$4:$Y$1048576,6,FALSE),"-") -> 成立 | I43: =IFERROR(VLOOKUP($C43,'【入力用②】案件ごと売上（D案件以上）'!$B$4:$Y$1048576,8,FALSE),"-") -> 4470 | J43: =SUMIF($C$5:$C$1048576,C43,$AM$5:$AM$1048576) -> 2669.6 | K43: =IFERROR(I43-J43,"-") -> 1800.4 | L43: =IFERROR(VLOOKUP($C43,'【入力用②】案件ごと売上（D案件以上）'!$B$4:$Y$1048576,11,FALSE),"-") -> 4 | M43: =IFERROR(I43/L43,"-") -> 1117.5 | N43: 丸田 | P43: 1 | R43: 0.42 | AA43: =IFERROR(VLOOKUP($N43,【管理用】BR_260204!$B$3:$D$20,3,FALSE)*O43,"-") -> 0 | AB43: =IFERROR(VLOOKUP($N43,【管理用】BR_260204!$B$3:$D$20,3,FALSE)*P43,"-") -> 1880 | AC43: =IFERROR(VLOOKUP($N43,【管理用】BR_260204!$B$3:$D$20,3,FALSE)*Q43,"-") -> 0 | AD43: =IFERROR(VLOOKUP($N43,【管理用】BR_260204!$B$3:$D$20,3,FALSE)*R43,"-") -> 789.6 | AE43: =IFERROR(VLOOKUP($N43,【管理用】BR_260204!$B$3:$D$20,3,FALSE)*S43,"-") -> 0 | AF43: =IFERROR(VLOOKUP($N43,【管理用】BR_260204!$B$3:$D$20,3,FALSE)*T43,"-") -> 0 | AG43: =IFERROR(VLOOKUP($N43,【管理用】BR_260204!$B$3:$D$20,3,FALSE)*U43,"-") -> 0 | AH43: =IFERROR(VLOOKUP($N43,【管理用】BR_260204!$B$3:$D$20,3,FALSE)*V43,"-") -> 0 | ... AL43: =IFERROR(VLOOKUP($N43,【管理用】BR_260204!$B$3:$D$20,3,FALSE)*Z43,"-") -> 0 | AM43: =SUM(AA43:AL43) -> 2669.6 | AN43: *
B44: =ROW(A44)-4 -> 40 | C44: 19 | D44: =IFERROR(VLOOKUP($C44,'【入力用②】案件ごと売上（D案件以上）'!$B$4:$Y$1048576,2,FALSE),"-") -> asics | E44: =IFERROR(VLOOKUP($C44,'【入力用②】案件ごと売上（D案件以上）'!$B$4:$Y$1048576,3,FALSE),"-") -> HRBP支援 | F44: =IFERROR(VLOOKUP($C44,'【入力用②】案件ごと売上（D案件以上）'!$B$4:$Y$1048576,4,FALSE),"-") -> 19_asics_HRBP支援 | G44: =IFERROR(VLOOKUP($C44,'【入力用②】案件ごと売上（D案件以上）'!$B$4:$Y$1048576,5,FALSE),"-") -> 組織開発 | H44: =IFERROR(VLOOKUP($C44,'【入力用②】案件ごと売上（D案件以上）'!$B$4:$Y$1048576,6,FALSE),"-") -> 成立 | I44: =IFERROR(VLOOKUP($C44,'【入力用②】案件ごと売上（D案件以上）'!$B$4:$Y$1048576,8,FALSE),"-") -> 400 | J44: =SUMIF($C$5:$C$1048576,C44,$AM$5:$AM$1048576) -> 398.88 | K44: =IFERROR(I44-J44,"-") -> 1.12 | L44: =IFERROR(VLOOKUP($C44,'【入力用②】案件ごと売上（D案件以上）'!$B$4:$Y$1048576,11,FALSE),"-") -> 1 | M44: =IFERROR(I44/L44,"-") -> 400 | N44: 森田 | O44: 0.104 | AA44: =IFERROR(VLOOKUP($N44,【管理用】BR_260204!$B$3:$D$20,3,FALSE)*O44,"-") -> 281.84 | AB44: =IFERROR(VLOOKUP($N44,【管理用】BR_260204!$B$3:$D$20,3,FALSE)*P44,"-") -> 0 | AC44: =IFERROR(VLOOKUP($N44,【管理用】BR_260204!$B$3:$D$20,3,FALSE)*Q44,"-") -> 0 | AD44: =IFERROR(VLOOKUP($N44,【管理用】BR_260204!$B$3:$D$20,3,FALSE)*R44,"-") -> 0 | AE44: =IFERROR(VLOOKUP($N44,【管理用】BR_260204!$B$3:$D$20,3,FALSE)*S44,"-") -> 0 | AF44: =IFERROR(VLOOKUP($N44,【管理用】BR_260204!$B$3:$D$20,3,FALSE)*T44,"-") -> 0 | AG44: =IFERROR(VLOOKUP($N44,【管理用】BR_260204!$B$3:$D$20,3,FALSE)*U44,"-") -> 0 | AH44: =IFERROR(VLOOKUP($N44,【管理用】BR_260204!$B$3:$D$20,3,FALSE)*V44,"-") -> 0 | ... AL44: =IFERROR(VLOOKUP($N44,【管理用】BR_260204!$B$3:$D$20,3,FALSE)*Z44,"-") -> 0 | AM44: =SUM(AA44:AL44) -> 281.84 | AN44: *
B45: =ROW(A45)-4 -> 41 | C45: 19 | D45: =IFERROR(VLOOKUP($C45,'【入力用②】案件ごと売上（D案件以上）'!$B$4:$Y$1048576,2,FALSE),"-") -> asics | E45: =IFERROR(VLOOKUP($C45,'【入力用②】案件ごと売上（D案件以上）'!$B$4:$Y$1048576,3,FALSE),"-") -> HRBP支援 | F45: =IFERROR(VLOOKUP($C45,'【入力用②】案件ごと売上（D案件以上）'!$B$4:$Y$1048576,4,FALSE),"-") -> 19_asics_HRBP支援 | G45: =IFERROR(VLOOKUP($C45,'【入力用②】案件ごと売上（D案件以上）'!$B$4:$Y$1048576,5,FALSE),"-") -> 組織開発 | H45: =IFERROR(VLOOKUP($C45,'【入力用②】案件ごと売上（D案件以上）'!$B$4:$Y$1048576,6,FALSE),"-") -> 成立 | I45: =IFERROR(VLOOKUP($C45,'【入力用②】案件ごと売上（D案件以上）'!$B$4:$Y$1048576,8,FALSE),"-") -> 400 | J45: =SUMIF($C$5:$C$1048576,C45,$AM$5:$AM$1048576) -> 398.88 | K45: =IFERROR(I45-J45,"-") -> 1.12 | L45: =IFERROR(VLOOKUP($C45,'【入力用②】案件ごと売上（D案件以上）'!$B$4:$Y$1048576,11,FALSE),"-") -> 1 | M45: =IFERROR(I45/L45,"-") -> 400 | N45: 小川 | O45: 0.019 | AA45: =IFERROR(VLOOKUP($N45,【管理用】BR_260204!$B$3:$D$20,3,FALSE)*O45,"-") -> 117.04 | AB45: =IFERROR(VLOOKUP($N45,【管理用】BR_260204!$B$3:$D$20,3,FALSE)*P45,"-") -> 0 | AC45: =IFERROR(VLOOKUP($N45,【管理用】BR_260204!$B$3:$D$20,3,FALSE)*Q45,"-") -> 0 | AD45: =IFERROR(VLOOKUP($N45,【管理用】BR_260204!$B$3:$D$20,3,FALSE)*R45,"-") -> 0 | AE45: =IFERROR(VLOOKUP($N45,【管理用】BR_260204!$B$3:$D$20,3,FALSE)*S45,"-") -> 0 | AF45: =IFERROR(VLOOKUP($N45,【管理用】BR_260204!$B$3:$D$20,3,FALSE)*T45,"-") -> 0 | AG45: =IFERROR(VLOOKUP($N45,【管理用】BR_260204!$B$3:$D$20,3,FALSE)*U45,"-") -> 0 | AH45: =IFERROR(VLOOKUP($N45,【管理用】BR_260204!$B$3:$D$20,3,FALSE)*V45,"-") -> 0 | ... AL45: =IFERROR(VLOOKUP($N45,【管理用】BR_260204!$B$3:$D$20,3,FALSE)*Z45,"-") -> 0 | AM45: =SUM(AA45:AL45) -> 117.04 | AN45: *
B46: =ROW(A46)-4 -> 42 | C46: 20 | D46: =IFERROR(VLOOKUP($C46,'【入力用②】案件ごと売上（D案件以上）'!$B$4:$Y$1048576,2,FALSE),"-") -> コメダ | E46: =IFERROR(VLOOKUP($C46,'【入力用②】案件ごと売上（D案件以上）'!$B$4:$Y$1048576,3,FALSE),"-") -> FC対応力向上 | F46: =IFERROR(VLOOKUP($C46,'【入力用②】案件ごと売上（D案件以上）'!$B$4:$Y$1048576,4,FALSE),"-") -> 20_コメダ_FC対応力向上 | G46: =IFERROR(VLOOKUP($C46,'【入力用②】案件ごと売上（D案件以上）'!$B$4:$Y$1048576,5,FALSE),"-") -> 人材育成 | H46: =IFERROR(VLOOKUP($C46,'【入力用②】案件ごと売上（D案件以上）'!$B$4:$Y$1048576,6,FALSE),"-") -> 成立 | I46: =IFERROR(VLOOKUP($C46,'【入力用②】案件ごと売上（D案件以上）'!$B$4:$Y$1048576,8,FALSE),"-") -> 2000 | J46: =SUMIF($C$5:$C$1048576,C46,$AM$5:$AM$1048576) -> 1999.98 | K46: =IFERROR(I46-J46,"-") -> 0.02 | L46: =IFERROR(VLOOKUP($C46,'【入力用②】案件ごと売上（D案件以上）'!$B$4:$Y$1048576,11,FALSE),"-") -> 3 | M46: =IFERROR(I46/L46,"-") -> 666.66667 | N46: 森田 | O46: 0.223 | P46: 0.223 | Q46: 0.292 | AA46: =IFERROR(VLOOKUP($N46,【管理用】BR_260204!$B$3:$D$20,3,FALSE)*O46,"-") -> 604.33 | AB46: =IFERROR(VLOOKUP($N46,【管理用】BR_260204!$B$3:$D$20,3,FALSE)*P46,"-") -> 604.33 | AC46: =IFERROR(VLOOKUP($N46,【管理用】BR_260204!$B$3:$D$20,3,FALSE)*Q46,"-") -> 791.32 | AD46: =IFERROR(VLOOKUP($N46,【管理用】BR_260204!$B$3:$D$20,3,FALSE)*R46,"-") -> 0 | AE46: =IFERROR(VLOOKUP($N46,【管理用】BR_260204!$B$3:$D$20,3,FALSE)*S46,"-") -> 0 | AF46: =IFERROR(VLOOKUP($N46,【管理用】BR_260204!$B$3:$D$20,3,FALSE)*T46,"-") -> 0 | AG46: =IFERROR(VLOOKUP($N46,【管理用】BR_260204!$B$3:$D$20,3,FALSE)*U46,"-") -> 0 | AH46: =IFERROR(VLOOKUP($N46,【管理用】BR_260204!$B$3:$D$20,3,FALSE)*V46,"-") -> 0 | ... AL46: =IFERROR(VLOOKUP($N46,【管理用】BR_260204!$B$3:$D$20,3,FALSE)*Z46,"-") -> 0 | AM46: =SUM(AA46:AL46) -> 1999.98 | AN46: *
B47: =ROW(A47)-4 -> 43 | C47: 21 | D47: =IFERROR(VLOOKUP($C47,'【入力用②】案件ごと売上（D案件以上）'!$B$4:$Y$1048576,2,FALSE),"-") -> ローソンエンタテインメント | E47: =IFERROR(VLOOKUP($C47,'【入力用②】案件ごと売上（D案件以上）'!$B$4:$Y$1048576,3,FALSE),"-") -> 人事制度・育成概要設計 | F47: =IFERROR(VLOOKUP($C47,'【入力用②】案件ごと売上（D案件以上）'!$B$4:$Y$1048576,4,FALSE),"-") -> 21_ローソンエンタテインメント_人事制度・育成概要設計 | G47: =IFERROR(VLOOKUP($C47,'【入力用②】案件ごと売上（D案件以上）'!$B$4:$Y$1048576,5,FALSE),"-") -> その他 | H47: =IFERROR(VLOOKUP($C47,'【入力用②】案件ごと売上（D案件以上）'!$B$4:$Y$1048576,6,FALSE),"-") -> 成立 | I47: =IFERROR(VLOOKUP($C47,'【入力用②】案件ごと売上（D案件以上）'!$B$4:$Y$1048576,8,FALSE),"-") -> 12300 | J47: =SUMIF($C$5:$C$1048576,C47,$AM$5:$AM$1048576) -> 12332.4 | K47: =IFERROR(I47-J47,"-") -> -32.4 | L47: =IFERROR(VLOOKUP($C47,'【入力用②】案件ごと売上（D案件以上）'!$B$4:$Y$1048576,11,FALSE),"-") -> 6 | M47: =IFERROR(I47/L47,"-") -> 2050 | N47: 小川 | O47: 0.09 | P47: 0.09 | Q47: 0.09 | R47: 0.09 | S47: 0.09 | T47: 0.09 | AA47: =IFERROR(VLOOKUP($N47,【管理用】BR_260204!$B$3:$D$20,3,FALSE)*O47,"-") -> 554.4 | AB47: =IFERROR(VLOOKUP($N47,【管理用】BR_260204!$B$3:$D$20,3,FALSE)*P47,"-") -> 554.4 | AC47: =IFERROR(VLOOKUP($N47,【管理用】BR_260204!$B$3:$D$20,3,FALSE)*Q47,"-") -> 554.4 | AD47: =IFERROR(VLOOKUP($N47,【管理用】BR_260204!$B$3:$D$20,3,FALSE)*R47,"-") -> 554.4 | AE47: =IFERROR(VLOOKUP($N47,【管理用】BR_260204!$B$3:$D$20,3,FALSE)*S47,"-") -> 554.4 | AF47: =IFERROR(VLOOKUP($N47,【管理用】BR_260204!$B$3:$D$20,3,FALSE)*T47,"-") -> 554.4 | AG47: =IFERROR(VLOOKUP($N47,【管理用】BR_260204!$B$3:$D$20,3,FALSE)*U47,"-") -> 0 | AH47: =IFERROR(VLOOKUP($N47,【管理用】BR_260204!$B$3:$D$20,3,FALSE)*V47,"-") -> 0 | ... AL47: =IFERROR(VLOOKUP($N47,【管理用】BR_260204!$B$3:$D$20,3,FALSE)*Z47,"-") -> 0 | AM47: =SUM(AA47:AL47) -> 3326.4 | AN47: *
B48: =ROW(A48)-4 -> 44 | C48: 21 | D48: =IFERROR(VLOOKUP($C48,'【入力用②】案件ごと売上（D案件以上）'!$B$4:$Y$1048576,2,FALSE),"-") -> ローソンエンタテインメント | E48: =IFERROR(VLOOKUP($C48,'【入力用②】案件ごと売上（D案件以上）'!$B$4:$Y$1048576,3,FALSE),"-") -> 人事制度・育成概要設計 | F48: =IFERROR(VLOOKUP($C48,'【入力用②】案件ごと売上（D案件以上）'!$B$4:$Y$1048576,4,FALSE),"-") -> 21_ローソンエンタテインメント_人事制度・育成概要設計 | G48: =IFERROR(VLOOKUP($C48,'【入力用②】案件ごと売上（D案件以上）'!$B$4:$Y$1048576,5,FALSE),"-") -> その他 | H48: =IFERROR(VLOOKUP($C48,'【入力用②】案件ごと売上（D案件以上）'!$B$4:$Y$1048576,6,FALSE),"-") -> 成立 | I48: =IFERROR(VLOOKUP($C48,'【入力用②】案件ごと売上（D案件以上）'!$B$4:$Y$1048576,8,FALSE),"-") -> 12300 | J48: =SUMIF($C$5:$C$1048576,C48,$AM$5:$AM$1048576) -> 12332.4 | K48: =IFERROR(I48-J48,"-") -> -32.4 | L48: =IFERROR(VLOOKUP($C48,'【入力用②】案件ごと売上（D案件以上）'!$B$4:$Y$1048576,11,FALSE),"-") -> 6 | M48: =IFERROR(I48/L48,"-") -> 2050 | N48: 芹澤 | O48: 0.4 | P48: 0.4 | Q48: 0.4 | R48: 0.4 | S48: 0.4 | T48: 0.4 | AA48: =IFERROR(VLOOKUP($N48,【管理用】BR_260204!$B$3:$D$20,3,FALSE)*O48,"-") -> 880 | AB48: =IFERROR(VLOOKUP($N48,【管理用】BR_260204!$B$3:$D$20,3,FALSE)*P48,"-") -> 880 | AC48: =IFERROR(VLOOKUP($N48,【管理用】BR_260204!$B$3:$D$20,3,FALSE)*Q48,"-") -> 880 | AD48: =IFERROR(VLOOKUP($N48,【管理用】BR_260204!$B$3:$D$20,3,FALSE)*R48,"-") -> 880 | AE48: =IFERROR(VLOOKUP($N48,【管理用】BR_260204!$B$3:$D$20,3,FALSE)*S48,"-") -> 880 | AF48: =IFERROR(VLOOKUP($N48,【管理用】BR_260204!$B$3:$D$20,3,FALSE)*T48,"-") -> 880 | AG48: =IFERROR(VLOOKUP($N48,【管理用】BR_260204!$B$3:$D$20,3,FALSE)*U48,"-") -> 0 | AH48: =IFERROR(VLOOKUP($N48,【管理用】BR_260204!$B$3:$D$20,3,FALSE)*V48,"-") -> 0 | ... AL48: =IFERROR(VLOOKUP($N48,【管理用】BR_260204!$B$3:$D$20,3,FALSE)*Z48,"-") -> 0 | AM48: =SUM(AA48:AL48) -> 5280 | AN48: *
B49: =ROW(A49)-4 -> 45 | C49: 21 | D49: =IFERROR(VLOOKUP($C49,'【入力用②】案件ごと売上（D案件以上）'!$B$4:$Y$1048576,2,FALSE),"-") -> ローソンエンタテインメント | E49: =IFERROR(VLOOKUP($C49,'【入力用②】案件ごと売上（D案件以上）'!$B$4:$Y$1048576,3,FALSE),"-") -> 人事制度・育成概要設計 | F49: =IFERROR(VLOOKUP($C49,'【入力用②】案件ごと売上（D案件以上）'!$B$4:$Y$1048576,4,FALSE),"-") -> 21_ローソンエンタテインメント_人事制度・育成概要設計 | G49: =IFERROR(VLOOKUP($C49,'【入力用②】案件ごと売上（D案件以上）'!$B$4:$Y$1048576,5,FALSE),"-") -> その他 | H49: =IFERROR(VLOOKUP($C49,'【入力用②】案件ごと売上（D案件以上）'!$B$4:$Y$1048576,6,FALSE),"-") -> 成立 | I49: =IFERROR(VLOOKUP($C49,'【入力用②】案件ごと売上（D案件以上）'!$B$4:$Y$1048576,8,FALSE),"-") -> 12300 | J49: =SUMIF($C$5:$C$1048576,C49,$AM$5:$AM$1048576) -> 12332.4 | K49: =IFERROR(I49-J49,"-") -> -32.4 | L49: =IFERROR(VLOOKUP($C49,'【入力用②】案件ごと売上（D案件以上）'!$B$4:$Y$1048576,11,FALSE),"-") -> 6 | M49: =IFERROR(I49/L49,"-") -> 2050 | N49: 弓本 | O49: 0.3 | P49: 0.3 | Q49: 0.3 | R49: 0.3 | S49: 0.3 | T49: 0.3 | AA49: =IFERROR(VLOOKUP($N49,【管理用】BR_260204!$B$3:$D$20,3,FALSE)*O49,"-") -> 621 | AB49: =IFERROR(VLOOKUP($N49,【管理用】BR_260204!$B$3:$D$20,3,FALSE)*P49,"-") -> 621 | AC49: =IFERROR(VLOOKUP($N49,【管理用】BR_260204!$B$3:$D$20,3,FALSE)*Q49,"-") -> 621 | AD49: =IFERROR(VLOOKUP($N49,【管理用】BR_260204!$B$3:$D$20,3,FALSE)*R49,"-") -> 621 | AE49: =IFERROR(VLOOKUP($N49,【管理用】BR_260204!$B$3:$D$20,3,FALSE)*S49,"-") -> 621 | AF49: =IFERROR(VLOOKUP($N49,【管理用】BR_260204!$B$3:$D$20,3,FALSE)*T49,"-") -> 621 | AG49: =IFERROR(VLOOKUP($N49,【管理用】BR_260204!$B$3:$D$20,3,FALSE)*U49,"-") -> 0 | AH49: =IFERROR(VLOOKUP($N49,【管理用】BR_260204!$B$3:$D$20,3,FALSE)*V49,"-") -> 0 | ... AL49: =IFERROR(VLOOKUP($N49,【管理用】BR_260204!$B$3:$D$20,3,FALSE)*Z49,"-") -> 0 | AM49: =SUM(AA49:AL49) -> 3726 | AN49: *
B50: =ROW(A50)-4 -> 46 | C50: 22 | D50: =IFERROR(VLOOKUP($C50,'【入力用②】案件ごと売上（D案件以上）'!$B$4:$Y$1048576,2,FALSE),"-") -> オーネスト | E50: =IFERROR(VLOOKUP($C50,'【入力用②】案件ごと売上（D案件以上）'!$B$4:$Y$1048576,3,FALSE),"-") -> MVV浸透支援Phase3 | F50: =IFERROR(VLOOKUP($C50,'【入力用②】案件ごと売上（D案件以上）'!$B$4:$Y$1048576,4,FALSE),"-") -> 22_オーネスト_MVV浸透支援Phase3 | G50: =IFERROR(VLOOKUP($C50,'【入力用②】案件ごと売上（D案件以上）'!$B$4:$Y$1048576,5,FALSE),"-") -> 組織開発 | H50: =IFERROR(VLOOKUP($C50,'【入力用②】案件ごと売上（D案件以上）'!$B$4:$Y$1048576,6,FALSE),"-") -> 成立 | I50: =IFERROR(VLOOKUP($C50,'【入力用②】案件ごと売上（D案件以上）'!$B$4:$Y$1048576,8,FALSE),"-") -> 1300 | J50: =SUMIF($C$5:$C$1048576,C50,$AM$5:$AM$1048576) -> 1330.4 | K50: =IFERROR(I50-J50,"-") -> -30.4 | L50: =IFERROR(VLOOKUP($C50,'【入力用②】案件ごと売上（D案件以上）'!$B$4:$Y$1048576,11,FALSE),"-") -> 1 | M50: =IFERROR(I50/L50,"-") -> 1300 | N50: 森田 | O50: 0.4 | AA50: =IFERROR(VLOOKUP($N50,【管理用】BR_260204!$B$3:$D$20,3,FALSE)*O50,"-") -> 1084 | AB50: =IFERROR(VLOOKUP($N50,【管理用】BR_260204!$B$3:$D$20,3,FALSE)*P50,"-") -> 0 | AC50: =IFERROR(VLOOKUP($N50,【管理用】BR_260204!$B$3:$D$20,3,FALSE)*Q50,"-") -> 0 | AD50: =IFERROR(VLOOKUP($N50,【管理用】BR_260204!$B$3:$D$20,3,FALSE)*R50,"-") -> 0 | AE50: =IFERROR(VLOOKUP($N50,【管理用】BR_260204!$B$3:$D$20,3,FALSE)*S50,"-") -> 0 | AF50: =IFERROR(VLOOKUP($N50,【管理用】BR_260204!$B$3:$D$20,3,FALSE)*T50,"-") -> 0 | AG50: =IFERROR(VLOOKUP($N50,【管理用】BR_260204!$B$3:$D$20,3,FALSE)*U50,"-") -> 0 | AH50: =IFERROR(VLOOKUP($N50,【管理用】BR_260204!$B$3:$D$20,3,FALSE)*V50,"-") -> 0 | ... AL50: =IFERROR(VLOOKUP($N50,【管理用】BR_260204!$B$3:$D$20,3,FALSE)*Z50,"-") -> 0 | AM50: =SUM(AA50:AL50) -> 1084 | AN50: *
B51: =ROW(A51)-4 -> 47 | C51: 22 | D51: =IFERROR(VLOOKUP($C51,'【入力用②】案件ごと売上（D案件以上）'!$B$4:$Y$1048576,2,FALSE),"-") -> オーネスト | E51: =IFERROR(VLOOKUP($C51,'【入力用②】案件ごと売上（D案件以上）'!$B$4:$Y$1048576,3,FALSE),"-") -> MVV浸透支援Phase3 | F51: =IFERROR(VLOOKUP($C51,'【入力用②】案件ごと売上（D案件以上）'!$B$4:$Y$1048576,4,FALSE),"-") -> 22_オーネスト_MVV浸透支援Phase3 | G51: =IFERROR(VLOOKUP($C51,'【入力用②】案件ごと売上（D案件以上）'!$B$4:$Y$1048576,5,FALSE),"-") -> 組織開発 | H51: =IFERROR(VLOOKUP($C51,'【入力用②】案件ごと売上（D案件以上）'!$B$4:$Y$1048576,6,FALSE),"-") -> 成立 | I51: =IFERROR(VLOOKUP($C51,'【入力用②】案件ごと売上（D案件以上）'!$B$4:$Y$1048576,8,FALSE),"-") -> 1300 | J51: =SUMIF($C$5:$C$1048576,C51,$AM$5:$AM$1048576) -> 1330.4 | K51: =IFERROR(I51-J51,"-") -> -30.4 | L51: =IFERROR(VLOOKUP($C51,'【入力用②】案件ごと売上（D案件以上）'!$B$4:$Y$1048576,11,FALSE),"-") -> 1 | M51: =IFERROR(I51/L51,"-") -> 1300 | N51: 小川 | O51: 0.04 | AA51: =IFERROR(VLOOKUP($N51,【管理用】BR_260204!$B$3:$D$20,3,FALSE)*O51,"-") -> 246.4 | AB51: =IFERROR(VLOOKUP($N51,【管理用】BR_260204!$B$3:$D$20,3,FALSE)*P51,"-") -> 0 | AC51: =IFERROR(VLOOKUP($N51,【管理用】BR_260204!$B$3:$D$20,3,FALSE)*Q51,"-") -> 0 | AD51: =IFERROR(VLOOKUP($N51,【管理用】BR_260204!$B$3:$D$20,3,FALSE)*R51,"-") -> 0 | AE51: =IFERROR(VLOOKUP($N51,【管理用】BR_260204!$B$3:$D$20,3,FALSE)*S51,"-") -> 0 | AF51: =IFERROR(VLOOKUP($N51,【管理用】BR_260204!$B$3:$D$20,3,FALSE)*T51,"-") -> 0 | AG51: =IFERROR(VLOOKUP($N51,【管理用】BR_260204!$B$3:$D$20,3,FALSE)*U51,"-") -> 0 | AH51: =IFERROR(VLOOKUP($N51,【管理用】BR_260204!$B$3:$D$20,3,FALSE)*V51,"-") -> 0 | ... AL51: =IFERROR(VLOOKUP($N51,【管理用】BR_260204!$B$3:$D$20,3,FALSE)*Z51,"-") -> 0 | AM51: =SUM(AA51:AL51) -> 246.4 | AN51: *
B52: =ROW(A52)-4 -> 48 | C52: 23 | D52: =IFERROR(VLOOKUP($C52,'【入力用②】案件ごと売上（D案件以上）'!$B$4:$Y$1048576,2,FALSE),"-") -> BeeX | E52: =IFERROR(VLOOKUP($C52,'【入力用②】案件ごと売上（D案件以上）'!$B$4:$Y$1048576,3,FALSE),"-") -> Aプロジェクト | F52: =IFERROR(VLOOKUP($C52,'【入力用②】案件ごと売上（D案件以上）'!$B$4:$Y$1048576,4,FALSE),"-") -> 23_BeeX_Aプロジェクト | G52: =IFERROR(VLOOKUP($C52,'【入力用②】案件ごと売上（D案件以上）'!$B$4:$Y$1048576,5,FALSE),"-") -> 人材育成 | H52: =IFERROR(VLOOKUP($C52,'【入力用②】案件ごと売上（D案件以上）'!$B$4:$Y$1048576,6,FALSE),"-") -> 失注 | I52: =IFERROR(VLOOKUP($C52,'【入力用②】案件ごと売上（D案件以上）'!$B$4:$Y$1048576,8,FALSE),"-") -> 4500 | J52: =SUMIF($C$5:$C$1048576,C52,$AM$5:$AM$1048576) -> 12240 | K52: =IFERROR(I52-J52,"-") -> -7740 | L52: =IFERROR(VLOOKUP($C52,'【入力用②】案件ごと売上（D案件以上）'!$B$4:$Y$1048576,11,FALSE),"-") -> 3 | M52: =IFERROR(I52/L52,"-") -> 1500 | N52: 啓亮 | O52: 0.8 | P52: 0.8 | Q52: 0.8 | R52: 0.8 | S52: 0.8 | T52: 0.8 | AA52: =IFERROR(VLOOKUP($N52,【管理用】BR_260204!$B$3:$D$20,3,FALSE)*O52,"-") -> 2040 | AB52: =IFERROR(VLOOKUP($N52,【管理用】BR_260204!$B$3:$D$20,3,FALSE)*P52,"-") -> 2040 | AC52: =IFERROR(VLOOKUP($N52,【管理用】BR_260204!$B$3:$D$20,3,FALSE)*Q52,"-") -> 2040 | AD52: =IFERROR(VLOOKUP($N52,【管理用】BR_260204!$B$3:$D$20,3,FALSE)*R52,"-") -> 2040 | AE52: =IFERROR(VLOOKUP($N52,【管理用】BR_260204!$B$3:$D$20,3,FALSE)*S52,"-") -> 2040 | AF52: =IFERROR(VLOOKUP($N52,【管理用】BR_260204!$B$3:$D$20,3,FALSE)*T52,"-") -> 2040 | AG52: =IFERROR(VLOOKUP($N52,【管理用】BR_260204!$B$3:$D$20,3,FALSE)*U52,"-") -> 0 | AH52: =IFERROR(VLOOKUP($N52,【管理用】BR_260204!$B$3:$D$20,3,FALSE)*V52,"-") -> 0 | ... AL52: =IFERROR(VLOOKUP($N52,【管理用】BR_260204!$B$3:$D$20,3,FALSE)*Z52,"-") -> 0 | AM52: =SUM(AA52:AL52) -> 12240 | AN52: *
B53: =ROW(A53)-4 -> 49 | C53: 24 | D53: =IFERROR(VLOOKUP($C53,'【入力用②】案件ごと売上（D案件以上）'!$B$4:$Y$1048576,2,FALSE),"-") -> ひらまつ | E53: =IFERROR(VLOOKUP($C53,'【入力用②】案件ごと売上（D案件以上）'!$B$4:$Y$1048576,3,FALSE),"-") -> 育成体系設計 | F53: =IFERROR(VLOOKUP($C53,'【入力用②】案件ごと売上（D案件以上）'!$B$4:$Y$1048576,4,FALSE),"-") -> 24_ひらまつ_育成体系設計 | G53: =IFERROR(VLOOKUP($C53,'【入力用②】案件ごと売上（D案件以上）'!$B$4:$Y$1048576,5,FALSE),"-") -> 人材育成 | H53: =IFERROR(VLOOKUP($C53,'【入力用②】案件ごと売上（D案件以上）'!$B$4:$Y$1048576,6,FALSE),"-") -> A | I53: =IFERROR(VLOOKUP($C53,'【入力用②】案件ごと売上（D案件以上）'!$B$4:$Y$1048576,8,FALSE),"-") -> 3600 | J53: =SUMIF($C$5:$C$1048576,C53,$AM$5:$AM$1048576) -> 3552.8 | K53: =IFERROR(I53-J53,"-") -> 47.2 | L53: =IFERROR(VLOOKUP($C53,'【入力用②】案件ごと売上（D案件以上）'!$B$4:$Y$1048576,11,FALSE),"-") -> 3 | M53: =IFERROR(I53/L53,"-") -> 1200 | N53: 啓亮 | S53: 0.4 | T53: 0.4 | U53: 0.4 | AA53: =IFERROR(VLOOKUP($N53,【管理用】BR_260204!$B$3:$D$20,3,FALSE)*O53,"-") -> 0 | AB53: =IFERROR(VLOOKUP($N53,【管理用】BR_260204!$B$3:$D$20,3,FALSE)*P53,"-") -> 0 | AC53: =IFERROR(VLOOKUP($N53,【管理用】BR_260204!$B$3:$D$20,3,FALSE)*Q53,"-") -> 0 | AD53: =IFERROR(VLOOKUP($N53,【管理用】BR_260204!$B$3:$D$20,3,FALSE)*R53,"-") -> 0 | AE53: =IFERROR(VLOOKUP($N53,【管理用】BR_260204!$B$3:$D$20,3,FALSE)*S53,"-") -> 1020 | AF53: =IFERROR(VLOOKUP($N53,【管理用】BR_260204!$B$3:$D$20,3,FALSE)*T53,"-") -> 1020 | AG53: =IFERROR(VLOOKUP($N53,【管理用】BR_260204!$B$3:$D$20,3,FALSE)*U53,"-") -> 1020 | AH53: =IFERROR(VLOOKUP($N53,【管理用】BR_260204!$B$3:$D$20,3,FALSE)*V53,"-") -> 0 | ... AL53: =IFERROR(VLOOKUP($N53,【管理用】BR_260204!$B$3:$D$20,3,FALSE)*Z53,"-") -> 0 | AM53: =SUM(AA53:AL53) -> 3060 | AN53: *
B54: =ROW(A54)-4 -> 50 | C54: 24 | D54: =IFERROR(VLOOKUP($C54,'【入力用②】案件ごと売上（D案件以上）'!$B$4:$Y$1048576,2,FALSE),"-") -> ひらまつ | E54: =IFERROR(VLOOKUP($C54,'【入力用②】案件ごと売上（D案件以上）'!$B$4:$Y$1048576,3,FALSE),"-") -> 育成体系設計 | F54: =IFERROR(VLOOKUP($C54,'【入力用②】案件ごと売上（D案件以上）'!$B$4:$Y$1048576,4,FALSE),"-") -> 24_ひらまつ_育成体系設計 | G54: =IFERROR(VLOOKUP($C54,'【入力用②】案件ごと売上（D案件以上）'!$B$4:$Y$1048576,5,FALSE),"-") -> 人材育成 | H54: =IFERROR(VLOOKUP($C54,'【入力用②】案件ごと売上（D案件以上）'!$B$4:$Y$1048576,6,FALSE),"-") -> A | I54: =IFERROR(VLOOKUP($C54,'【入力用②】案件ごと売上（D案件以上）'!$B$4:$Y$1048576,8,FALSE),"-") -> 3600 | J54: =SUMIF($C$5:$C$1048576,C54,$AM$5:$AM$1048576) -> 3552.8 | K54: =IFERROR(I54-J54,"-") -> 47.2 | L54: =IFERROR(VLOOKUP($C54,'【入力用②】案件ごと売上（D案件以上）'!$B$4:$Y$1048576,11,FALSE),"-") -> 3 | M54: =IFERROR(I54/L54,"-") -> 1200 | N54: 小川 | S54: 0.04 | T54: 0.04 | AA54: =IFERROR(VLOOKUP($N54,【管理用】BR_260204!$B$3:$D$20,3,FALSE)*O54,"-") -> 0 | AB54: =IFERROR(VLOOKUP($N54,【管理用】BR_260204!$B$3:$D$20,3,FALSE)*P54,"-") -> 0 | AC54: =IFERROR(VLOOKUP($N54,【管理用】BR_260204!$B$3:$D$20,3,FALSE)*Q54,"-") -> 0 | AD54: =IFERROR(VLOOKUP($N54,【管理用】BR_260204!$B$3:$D$20,3,FALSE)*R54,"-") -> 0 | AE54: =IFERROR(VLOOKUP($N54,【管理用】BR_260204!$B$3:$D$20,3,FALSE)*S54,"-") -> 246.4 | AF54: =IFERROR(VLOOKUP($N54,【管理用】BR_260204!$B$3:$D$20,3,FALSE)*T54,"-") -> 246.4 | AG54: =IFERROR(VLOOKUP($N54,【管理用】BR_260204!$B$3:$D$20,3,FALSE)*U54,"-") -> 0 | AH54: =IFERROR(VLOOKUP($N54,【管理用】BR_260204!$B$3:$D$20,3,FALSE)*V54,"-") -> 0 | ... AL54: =IFERROR(VLOOKUP($N54,【管理用】BR_260204!$B$3:$D$20,3,FALSE)*Z54,"-") -> 0 | AM54: =SUM(AA54:AL54) -> 492.8 | AN54: *
B55: =ROW(A55)-4 -> 51 | C55: 25 | D55: =IFERROR(VLOOKUP($C55,'【入力用②】案件ごと売上（D案件以上）'!$B$4:$Y$1048576,2,FALSE),"-") -> パラマウントベッド | E55: =IFERROR(VLOOKUP($C55,'【入力用②】案件ごと売上（D案件以上）'!$B$4:$Y$1048576,3,FALSE),"-") -> 女性社員交流会 企画支援 | F55: =IFERROR(VLOOKUP($C55,'【入力用②】案件ごと売上（D案件以上）'!$B$4:$Y$1048576,4,FALSE),"-") -> 25_パラマウントベッド_女性社員交流会 企画支援 | G55: =IFERROR(VLOOKUP($C55,'【入力用②】案件ごと売上（D案件以上）'!$B$4:$Y$1048576,5,FALSE),"-") -> その他 | H55: =IFERROR(VLOOKUP($C55,'【入力用②】案件ごと売上（D案件以上）'!$B$4:$Y$1048576,6,FALSE),"-") -> 成立 | I55: =IFERROR(VLOOKUP($C55,'【入力用②】案件ごと売上（D案件以上）'!$B$4:$Y$1048576,8,FALSE),"-") -> 500 | J55: =SUMIF($C$5:$C$1048576,C55,$AM$5:$AM$1048576) -> 499.892 | K55: =IFERROR(I55-J55,"-") -> 0.108 | L55: =IFERROR(VLOOKUP($C55,'【入力用②】案件ごと売上（D案件以上）'!$B$4:$Y$1048576,11,FALSE),"-") -> 1 | M55: =IFERROR(I55/L55,"-") -> 500 | N55: 丸田 | O55: 0.2659 | AA55: =IFERROR(VLOOKUP($N55,【管理用】BR_260204!$B$3:$D$20,3,FALSE)*O55,"-") -> 499.892 | AB55: =IFERROR(VLOOKUP($N55,【管理用】BR_260204!$B$3:$D$20,3,FALSE)*P55,"-") -> 0 | AC55: =IFERROR(VLOOKUP($N55,【管理用】BR_260204!$B$3:$D$20,3,FALSE)*Q55,"-") -> 0 | AD55: =IFERROR(VLOOKUP($N55,【管理用】BR_260204!$B$3:$D$20,3,FALSE)*R55,"-") -> 0 | AE55: =IFERROR(VLOOKUP($N55,【管理用】BR_260204!$B$3:$D$20,3,FALSE)*S55,"-") -> 0 | AF55: =IFERROR(VLOOKUP($N55,【管理用】BR_260204!$B$3:$D$20,3,FALSE)*T55,"-") -> 0 | AG55: =IFERROR(VLOOKUP($N55,【管理用】BR_260204!$B$3:$D$20,3,FALSE)*U55,"-") -> 0 | AH55: =IFERROR(VLOOKUP($N55,【管理用】BR_260204!$B$3:$D$20,3,FALSE)*V55,"-") -> 0 | ... AL55: =IFERROR(VLOOKUP($N55,【管理用】BR_260204!$B$3:$D$20,3,FALSE)*Z55,"-") -> 0 | AM55: =SUM(AA55:AL55) -> 499.892 | AN55: *
B56: =ROW(A56)-4 -> 52 | C56: 26 | D56: =IFERROR(VLOOKUP($C56,'【入力用②】案件ごと売上（D案件以上）'!$B$4:$Y$1048576,2,FALSE),"-") -> 西武HD | E56: =IFERROR(VLOOKUP($C56,'【入力用②】案件ごと売上（D案件以上）'!$B$4:$Y$1048576,3,FALSE),"-") -> オンボーディング・OJT企画 | F56: =IFERROR(VLOOKUP($C56,'【入力用②】案件ごと売上（D案件以上）'!$B$4:$Y$1048576,4,FALSE),"-") -> 26_西武HD_オンボーディング・OJT企画 | G56: =IFERROR(VLOOKUP($C56,'【入力用②】案件ごと売上（D案件以上）'!$B$4:$Y$1048576,5,FALSE),"-") -> その他 | H56: =IFERROR(VLOOKUP($C56,'【入力用②】案件ごと売上（D案件以上）'!$B$4:$Y$1048576,6,FALSE),"-") -> 失注 | I56: =IFERROR(VLOOKUP($C56,'【入力用②】案件ごと売上（D案件以上）'!$B$4:$Y$1048576,8,FALSE),"-") -> 2000 | J56: =SUMIF($C$5:$C$1048576,C56,$AM$5:$AM$1048576) -> 1987.2 | K56: =IFERROR(I56-J56,"-") -> 12.8 | L56: =IFERROR(VLOOKUP($C56,'【入力用②】案件ごと売上（D案件以上）'!$B$4:$Y$1048576,11,FALSE),"-") -> 3 | M56: =IFERROR(I56/L56,"-") -> 666.66667 | N56: 弓本 | P56: 0.32 | Q56: 0.32 | R56: 0.32 | AA56: =IFERROR(VLOOKUP($N56,【管理用】BR_260204!$B$3:$D$20,3,FALSE)*O56,"-") -> 0 | AB56: =IFERROR(VLOOKUP($N56,【管理用】BR_260204!$B$3:$D$20,3,FALSE)*P56,"-") -> 662.4 | AC56: =IFERROR(VLOOKUP($N56,【管理用】BR_260204!$B$3:$D$20,3,FALSE)*Q56,"-") -> 662.4 | AD56: =IFERROR(VLOOKUP($N56,【管理用】BR_260204!$B$3:$D$20,3,FALSE)*R56,"-") -> 662.4 | AE56: =IFERROR(VLOOKUP($N56,【管理用】BR_260204!$B$3:$D$20,3,FALSE)*S56,"-") -> 0 | AF56: =IFERROR(VLOOKUP($N56,【管理用】BR_260204!$B$3:$D$20,3,FALSE)*T56,"-") -> 0 | AG56: =IFERROR(VLOOKUP($N56,【管理用】BR_260204!$B$3:$D$20,3,FALSE)*U56,"-") -> 0 | AH56: =IFERROR(VLOOKUP($N56,【管理用】BR_260204!$B$3:$D$20,3,FALSE)*V56,"-") -> 0 | ... AL56: =IFERROR(VLOOKUP($N56,【管理用】BR_260204!$B$3:$D$20,3,FALSE)*Z56,"-") -> 0 | AM56: =SUM(AA56:AL56) -> 1987.2 | AN56: *
B57: =ROW(A57)-4 -> 53 | C57: 27 | D57: =IFERROR(VLOOKUP($C57,'【入力用②】案件ごと売上（D案件以上）'!$B$4:$Y$1048576,2,FALSE),"-") -> PHCホールディングス | E57: =IFERROR(VLOOKUP($C57,'【入力用②】案件ごと売上（D案件以上）'!$B$4:$Y$1048576,3,FALSE),"-") -> オンボ・採用支援（中長期含） | F57: =IFERROR(VLOOKUP($C57,'【入力用②】案件ごと売上（D案件以上）'!$B$4:$Y$1048576,4,FALSE),"-") -> 27_PHCホールディングス_オンボ・採用支援（中長期含） | G57: =IFERROR(VLOOKUP($C57,'【入力用②】案件ごと売上（D案件以上）'!$B$4:$Y$1048576,5,FALSE),"-") -> その他 | H57: =IFERROR(VLOOKUP($C57,'【入力用②】案件ごと売上（D案件以上）'!$B$4:$Y$1048576,6,FALSE),"-") -> C | I57: =IFERROR(VLOOKUP($C57,'【入力用②】案件ごと売上（D案件以上）'!$B$4:$Y$1048576,8,FALSE),"-") -> 6000 | J57: =SUMIF($C$5:$C$1048576,C57,$AM$5:$AM$1048576) -> 6023.7 | K57: =IFERROR(I57-J57,"-") -> -23.7 | L57: =IFERROR(VLOOKUP($C57,'【入力用②】案件ごと売上（D案件以上）'!$B$4:$Y$1048576,11,FALSE),"-") -> 3 | M57: =IFERROR(I57/L57,"-") -> 2000 | N57: 弓本 | P57: 0.97 | Q57: 0.97 | R57: 0.97 | AA57: =IFERROR(VLOOKUP($N57,【管理用】BR_260204!$B$3:$D$20,3,FALSE)*O57,"-") -> 0 | AB57: =IFERROR(VLOOKUP($N57,【管理用】BR_260204!$B$3:$D$20,3,FALSE)*P57,"-") -> 2007.9 | AC57: =IFERROR(VLOOKUP($N57,【管理用】BR_260204!$B$3:$D$20,3,FALSE)*Q57,"-") -> 2007.9 | AD57: =IFERROR(VLOOKUP($N57,【管理用】BR_260204!$B$3:$D$20,3,FALSE)*R57,"-") -> 2007.9 | AE57: =IFERROR(VLOOKUP($N57,【管理用】BR_260204!$B$3:$D$20,3,FALSE)*S57,"-") -> 0 | AF57: =IFERROR(VLOOKUP($N57,【管理用】BR_260204!$B$3:$D$20,3,FALSE)*T57,"-") -> 0 | AG57: =IFERROR(VLOOKUP($N57,【管理用】BR_260204!$B$3:$D$20,3,FALSE)*U57,"-") -> 0 | AH57: =IFERROR(VLOOKUP($N57,【管理用】BR_260204!$B$3:$D$20,3,FALSE)*V57,"-") -> 0 | ... AL57: =IFERROR(VLOOKUP($N57,【管理用】BR_260204!$B$3:$D$20,3,FALSE)*Z57,"-") -> 0 | AM57: =SUM(AA57:AL57) -> 6023.7 | AN57: *
B58: =ROW(A58)-4 -> 54 | C58: 28 | D58: =IFERROR(VLOOKUP($C58,'【入力用②】案件ごと売上（D案件以上）'!$B$4:$Y$1048576,2,FALSE),"-") -> 安田工業 | E58: =IFERROR(VLOOKUP($C58,'【入力用②】案件ごと売上（D案件以上）'!$B$4:$Y$1048576,3,FALSE),"-") -> 人事戦略検討 | F58: =IFERROR(VLOOKUP($C58,'【入力用②】案件ごと売上（D案件以上）'!$B$4:$Y$1048576,4,FALSE),"-") -> 28_安田工業_人事戦略検討 | G58: =IFERROR(VLOOKUP($C58,'【入力用②】案件ごと売上（D案件以上）'!$B$4:$Y$1048576,5,FALSE),"-") -> その他 | H58: =IFERROR(VLOOKUP($C58,'【入力用②】案件ごと売上（D案件以上）'!$B$4:$Y$1048576,6,FALSE),"-") -> D | I58: =IFERROR(VLOOKUP($C58,'【入力用②】案件ごと売上（D案件以上）'!$B$4:$Y$1048576,8,FALSE),"-") -> 12000 | J58: =SUMIF($C$5:$C$1048576,C58,$AM$5:$AM$1048576) -> 3696 | K58: =IFERROR(I58-J58,"-") -> 8304 | L58: =IFERROR(VLOOKUP($C58,'【入力用②】案件ごと売上（D案件以上）'!$B$4:$Y$1048576,11,FALSE),"-") -> 6 | M58: =IFERROR(I58/L58,"-") -> 2000 | N58: 小川 | P58: 0.1 | Q58: 0.1 | R58: 0.1 | S58: 0.1 | T58: 0.1 | U58: 0.1 | AA58: =IFERROR(VLOOKUP($N58,【管理用】BR_260204!$B$3:$D$20,3,FALSE)*O58,"-") -> 0 | AB58: =IFERROR(VLOOKUP($N58,【管理用】BR_260204!$B$3:$D$20,3,FALSE)*P58,"-") -> 616 | AC58: =IFERROR(VLOOKUP($N58,【管理用】BR_260204!$B$3:$D$20,3,FALSE)*Q58,"-") -> 616 | AD58: =IFERROR(VLOOKUP($N58,【管理用】BR_260204!$B$3:$D$20,3,FALSE)*R58,"-") -> 616 | AE58: =IFERROR(VLOOKUP($N58,【管理用】BR_260204!$B$3:$D$20,3,FALSE)*S58,"-") -> 616 | AF58: =IFERROR(VLOOKUP($N58,【管理用】BR_260204!$B$3:$D$20,3,FALSE)*T58,"-") -> 616 | AG58: =IFERROR(VLOOKUP($N58,【管理用】BR_260204!$B$3:$D$20,3,FALSE)*U58,"-") -> 616 | AH58: =IFERROR(VLOOKUP($N58,【管理用】BR_260204!$B$3:$D$20,3,FALSE)*V58,"-") -> 0 | ... AL58: =IFERROR(VLOOKUP($N58,【管理用】BR_260204!$B$3:$D$20,3,FALSE)*Z58,"-") -> 0 | AM58: =SUM(AA58:AL58) -> 3696 | AN58: *
B59: =ROW(A59)-4 -> 55 | D59: =IFERROR(VLOOKUP($C59,'【入力用②】案件ごと売上（D案件以上）'!$B$4:$Y$1048576,2,FALSE),"-") -> - | E59: =IFERROR(VLOOKUP($C59,'【入力用②】案件ごと売上（D案件以上）'!$B$4:$Y$1048576,3,FALSE),"-") -> - | F59: =IFERROR(VLOOKUP($C59,'【入力用②】案件ごと売上（D案件以上）'!$B$4:$Y$1048576,4,FALSE),"-") -> - | G59: =IFERROR(VLOOKUP($C59,'【入力用②】案件ごと売上（D案件以上）'!$B$4:$Y$1048576,5,FALSE),"-") -> - | H59: =IFERROR(VLOOKUP($C59,'【入力用②】案件ごと売上（D案件以上）'!$B$4:$Y$1048576,6,FALSE),"-") -> - | I59: =IFERROR(VLOOKUP($C59,'【入力用②】案件ごと売上（D案件以上）'!$B$4:$Y$1048576,8,FALSE),"-") -> - | J59: =SUMIF($C$5:$C$1048576,C59,$AM$5:$AM$1048576) -> 0 | K59: =IFERROR(I59-J59,"-") -> - | L59: =IFERROR(VLOOKUP($C59,'【入力用②】案件ごと売上（D案件以上）'!$B$4:$Y$1048576,11,FALSE),"-") -> - | M59: =IFERROR(I59/L59,"-") -> - | AA59: =IFERROR(VLOOKUP($N59,【管理用】BR_260204!$B$3:$D$20,3,FALSE)*O59,"-") -> - | AB59: =IFERROR(VLOOKUP($N59,【管理用】BR_260204!$B$3:$D$20,3,FALSE)*P59,"-") -> - | AC59: =IFERROR(VLOOKUP($N59,【管理用】BR_260204!$B$3:$D$20,3,FALSE)*Q59,"-") -> - | AD59: =IFERROR(VLOOKUP($N59,【管理用】BR_260204!$B$3:$D$20,3,FALSE)*R59,"-") -> - | AE59: =IFERROR(VLOOKUP($N59,【管理用】BR_260204!$B$3:$D$20,3,FALSE)*S59,"-") -> - | AF59: =IFERROR(VLOOKUP($N59,【管理用】BR_260204!$B$3:$D$20,3,FALSE)*T59,"-") -> - | AG59: =IFERROR(VLOOKUP($N59,【管理用】BR_260204!$B$3:$D$20,3,FALSE)*U59,"-") -> - | AH59: =IFERROR(VLOOKUP($N59,【管理用】BR_260204!$B$3:$D$20,3,FALSE)*V59,"-") -> - | ... AL59: =IFERROR(VLOOKUP($N59,【管理用】BR_260204!$B$3:$D$20,3,FALSE)*Z59,"-") -> - | AM59: =SUM(AA59:AL59) -> 0 | AN59: *
B60: =ROW(A60)-4 -> 56 | C60: 29 | D60: =IFERROR(VLOOKUP($C60,'【入力用②】案件ごと売上（D案件以上）'!$B$4:$Y$1048576,2,FALSE),"-") -> パラマウントベッド | E60: =IFERROR(VLOOKUP($C60,'【入力用②】案件ごと売上（D案件以上）'!$B$4:$Y$1048576,3,FALSE),"-") -> 女性社員交流会 キックオフイベント支援 | F60: =IFERROR(VLOOKUP($C60,'【入力用②】案件ごと売上（D案件以上）'!$B$4:$Y$1048576,4,FALSE),"-") -> 29_パラマウントベッド_女性社員交流会 キックオフイベント支援 | G60: =IFERROR(VLOOKUP($C60,'【入力用②】案件ごと売上（D案件以上）'!$B$4:$Y$1048576,5,FALSE),"-") -> その他 | H60: =IFERROR(VLOOKUP($C60,'【入力用②】案件ごと売上（D案件以上）'!$B$4:$Y$1048576,6,FALSE),"-") -> 成立 | I60: =IFERROR(VLOOKUP($C60,'【入力用②】案件ごと売上（D案件以上）'!$B$4:$Y$1048576,8,FALSE),"-") -> 700 | J60: =SUMIF($C$5:$C$1048576,C60,$AM$5:$AM$1048576) -> 282 | K60: =IFERROR(I60-J60,"-") -> 418 | L60: =IFERROR(VLOOKUP($C60,'【入力用②】案件ごと売上（D案件以上）'!$B$4:$Y$1048576,11,FALSE),"-") -> 1 | M60: =IFERROR(I60/L60,"-") -> 700 | N60: 丸田 | Q60: 0.15 | AA60: =IFERROR(VLOOKUP($N60,【管理用】BR_260204!$B$3:$D$20,3,FALSE)*O60,"-") -> 0 | AB60: =IFERROR(VLOOKUP($N60,【管理用】BR_260204!$B$3:$D$20,3,FALSE)*P60,"-") -> 0 | AC60: =IFERROR(VLOOKUP($N60,【管理用】BR_260204!$B$3:$D$20,3,FALSE)*Q60,"-") -> 282 | AD60: =IFERROR(VLOOKUP($N60,【管理用】BR_260204!$B$3:$D$20,3,FALSE)*R60,"-") -> 0 | AE60: =IFERROR(VLOOKUP($N60,【管理用】BR_260204!$B$3:$D$20,3,FALSE)*S60,"-") -> 0 | AF60: =IFERROR(VLOOKUP($N60,【管理用】BR_260204!$B$3:$D$20,3,FALSE)*T60,"-") -> 0 | AG60: =IFERROR(VLOOKUP($N60,【管理用】BR_260204!$B$3:$D$20,3,FALSE)*U60,"-") -> 0 | AH60: =IFERROR(VLOOKUP($N60,【管理用】BR_260204!$B$3:$D$20,3,FALSE)*V60,"-") -> 0 | ... AL60: =IFERROR(VLOOKUP($N60,【管理用】BR_260204!$B$3:$D$20,3,FALSE)*Z60,"-") -> 0 | AM60: =SUM(AA60:AL60) -> 282 | AN60: *
B61: =ROW(A61)-4 -> 57 | C61: 30 | D61: =IFERROR(VLOOKUP($C61,'【入力用②】案件ごと売上（D案件以上）'!$B$4:$Y$1048576,2,FALSE),"-") -> パラマウントベッド | E61: =IFERROR(VLOOKUP($C61,'【入力用②】案件ごと売上（D案件以上）'!$B$4:$Y$1048576,3,FALSE),"-") -> 女性社員交流会_女性キャリア研修 | F61: =IFERROR(VLOOKUP($C61,'【入力用②】案件ごと売上（D案件以上）'!$B$4:$Y$1048576,4,FALSE),"-") -> 30_パラマウントベッド_女性社員交流会_女性キャリア研修 | G61: =IFERROR(VLOOKUP($C61,'【入力用②】案件ごと売上（D案件以上）'!$B$4:$Y$1048576,5,FALSE),"-") -> その他 | H61: =IFERROR(VLOOKUP($C61,'【入力用②】案件ごと売上（D案件以上）'!$B$4:$Y$1048576,6,FALSE),"-") -> 成立 | I61: =IFERROR(VLOOKUP($C61,'【入力用②】案件ごと売上（D案件以上）'!$B$4:$Y$1048576,8,FALSE),"-") -> 1164 | J61: =SUMIF($C$5:$C$1048576,C61,$AM$5:$AM$1048576) -> 225.6 | K61: =IFERROR(I61-J61,"-") -> 938.4 | L61: =IFERROR(VLOOKUP($C61,'【入力用②】案件ごと売上（D案件以上）'!$B$4:$Y$1048576,11,FALSE),"-") -> 2 | M61: =IFERROR(I61/L61,"-") -> 582 | N61: 丸田 | R61: 0.12 | AA61: =IFERROR(VLOOKUP($N61,【管理用】BR_260204!$B$3:$D$20,3,FALSE)*O61,"-") -> 0 | AB61: =IFERROR(VLOOKUP($N61,【管理用】BR_260204!$B$3:$D$20,3,FALSE)*P61,"-") -> 0 | AC61: =IFERROR(VLOOKUP($N61,【管理用】BR_260204!$B$3:$D$20,3,FALSE)*Q61,"-") -> 0 | AD61: =IFERROR(VLOOKUP($N61,【管理用】BR_260204!$B$3:$D$20,3,FALSE)*R61,"-") -> 225.6 | AE61: =IFERROR(VLOOKUP($N61,【管理用】BR_260204!$B$3:$D$20,3,FALSE)*S61,"-") -> 0 | AF61: =IFERROR(VLOOKUP($N61,【管理用】BR_260204!$B$3:$D$20,3,FALSE)*T61,"-") -> 0 | AG61: =IFERROR(VLOOKUP($N61,【管理用】BR_260204!$B$3:$D$20,3,FALSE)*U61,"-") -> 0 | AH61: =IFERROR(VLOOKUP($N61,【管理用】BR_260204!$B$3:$D$20,3,FALSE)*V61,"-") -> 0 | ... AL61: =IFERROR(VLOOKUP($N61,【管理用】BR_260204!$B$3:$D$20,3,FALSE)*Z61,"-") -> 0 | AM61: =SUM(AA61:AL61) -> 225.6 | AN61: *
B62: =ROW(A62)-4 -> 58 | C62: 5 | D62: =IFERROR(VLOOKUP($C62,'【入力用②】案件ごと売上（D案件以上）'!$B$4:$Y$1048576,2,FALSE),"-") -> YAMAGATA | E62: =IFERROR(VLOOKUP($C62,'【入力用②】案件ごと売上（D案件以上）'!$B$4:$Y$1048576,3,FALSE),"-") -> 新事業立ち上げ支援 | F62: =IFERROR(VLOOKUP($C62,'【入力用②】案件ごと売上（D案件以上）'!$B$4:$Y$1048576,4,FALSE),"-") -> 05_YAMAGATA_新事業立ち上げ支援 | G62: =IFERROR(VLOOKUP($C62,'【入力用②】案件ごと売上（D案件以上）'!$B$4:$Y$1048576,5,FALSE),"-") -> その他 | H62: =IFERROR(VLOOKUP($C62,'【入力用②】案件ごと売上（D案件以上）'!$B$4:$Y$1048576,6,FALSE),"-") -> 成立 | I62: =IFERROR(VLOOKUP($C62,'【入力用②】案件ごと売上（D案件以上）'!$B$4:$Y$1048576,8,FALSE),"-") -> 14500 | J62: =SUMIF($C$5:$C$1048576,C62,$AM$5:$AM$1048576) -> 13528 | K62: =IFERROR(I62-J62,"-") -> 972 | L62: =IFERROR(VLOOKUP($C62,'【入力用②】案件ごと売上（D案件以上）'!$B$4:$Y$1048576,11,FALSE),"-") -> 4 | M62: =IFERROR(I62/L62,"-") -> 3625 | N62: 外部 | O62: 0.4 | P62: 0.4 | Q62: 0.4 | R62: 0.4 | AA62: =IFERROR(VLOOKUP($N62,【管理用】BR_260204!$B$3:$D$20,3,FALSE)*O62,"-") -> 400 | AB62: =IFERROR(VLOOKUP($N62,【管理用】BR_260204!$B$3:$D$20,3,FALSE)*P62,"-") -> 400 | AC62: =IFERROR(VLOOKUP($N62,【管理用】BR_260204!$B$3:$D$20,3,FALSE)*Q62,"-") -> 400 | AD62: =IFERROR(VLOOKUP($N62,【管理用】BR_260204!$B$3:$D$20,3,FALSE)*R62,"-") -> 400 | AE62: =IFERROR(VLOOKUP($N62,【管理用】BR_260204!$B$3:$D$20,3,FALSE)*S62,"-") -> 0 | AF62: =IFERROR(VLOOKUP($N62,【管理用】BR_260204!$B$3:$D$20,3,FALSE)*T62,"-") -> 0 | AG62: =IFERROR(VLOOKUP($N62,【管理用】BR_260204!$B$3:$D$20,3,FALSE)*U62,"-") -> 0 | AH62: =IFERROR(VLOOKUP($N62,【管理用】BR_260204!$B$3:$D$20,3,FALSE)*V62,"-") -> 0 | ... AL62: =IFERROR(VLOOKUP($N62,【管理用】BR_260204!$B$3:$D$20,3,FALSE)*Z62,"-") -> 0 | AM62: =SUM(AA62:AL62) -> 1600 | AN62: *
B63: =ROW(A63)-4 -> 59 | C63: 31 | D63: =IFERROR(VLOOKUP($C63,'【入力用②】案件ごと売上（D案件以上）'!$B$4:$Y$1048576,2,FALSE),"-") -> パーソルクロステクノロジー | E63: =IFERROR(VLOOKUP($C63,'【入力用②】案件ごと売上（D案件以上）'!$B$4:$Y$1048576,3,FALSE),"-") -> 社内広報業務支援 | F63: =IFERROR(VLOOKUP($C63,'【入力用②】案件ごと売上（D案件以上）'!$B$4:$Y$1048576,4,FALSE),"-") -> 31_パーソルクロステクノロジー_社内広報業務支援 | G63: =IFERROR(VLOOKUP($C63,'【入力用②】案件ごと売上（D案件以上）'!$B$4:$Y$1048576,5,FALSE),"-") -> 組織開発 | H63: =IFERROR(VLOOKUP($C63,'【入力用②】案件ごと売上（D案件以上）'!$B$4:$Y$1048576,6,FALSE),"-") -> 成立 | I63: =IFERROR(VLOOKUP($C63,'【入力用②】案件ごと売上（D案件以上）'!$B$4:$Y$1048576,8,FALSE),"-") -> 2250 | J63: =SUMIF($C$5:$C$1048576,C63,$AM$5:$AM$1048576) -> 2256 | K63: =IFERROR(I63-J63,"-") -> -6 | L63: =IFERROR(VLOOKUP($C63,'【入力用②】案件ごと売上（D案件以上）'!$B$4:$Y$1048576,11,FALSE),"-") -> 3 | M63: =IFERROR(I63/L63,"-") -> 750 | N63: 丸田 | P63: 0.4 | Q63: 0.4 | R63: 0.4 | AA63: =IFERROR(VLOOKUP($N63,【管理用】BR_260204!$B$3:$D$20,3,FALSE)*O63,"-") -> 0 | AB63: =IFERROR(VLOOKUP($N63,【管理用】BR_260204!$B$3:$D$20,3,FALSE)*P63,"-") -> 752 | AC63: =IFERROR(VLOOKUP($N63,【管理用】BR_260204!$B$3:$D$20,3,FALSE)*Q63,"-") -> 752 | AD63: =IFERROR(VLOOKUP($N63,【管理用】BR_260204!$B$3:$D$20,3,FALSE)*R63,"-") -> 752 | AE63: =IFERROR(VLOOKUP($N63,【管理用】BR_260204!$B$3:$D$20,3,FALSE)*S63,"-") -> 0 | AF63: =IFERROR(VLOOKUP($N63,【管理用】BR_260204!$B$3:$D$20,3,FALSE)*T63,"-") -> 0 | AG63: =IFERROR(VLOOKUP($N63,【管理用】BR_260204!$B$3:$D$20,3,FALSE)*U63,"-") -> 0 | AH63: =IFERROR(VLOOKUP($N63,【管理用】BR_260204!$B$3:$D$20,3,FALSE)*V63,"-") -> 0 | ... AL63: =IFERROR(VLOOKUP($N63,【管理用】BR_260204!$B$3:$D$20,3,FALSE)*Z63,"-") -> 0 | AM63: =SUM(AA63:AL63) -> 2256 | AN63: *
B64: =ROW(A64)-4 -> 60 | C64: 34 | D64: =IFERROR(VLOOKUP($C64,'【入力用②】案件ごと売上（D案件以上）'!$B$4:$Y$1048576,2,FALSE),"-") -> インテージテクノスフィア | E64: =IFERROR(VLOOKUP($C64,'【入力用②】案件ごと売上（D案件以上）'!$B$4:$Y$1048576,3,FALSE),"-") -> 経営層向けレポート作成支援_Phase1 | F64: =IFERROR(VLOOKUP($C64,'【入力用②】案件ごと売上（D案件以上）'!$B$4:$Y$1048576,4,FALSE),"-") -> 34_インテージテクノスフィア_経営層向けレポート作成支援_Phase1 | G64: =IFERROR(VLOOKUP($C64,'【入力用②】案件ごと売上（D案件以上）'!$B$4:$Y$1048576,5,FALSE),"-") -> その他 | H64: =IFERROR(VLOOKUP($C64,'【入力用②】案件ごと売上（D案件以上）'!$B$4:$Y$1048576,6,FALSE),"-") -> 失注 | I64: =IFERROR(VLOOKUP($C64,'【入力用②】案件ごと売上（D案件以上）'!$B$4:$Y$1048576,8,FALSE),"-") -> 900 | J64: =SUMIF($C$5:$C$1048576,C64,$AM$5:$AM$1048576) -> 889.6 | K64: =IFERROR(I64-J64,"-") -> 10.4 | L64: =IFERROR(VLOOKUP($C64,'【入力用②】案件ごと売上（D案件以上）'!$B$4:$Y$1048576,11,FALSE),"-") -> 1 | M64: =IFERROR(I64/L64,"-") -> 900 | N64: 弓本 | P64: 0.4 | AA64: =IFERROR(VLOOKUP($N64,【管理用】BR_260204!$B$3:$D$20,3,FALSE)*O64,"-") -> 0 | AB64: =IFERROR(VLOOKUP($N64,【管理用】BR_260204!$B$3:$D$20,3,FALSE)*P64,"-") -> 828 | AC64: =IFERROR(VLOOKUP($N64,【管理用】BR_260204!$B$3:$D$20,3,FALSE)*Q64,"-") -> 0 | AD64: =IFERROR(VLOOKUP($N64,【管理用】BR_260204!$B$3:$D$20,3,FALSE)*R64,"-") -> 0 | AE64: =IFERROR(VLOOKUP($N64,【管理用】BR_260204!$B$3:$D$20,3,FALSE)*S64,"-") -> 0 | AF64: =IFERROR(VLOOKUP($N64,【管理用】BR_260204!$B$3:$D$20,3,FALSE)*T64,"-") -> 0 | AG64: =IFERROR(VLOOKUP($N64,【管理用】BR_260204!$B$3:$D$20,3,FALSE)*U64,"-") -> 0 | AH64: =IFERROR(VLOOKUP($N64,【管理用】BR_260204!$B$3:$D$20,3,FALSE)*V64,"-") -> 0 | ... AL64: =IFERROR(VLOOKUP($N64,【管理用】BR_260204!$B$3:$D$20,3,FALSE)*Z64,"-") -> 0 | AM64: =SUM(AA64:AL64) -> 828 | AN64: *
B65: =ROW(A65)-4 -> 61 | C65: 34 | D65: =IFERROR(VLOOKUP($C65,'【入力用②】案件ごと売上（D案件以上）'!$B$4:$Y$1048576,2,FALSE),"-") -> インテージテクノスフィア | E65: =IFERROR(VLOOKUP($C65,'【入力用②】案件ごと売上（D案件以上）'!$B$4:$Y$1048576,3,FALSE),"-") -> 経営層向けレポート作成支援_Phase1 | F65: =IFERROR(VLOOKUP($C65,'【入力用②】案件ごと売上（D案件以上）'!$B$4:$Y$1048576,4,FALSE),"-") -> 34_インテージテクノスフィア_経営層向けレポート作成支援_Phase1 | G65: =IFERROR(VLOOKUP($C65,'【入力用②】案件ごと売上（D案件以上）'!$B$4:$Y$1048576,5,FALSE),"-") -> その他 | H65: =IFERROR(VLOOKUP($C65,'【入力用②】案件ごと売上（D案件以上）'!$B$4:$Y$1048576,6,FALSE),"-") -> 失注 | I65: =IFERROR(VLOOKUP($C65,'【入力用②】案件ごと売上（D案件以上）'!$B$4:$Y$1048576,8,FALSE),"-") -> 900 | J65: =SUMIF($C$5:$C$1048576,C65,$AM$5:$AM$1048576) -> 889.6 | K65: =IFERROR(I65-J65,"-") -> 10.4 | L65: =IFERROR(VLOOKUP($C65,'【入力用②】案件ごと売上（D案件以上）'!$B$4:$Y$1048576,11,FALSE),"-") -> 1 | M65: =IFERROR(I65/L65,"-") -> 900 | N65: 小川 | P65: 0.01 | AA65: =IFERROR(VLOOKUP($N65,【管理用】BR_260204!$B$3:$D$20,3,FALSE)*O65,"-") -> 0 | AB65: =IFERROR(VLOOKUP($N65,【管理用】BR_260204!$B$3:$D$20,3,FALSE)*P65,"-") -> 61.6 | AC65: =IFERROR(VLOOKUP($N65,【管理用】BR_260204!$B$3:$D$20,3,FALSE)*Q65,"-") -> 0 | AD65: =IFERROR(VLOOKUP($N65,【管理用】BR_260204!$B$3:$D$20,3,FALSE)*R65,"-") -> 0 | AE65: =IFERROR(VLOOKUP($N65,【管理用】BR_260204!$B$3:$D$20,3,FALSE)*S65,"-") -> 0 | AF65: =IFERROR(VLOOKUP($N65,【管理用】BR_260204!$B$3:$D$20,3,FALSE)*T65,"-") -> 0 | AG65: =IFERROR(VLOOKUP($N65,【管理用】BR_260204!$B$3:$D$20,3,FALSE)*U65,"-") -> 0 | AH65: =IFERROR(VLOOKUP($N65,【管理用】BR_260204!$B$3:$D$20,3,FALSE)*V65,"-") -> 0 | ... AL65: =IFERROR(VLOOKUP($N65,【管理用】BR_260204!$B$3:$D$20,3,FALSE)*Z65,"-") -> 0 | AM65: =SUM(AA65:AL65) -> 61.6 | AN65: *
B66: =ROW(A66)-4 -> 62 | C66: 36 | D66: =IFERROR(VLOOKUP($C66,'【入力用②】案件ごと売上（D案件以上）'!$B$4:$Y$1048576,2,FALSE),"-") -> パラドックス | E66: =IFERROR(VLOOKUP($C66,'【入力用②】案件ごと売上（D案件以上）'!$B$4:$Y$1048576,3,FALSE),"-") -> 森の歩き方実装支援（10月以降） | F66: =IFERROR(VLOOKUP($C66,'【入力用②】案件ごと売上（D案件以上）'!$B$4:$Y$1048576,4,FALSE),"-") -> 36_パラドックス_森の歩き方実装支援（10月以降） | G66: =IFERROR(VLOOKUP($C66,'【入力用②】案件ごと売上（D案件以上）'!$B$4:$Y$1048576,5,FALSE),"-") -> 人材育成 | H66: =IFERROR(VLOOKUP($C66,'【入力用②】案件ごと売上（D案件以上）'!$B$4:$Y$1048576,6,FALSE),"-") -> 成立 | I66: =IFERROR(VLOOKUP($C66,'【入力用②】案件ごと売上（D案件以上）'!$B$4:$Y$1048576,8,FALSE),"-") -> 1650 | J66: =SUMIF($C$5:$C$1048576,C66,$AM$5:$AM$1048576) -> 1657.5 | K66: =IFERROR(I66-J66,"-") -> -7.5 | L66: =IFERROR(VLOOKUP($C66,'【入力用②】案件ごと売上（D案件以上）'!$B$4:$Y$1048576,11,FALSE),"-") -> 6 | M66: =IFERROR(I66/L66,"-") -> 275 | N66: 啓亮 | P66: 0.05 | Q66: 0.12 | R66: 0.12 | S66: 0.12 | T66: 0.12 | U66: 0.12 | AA66: =IFERROR(VLOOKUP($N66,【管理用】BR_260204!$B$3:$D$20,3,FALSE)*O66,"-") -> 0 | AB66: =IFERROR(VLOOKUP($N66,【管理用】BR_260204!$B$3:$D$20,3,FALSE)*P66,"-") -> 127.5 | AC66: =IFERROR(VLOOKUP($N66,【管理用】BR_260204!$B$3:$D$20,3,FALSE)*Q66,"-") -> 306 | AD66: =IFERROR(VLOOKUP($N66,【管理用】BR_260204!$B$3:$D$20,3,FALSE)*R66,"-") -> 306 | AE66: =IFERROR(VLOOKUP($N66,【管理用】BR_260204!$B$3:$D$20,3,FALSE)*S66,"-") -> 306 | AF66: =IFERROR(VLOOKUP($N66,【管理用】BR_260204!$B$3:$D$20,3,FALSE)*T66,"-") -> 306 | AG66: =IFERROR(VLOOKUP($N66,【管理用】BR_260204!$B$3:$D$20,3,FALSE)*U66,"-") -> 306 | AH66: =IFERROR(VLOOKUP($N66,【管理用】BR_260204!$B$3:$D$20,3,FALSE)*V66,"-") -> 0 | ... AL66: =IFERROR(VLOOKUP($N66,【管理用】BR_260204!$B$3:$D$20,3,FALSE)*Z66,"-") -> 0 | AM66: =SUM(AA66:AL66) -> 1657.5 | AN66: *
B67: =ROW(A67)-4 -> 63 | C67: 33 | D67: =IFERROR(VLOOKUP($C67,'【入力用②】案件ごと売上（D案件以上）'!$B$4:$Y$1048576,2,FALSE),"-") -> 田島ルーフィング | E67: =IFERROR(VLOOKUP($C67,'【入力用②】案件ごと売上（D案件以上）'!$B$4:$Y$1048576,3,FALSE),"-") -> 推せる職場診断 | F67: =IFERROR(VLOOKUP($C67,'【入力用②】案件ごと売上（D案件以上）'!$B$4:$Y$1048576,4,FALSE),"-") -> 33_田島ルーフィング_推せる職場診断 | G67: =IFERROR(VLOOKUP($C67,'【入力用②】案件ごと売上（D案件以上）'!$B$4:$Y$1048576,5,FALSE),"-") -> 組織開発 | H67: =IFERROR(VLOOKUP($C67,'【入力用②】案件ごと売上（D案件以上）'!$B$4:$Y$1048576,6,FALSE),"-") -> 成立 | I67: =IFERROR(VLOOKUP($C67,'【入力用②】案件ごと売上（D案件以上）'!$B$4:$Y$1048576,8,FALSE),"-") -> 3100 | J67: =SUMIF($C$5:$C$1048576,C67,$AM$5:$AM$1048576) -> 3118.65 | K67: =IFERROR(I67-J67,"-") -> -18.65 | L67: =IFERROR(VLOOKUP($C67,'【入力用②】案件ごと売上（D案件以上）'!$B$4:$Y$1048576,11,FALSE),"-") -> 5 | M67: =IFERROR(I67/L67,"-") -> 620 | N67: 啓亮 | P67: 0.394 | Q67: 0.394 | R67: 0.12 | S67: 0.12 | T67: 0.195 | AA67: =IFERROR(VLOOKUP($N67,【管理用】BR_260204!$B$3:$D$20,3,FALSE)*O67,"-") -> 0 | AB67: =IFERROR(VLOOKUP($N67,【管理用】BR_260204!$B$3:$D$20,3,FALSE)*P67,"-") -> 1004.7 | AC67: =IFERROR(VLOOKUP($N67,【管理用】BR_260204!$B$3:$D$20,3,FALSE)*Q67,"-") -> 1004.7 | AD67: =IFERROR(VLOOKUP($N67,【管理用】BR_260204!$B$3:$D$20,3,FALSE)*R67,"-") -> 306 | AE67: =IFERROR(VLOOKUP($N67,【管理用】BR_260204!$B$3:$D$20,3,FALSE)*S67,"-") -> 306 | AF67: =IFERROR(VLOOKUP($N67,【管理用】BR_260204!$B$3:$D$20,3,FALSE)*T67,"-") -> 497.25 | AG67: =IFERROR(VLOOKUP($N67,【管理用】BR_260204!$B$3:$D$20,3,FALSE)*U67,"-") -> 0 | AH67: =IFERROR(VLOOKUP($N67,【管理用】BR_260204!$B$3:$D$20,3,FALSE)*V67,"-") -> 0 | ... AL67: =IFERROR(VLOOKUP($N67,【管理用】BR_260204!$B$3:$D$20,3,FALSE)*Z67,"-") -> 0 | AM67: =SUM(AA67:AL67) -> 3118.65 | AN67: *
B68: =ROW(A68)-4 -> 64 | C68: 40 | D68: =IFERROR(VLOOKUP($C68,'【入力用②】案件ごと売上（D案件以上）'!$B$4:$Y$1048576,2,FALSE),"-") -> 三井情報 | E68: =IFERROR(VLOOKUP($C68,'【入力用②】案件ごと売上（D案件以上）'!$B$4:$Y$1048576,3,FALSE),"-") -> 人材マネジメントアドバイザリー | F68: =IFERROR(VLOOKUP($C68,'【入力用②】案件ごと売上（D案件以上）'!$B$4:$Y$1048576,4,FALSE),"-") -> 40_三井情報_人材マネジメントアドバイザリー | G68: =IFERROR(VLOOKUP($C68,'【入力用②】案件ごと売上（D案件以上）'!$B$4:$Y$1048576,5,FALSE),"-") -> 人材育成 | H68: =IFERROR(VLOOKUP($C68,'【入力用②】案件ごと売上（D案件以上）'!$B$4:$Y$1048576,6,FALSE),"-") -> 成立 | I68: =IFERROR(VLOOKUP($C68,'【入力用②】案件ごと売上（D案件以上）'!$B$4:$Y$1048576,8,FALSE),"-") -> 3500 | J68: =SUMIF($C$5:$C$1048576,C68,$AM$5:$AM$1048576) -> 3442.5 | K68: =IFERROR(I68-J68,"-") -> 57.5 | L68: =IFERROR(VLOOKUP($C68,'【入力用②】案件ごと売上（D案件以上）'!$B$4:$Y$1048576,11,FALSE),"-") -> 5 | M68: =IFERROR(I68/L68,"-") -> 700 | N68: 小川 | AA68: =IFERROR(VLOOKUP($N68,【管理用】BR_260204!$B$3:$D$20,3,FALSE)*O68,"-") -> 0 | AB68: =IFERROR(VLOOKUP($N68,【管理用】BR_260204!$B$3:$D$20,3,FALSE)*P68,"-") -> 0 | AC68: =IFERROR(VLOOKUP($N68,【管理用】BR_260204!$B$3:$D$20,3,FALSE)*Q68,"-") -> 0 | AD68: =IFERROR(VLOOKUP($N68,【管理用】BR_260204!$B$3:$D$20,3,FALSE)*R68,"-") -> 0 | AE68: =IFERROR(VLOOKUP($N68,【管理用】BR_260204!$B$3:$D$20,3,FALSE)*S68,"-") -> 0 | AF68: =IFERROR(VLOOKUP($N68,【管理用】BR_260204!$B$3:$D$20,3,FALSE)*T68,"-") -> 0 | AG68: =IFERROR(VLOOKUP($N68,【管理用】BR_260204!$B$3:$D$20,3,FALSE)*U68,"-") -> 0 | AH68: =IFERROR(VLOOKUP($N68,【管理用】BR_260204!$B$3:$D$20,3,FALSE)*V68,"-") -> 0 | ... AL68: =IFERROR(VLOOKUP($N68,【管理用】BR_260204!$B$3:$D$20,3,FALSE)*Z68,"-") -> 0 | AM68: =SUM(AA68:AL68) -> 0 | AN68: *
B69: =ROW(A69)-4 -> 65 | C69: 40 | D69: =IFERROR(VLOOKUP($C69,'【入力用②】案件ごと売上（D案件以上）'!$B$4:$Y$1048576,2,FALSE),"-") -> 三井情報 | E69: =IFERROR(VLOOKUP($C69,'【入力用②】案件ごと売上（D案件以上）'!$B$4:$Y$1048576,3,FALSE),"-") -> 人材マネジメントアドバイザリー | F69: =IFERROR(VLOOKUP($C69,'【入力用②】案件ごと売上（D案件以上）'!$B$4:$Y$1048576,4,FALSE),"-") -> 40_三井情報_人材マネジメントアドバイザリー | G69: =IFERROR(VLOOKUP($C69,'【入力用②】案件ごと売上（D案件以上）'!$B$4:$Y$1048576,5,FALSE),"-") -> 人材育成 | H69: =IFERROR(VLOOKUP($C69,'【入力用②】案件ごと売上（D案件以上）'!$B$4:$Y$1048576,6,FALSE),"-") -> 成立 | I69: =IFERROR(VLOOKUP($C69,'【入力用②】案件ごと売上（D案件以上）'!$B$4:$Y$1048576,8,FALSE),"-") -> 3500 | J69: =SUMIF($C$5:$C$1048576,C69,$AM$5:$AM$1048576) -> 3442.5 | K69: =IFERROR(I69-J69,"-") -> 57.5 | L69: =IFERROR(VLOOKUP($C69,'【入力用②】案件ごと売上（D案件以上）'!$B$4:$Y$1048576,11,FALSE),"-") -> 5 | M69: =IFERROR(I69/L69,"-") -> 700 | N69: 啓亮 | Q69: 0.27 | R69: 0.27 | S69: 0.27 | T69: 0.27 | U69: 0.27 | AA69: =IFERROR(VLOOKUP($N69,【管理用】BR_260204!$B$3:$D$20,3,FALSE)*O69,"-") -> 0 | AB69: =IFERROR(VLOOKUP($N69,【管理用】BR_260204!$B$3:$D$20,3,FALSE)*P69,"-") -> 0 | AC69: =IFERROR(VLOOKUP($N69,【管理用】BR_260204!$B$3:$D$20,3,FALSE)*Q69,"-") -> 688.5 | AD69: =IFERROR(VLOOKUP($N69,【管理用】BR_260204!$B$3:$D$20,3,FALSE)*R69,"-") -> 688.5 | AE69: =IFERROR(VLOOKUP($N69,【管理用】BR_260204!$B$3:$D$20,3,FALSE)*S69,"-") -> 688.5 | AF69: =IFERROR(VLOOKUP($N69,【管理用】BR_260204!$B$3:$D$20,3,FALSE)*T69,"-") -> 688.5 | AG69: =IFERROR(VLOOKUP($N69,【管理用】BR_260204!$B$3:$D$20,3,FALSE)*U69,"-") -> 688.5 | AH69: =IFERROR(VLOOKUP($N69,【管理用】BR_260204!$B$3:$D$20,3,FALSE)*V69,"-") -> 0 | ... AL69: =IFERROR(VLOOKUP($N69,【管理用】BR_260204!$B$3:$D$20,3,FALSE)*Z69,"-") -> 0 | AM69: =SUM(AA69:AL69) -> 3442.5 | AN69: *
B70: =ROW(A70)-4 -> 66 | C70: 43 | D70: =IFERROR(VLOOKUP($C70,'【入力用②】案件ごと売上（D案件以上）'!$B$4:$Y$1048576,2,FALSE),"-") -> 一条工務店 | E70: =IFERROR(VLOOKUP($C70,'【入力用②】案件ごと売上（D案件以上）'!$B$4:$Y$1048576,3,FALSE),"-") -> 育成体系 | F70: =IFERROR(VLOOKUP($C70,'【入力用②】案件ごと売上（D案件以上）'!$B$4:$Y$1048576,4,FALSE),"-") -> 43_一条工務店_育成体系 | G70: =IFERROR(VLOOKUP($C70,'【入力用②】案件ごと売上（D案件以上）'!$B$4:$Y$1048576,5,FALSE),"-") -> 人材育成 | H70: =IFERROR(VLOOKUP($C70,'【入力用②】案件ごと売上（D案件以上）'!$B$4:$Y$1048576,6,FALSE),"-") -> 失注 | I70: =IFERROR(VLOOKUP($C70,'【入力用②】案件ごと売上（D案件以上）'!$B$4:$Y$1048576,8,FALSE),"-") -> 4000 | J70: =SUMIF($C$5:$C$1048576,C70,$AM$5:$AM$1048576) -> 3825 | K70: =IFERROR(I70-J70,"-") -> 175 | L70: =IFERROR(VLOOKUP($C70,'【入力用②】案件ごと売上（D案件以上）'!$B$4:$Y$1048576,11,FALSE),"-") -> 2 | M70: =IFERROR(I70/L70,"-") -> 2000 | N70: 啓亮 | R70: 0.75 | S70: 0.75 | AA70: =IFERROR(VLOOKUP($N70,【管理用】BR_260204!$B$3:$D$20,3,FALSE)*O70,"-") -> 0 | AB70: =IFERROR(VLOOKUP($N70,【管理用】BR_260204!$B$3:$D$20,3,FALSE)*P70,"-") -> 0 | AC70: =IFERROR(VLOOKUP($N70,【管理用】BR_260204!$B$3:$D$20,3,FALSE)*Q70,"-") -> 0 | AD70: =IFERROR(VLOOKUP($N70,【管理用】BR_260204!$B$3:$D$20,3,FALSE)*R70,"-") -> 1912.5 | AE70: =IFERROR(VLOOKUP($N70,【管理用】BR_260204!$B$3:$D$20,3,FALSE)*S70,"-") -> 1912.5 | AF70: =IFERROR(VLOOKUP($N70,【管理用】BR_260204!$B$3:$D$20,3,FALSE)*T70,"-") -> 0 | AG70: =IFERROR(VLOOKUP($N70,【管理用】BR_260204!$B$3:$D$20,3,FALSE)*U70,"-") -> 0 | AH70: =IFERROR(VLOOKUP($N70,【管理用】BR_260204!$B$3:$D$20,3,FALSE)*V70,"-") -> 0 | ... AL70: =IFERROR(VLOOKUP($N70,【管理用】BR_260204!$B$3:$D$20,3,FALSE)*Z70,"-") -> 0 | AM70: =SUM(AA70:AL70) -> 3825 | AN70: *
B71: =ROW(A71)-4 -> 67 | C71: 41 | D71: =IFERROR(VLOOKUP($C71,'【入力用②】案件ごと売上（D案件以上）'!$B$4:$Y$1048576,2,FALSE),"-") -> トヨタコネクティッド | E71: =IFERROR(VLOOKUP($C71,'【入力用②】案件ごと売上（D案件以上）'!$B$4:$Y$1048576,3,FALSE),"-") -> オンボーディング施策設計 | F71: =IFERROR(VLOOKUP($C71,'【入力用②】案件ごと売上（D案件以上）'!$B$4:$Y$1048576,4,FALSE),"-") -> 41_トヨタコネクティッド_オンボーディング施策設計 | G71: =IFERROR(VLOOKUP($C71,'【入力用②】案件ごと売上（D案件以上）'!$B$4:$Y$1048576,5,FALSE),"-") -> 組織開発 | H71: =IFERROR(VLOOKUP($C71,'【入力用②】案件ごと売上（D案件以上）'!$B$4:$Y$1048576,6,FALSE),"-") -> A | I71: =IFERROR(VLOOKUP($C71,'【入力用②】案件ごと売上（D案件以上）'!$B$4:$Y$1048576,8,FALSE),"-") -> 6000 | J71: =SUMIF($C$5:$C$1048576,C71,$AM$5:$AM$1048576) -> 5716 | K71: =IFERROR(I71-J71,"-") -> 284 | L71: =IFERROR(VLOOKUP($C71,'【入力用②】案件ごと売上（D案件以上）'!$B$4:$Y$1048576,11,FALSE),"-") -> 3 | M71: =IFERROR(I71/L71,"-") -> 2000 | N71: 小川 | T71: 0.05 | U71: 0.05 | AA71: =IFERROR(VLOOKUP($N71,【管理用】BR_260204!$B$3:$D$20,3,FALSE)*O71,"-") -> 0 | AB71: =IFERROR(VLOOKUP($N71,【管理用】BR_260204!$B$3:$D$20,3,FALSE)*P71,"-") -> 0 | AC71: =IFERROR(VLOOKUP($N71,【管理用】BR_260204!$B$3:$D$20,3,FALSE)*Q71,"-") -> 0 | AD71: =IFERROR(VLOOKUP($N71,【管理用】BR_260204!$B$3:$D$20,3,FALSE)*R71,"-") -> 0 | AE71: =IFERROR(VLOOKUP($N71,【管理用】BR_260204!$B$3:$D$20,3,FALSE)*S71,"-") -> 0 | AF71: =IFERROR(VLOOKUP($N71,【管理用】BR_260204!$B$3:$D$20,3,FALSE)*T71,"-") -> 308 | AG71: =IFERROR(VLOOKUP($N71,【管理用】BR_260204!$B$3:$D$20,3,FALSE)*U71,"-") -> 308 | AH71: =IFERROR(VLOOKUP($N71,【管理用】BR_260204!$B$3:$D$20,3,FALSE)*V71,"-") -> 0 | ... AL71: =IFERROR(VLOOKUP($N71,【管理用】BR_260204!$B$3:$D$20,3,FALSE)*Z71,"-") -> 0 | AM71: =SUM(AA71:AL71) -> 616 | AN71: *
B72: =ROW(A72)-4 -> 68 | C72: 41 | D72: =IFERROR(VLOOKUP($C72,'【入力用②】案件ごと売上（D案件以上）'!$B$4:$Y$1048576,2,FALSE),"-") -> トヨタコネクティッド | E72: =IFERROR(VLOOKUP($C72,'【入力用②】案件ごと売上（D案件以上）'!$B$4:$Y$1048576,3,FALSE),"-") -> オンボーディング施策設計 | F72: =IFERROR(VLOOKUP($C72,'【入力用②】案件ごと売上（D案件以上）'!$B$4:$Y$1048576,4,FALSE),"-") -> 41_トヨタコネクティッド_オンボーディング施策設計 | G72: =IFERROR(VLOOKUP($C72,'【入力用②】案件ごと売上（D案件以上）'!$B$4:$Y$1048576,5,FALSE),"-") -> 組織開発 | H72: =IFERROR(VLOOKUP($C72,'【入力用②】案件ごと売上（D案件以上）'!$B$4:$Y$1048576,6,FALSE),"-") -> A | I72: =IFERROR(VLOOKUP($C72,'【入力用②】案件ごと売上（D案件以上）'!$B$4:$Y$1048576,8,FALSE),"-") -> 6000 | J72: =SUMIF($C$5:$C$1048576,C72,$AM$5:$AM$1048576) -> 5716 | K72: =IFERROR(I72-J72,"-") -> 284 | L72: =IFERROR(VLOOKUP($C72,'【入力用②】案件ごと売上（D案件以上）'!$B$4:$Y$1048576,11,FALSE),"-") -> 3 | M72: =IFERROR(I72/L72,"-") -> 2000 | N72: 啓亮 | S72: 0.7 | T72: 0.65 | U72: 0.65 | AA72: =IFERROR(VLOOKUP($N72,【管理用】BR_260204!$B$3:$D$20,3,FALSE)*O72,"-") -> 0 | AB72: =IFERROR(VLOOKUP($N72,【管理用】BR_260204!$B$3:$D$20,3,FALSE)*P72,"-") -> 0 | AC72: =IFERROR(VLOOKUP($N72,【管理用】BR_260204!$B$3:$D$20,3,FALSE)*Q72,"-") -> 0 | AD72: =IFERROR(VLOOKUP($N72,【管理用】BR_260204!$B$3:$D$20,3,FALSE)*R72,"-") -> 0 | AE72: =IFERROR(VLOOKUP($N72,【管理用】BR_260204!$B$3:$D$20,3,FALSE)*S72,"-") -> 1785 | AF72: =IFERROR(VLOOKUP($N72,【管理用】BR_260204!$B$3:$D$20,3,FALSE)*T72,"-") -> 1657.5 | AG72: =IFERROR(VLOOKUP($N72,【管理用】BR_260204!$B$3:$D$20,3,FALSE)*U72,"-") -> 1657.5 | AH72: =IFERROR(VLOOKUP($N72,【管理用】BR_260204!$B$3:$D$20,3,FALSE)*V72,"-") -> 0 | ... AL72: =IFERROR(VLOOKUP($N72,【管理用】BR_260204!$B$3:$D$20,3,FALSE)*Z72,"-") -> 0 | AM72: =SUM(AA72:AL72) -> 5100 | AN72: *
B73: =ROW(A73)-4 -> 69 | C73: 48 | D73: =IFERROR(VLOOKUP($C73,'【入力用②】案件ごと売上（D案件以上）'!$B$4:$Y$1048576,2,FALSE),"-") -> アートプレスト | E73: =IFERROR(VLOOKUP($C73,'【入力用②】案件ごと売上（D案件以上）'!$B$4:$Y$1048576,3,FALSE),"-") -> 評価者研修（期末評価） | F73: =IFERROR(VLOOKUP($C73,'【入力用②】案件ごと売上（D案件以上）'!$B$4:$Y$1048576,4,FALSE),"-") -> 48_アートプレスト_評価者研修（期末評価） | G73: =IFERROR(VLOOKUP($C73,'【入力用②】案件ごと売上（D案件以上）'!$B$4:$Y$1048576,5,FALSE),"-") -> 人材育成 | H73: =IFERROR(VLOOKUP($C73,'【入力用②】案件ごと売上（D案件以上）'!$B$4:$Y$1048576,6,FALSE),"-") -> 成立 | I73: =IFERROR(VLOOKUP($C73,'【入力用②】案件ごと売上（D案件以上）'!$B$4:$Y$1048576,8,FALSE),"-") -> 100 | J73: =SUMIF($C$5:$C$1048576,C73,$AM$5:$AM$1048576) -> 100.35 | K73: =IFERROR(I73-J73,"-") -> -0.35 | L73: =IFERROR(VLOOKUP($C73,'【入力用②】案件ごと売上（D案件以上）'!$B$4:$Y$1048576,11,FALSE),"-") -> 1 | M73: =IFERROR(I73/L73,"-") -> 100 | N73: 友祐 | T73: 0.045 | AA73: =IFERROR(VLOOKUP($N73,【管理用】BR_260204!$B$3:$D$20,3,FALSE)*O73,"-") -> 0 | AB73: =IFERROR(VLOOKUP($N73,【管理用】BR_260204!$B$3:$D$20,3,FALSE)*P73,"-") -> 0 | AC73: =IFERROR(VLOOKUP($N73,【管理用】BR_260204!$B$3:$D$20,3,FALSE)*Q73,"-") -> 0 | AD73: =IFERROR(VLOOKUP($N73,【管理用】BR_260204!$B$3:$D$20,3,FALSE)*R73,"-") -> 0 | AE73: =IFERROR(VLOOKUP($N73,【管理用】BR_260204!$B$3:$D$20,3,FALSE)*S73,"-") -> 0 | AF73: =IFERROR(VLOOKUP($N73,【管理用】BR_260204!$B$3:$D$20,3,FALSE)*T73,"-") -> 100.35 | AG73: =IFERROR(VLOOKUP($N73,【管理用】BR_260204!$B$3:$D$20,3,FALSE)*U73,"-") -> 0 | AH73: =IFERROR(VLOOKUP($N73,【管理用】BR_260204!$B$3:$D$20,3,FALSE)*V73,"-") -> 0 | ... AL73: =IFERROR(VLOOKUP($N73,【管理用】BR_260204!$B$3:$D$20,3,FALSE)*Z73,"-") -> 0 | AM73: =SUM(AA73:AL73) -> 100.35 | AN73: *
B74: =ROW(A74)-4 -> 70 | C74: 49 | D74: =IFERROR(VLOOKUP($C74,'【入力用②】案件ごと売上（D案件以上）'!$B$4:$Y$1048576,2,FALSE),"-") -> アートプレスト | E74: =IFERROR(VLOOKUP($C74,'【入力用②】案件ごと売上（D案件以上）'!$B$4:$Y$1048576,3,FALSE),"-") -> 2026年上期人事施策実行支援 | F74: =IFERROR(VLOOKUP($C74,'【入力用②】案件ごと売上（D案件以上）'!$B$4:$Y$1048576,4,FALSE),"-") -> 49_アートプレスト_2026年上期人事施策実行支援 | G74: =IFERROR(VLOOKUP($C74,'【入力用②】案件ごと売上（D案件以上）'!$B$4:$Y$1048576,5,FALSE),"-") -> その他 | H74: =IFERROR(VLOOKUP($C74,'【入力用②】案件ごと売上（D案件以上）'!$B$4:$Y$1048576,6,FALSE),"-") -> D | I74: =IFERROR(VLOOKUP($C74,'【入力用②】案件ごと売上（D案件以上）'!$B$4:$Y$1048576,8,FALSE),"-") -> 25000 | J74: =SUMIF($C$5:$C$1048576,C74,$AM$5:$AM$1048576) -> 24998.3 | K74: =IFERROR(I74-J74,"-") -> 1.7 | L74: =IFERROR(VLOOKUP($C74,'【入力用②】案件ごと売上（D案件以上）'!$B$4:$Y$1048576,11,FALSE),"-") -> 5 | M74: =IFERROR(I74/L74,"-") -> 5000 | N74: 友祐 | V74: 2.242 | W74: 2.242 | X74: 2.242 | Y74: 2.242 | Z74: 2.242 | AA74: =IFERROR(VLOOKUP($N74,【管理用】BR_260204!$B$3:$D$20,3,FALSE)*O74,"-") -> 0 | AB74: =IFERROR(VLOOKUP($N74,【管理用】BR_260204!$B$3:$D$20,3,FALSE)*P74,"-") -> 0 | AC74: =IFERROR(VLOOKUP($N74,【管理用】BR_260204!$B$3:$D$20,3,FALSE)*Q74,"-") -> 0 | AD74: =IFERROR(VLOOKUP($N74,【管理用】BR_260204!$B$3:$D$20,3,FALSE)*R74,"-") -> 0 | AE74: =IFERROR(VLOOKUP($N74,【管理用】BR_260204!$B$3:$D$20,3,FALSE)*S74,"-") -> 0 | AF74: =IFERROR(VLOOKUP($N74,【管理用】BR_260204!$B$3:$D$20,3,FALSE)*T74,"-") -> 0 | AG74: =IFERROR(VLOOKUP($N74,【管理用】BR_260204!$B$3:$D$20,3,FALSE)*U74,"-") -> 0 | AH74: =IFERROR(VLOOKUP($N74,【管理用】BR_260204!$B$3:$D$20,3,FALSE)*V74,"-") -> 4999.66 | ... AL74: =IFERROR(VLOOKUP($N74,【管理用】BR_260204!$B$3:$D$20,3,FALSE)*Z74,"-") -> 4999.66 | AM74: =SUM(AA74:AL74) -> 24998.3 | AN74: *
B75: =ROW(A75)-4 -> 71 | C75: 11 | D75: =IFERROR(VLOOKUP($C75,'【入力用②】案件ごと売上（D案件以上）'!$B$4:$Y$1048576,2,FALSE),"-") -> MSプライマリー | E75: =IFERROR(VLOOKUP($C75,'【入力用②】案件ごと売上（D案件以上）'!$B$4:$Y$1048576,3,FALSE),"-") -> エンゲージメントサーベイ | F75: =IFERROR(VLOOKUP($C75,'【入力用②】案件ごと売上（D案件以上）'!$B$4:$Y$1048576,4,FALSE),"-") -> 11_MSプライマリー_エンゲージメントサーベイ | G75: =IFERROR(VLOOKUP($C75,'【入力用②】案件ごと売上（D案件以上）'!$B$4:$Y$1048576,5,FALSE),"-") -> その他 | H75: =IFERROR(VLOOKUP($C75,'【入力用②】案件ごと売上（D案件以上）'!$B$4:$Y$1048576,6,FALSE),"-") -> A | I75: =IFERROR(VLOOKUP($C75,'【入力用②】案件ごと売上（D案件以上）'!$B$4:$Y$1048576,8,FALSE),"-") -> 7000 | J75: =SUMIF($C$5:$C$1048576,C75,$AM$5:$AM$1048576) -> 6999.6 | K75: =IFERROR(I75-J75,"-") -> 0.4 | L75: =IFERROR(VLOOKUP($C75,'【入力用②】案件ごと売上（D案件以上）'!$B$4:$Y$1048576,11,FALSE),"-") -> 4 | M75: =IFERROR(I75/L75,"-") -> 1750 | N75: 加藤 | R75: 0.05 | AA75: =IFERROR(VLOOKUP($N75,【管理用】BR_260204!$B$3:$D$20,3,FALSE)*O75,"-") -> 0 | AB75: =IFERROR(VLOOKUP($N75,【管理用】BR_260204!$B$3:$D$20,3,FALSE)*P75,"-") -> 0 | AC75: =IFERROR(VLOOKUP($N75,【管理用】BR_260204!$B$3:$D$20,3,FALSE)*Q75,"-") -> 0 | AD75: =IFERROR(VLOOKUP($N75,【管理用】BR_260204!$B$3:$D$20,3,FALSE)*R75,"-") -> 87.5 | AE75: =IFERROR(VLOOKUP($N75,【管理用】BR_260204!$B$3:$D$20,3,FALSE)*S75,"-") -> 0 | AF75: =IFERROR(VLOOKUP($N75,【管理用】BR_260204!$B$3:$D$20,3,FALSE)*T75,"-") -> 0 | AG75: =IFERROR(VLOOKUP($N75,【管理用】BR_260204!$B$3:$D$20,3,FALSE)*U75,"-") -> 0 | AH75: =IFERROR(VLOOKUP($N75,【管理用】BR_260204!$B$3:$D$20,3,FALSE)*V75,"-") -> 0 | ... AL75: =IFERROR(VLOOKUP($N75,【管理用】BR_260204!$B$3:$D$20,3,FALSE)*Z75,"-") -> 0 | AM75: =SUM(AA75:AL75) -> 87.5 | AN75: *
B76: =ROW(A76)-4 -> 72 | C76: 50 | D76: =IFERROR(VLOOKUP($C76,'【入力用②】案件ごと売上（D案件以上）'!$B$4:$Y$1048576,2,FALSE),"-") -> 宮﨑精鋼 | E76: =IFERROR(VLOOKUP($C76,'【入力用②】案件ごと売上（D案件以上）'!$B$4:$Y$1048576,3,FALSE),"-") -> 部課長FB | F76: =IFERROR(VLOOKUP($C76,'【入力用②】案件ごと売上（D案件以上）'!$B$4:$Y$1048576,4,FALSE),"-") -> 50_宮﨑精鋼_部課長FB | G76: =IFERROR(VLOOKUP($C76,'【入力用②】案件ごと売上（D案件以上）'!$B$4:$Y$1048576,5,FALSE),"-") -> HRアナリティクス | H76: =IFERROR(VLOOKUP($C76,'【入力用②】案件ごと売上（D案件以上）'!$B$4:$Y$1048576,6,FALSE),"-") -> 成立 | I76: =IFERROR(VLOOKUP($C76,'【入力用②】案件ごと売上（D案件以上）'!$B$4:$Y$1048576,8,FALSE),"-") -> 100 | J76: =SUMIF($C$5:$C$1048576,C76,$AM$5:$AM$1048576) -> 99 | K76: =IFERROR(I76-J76,"-") -> 1 | L76: =IFERROR(VLOOKUP($C76,'【入力用②】案件ごと売上（D案件以上）'!$B$4:$Y$1048576,11,FALSE),"-") -> 0.5 | M76: =IFERROR(I76/L76,"-") -> 200 | N76: 芹澤 | R76: 0.045 | AA76: =IFERROR(VLOOKUP($N76,【管理用】BR_260204!$B$3:$D$20,3,FALSE)*O76,"-") -> 0 | AB76: =IFERROR(VLOOKUP($N76,【管理用】BR_260204!$B$3:$D$20,3,FALSE)*P76,"-") -> 0 | AC76: =IFERROR(VLOOKUP($N76,【管理用】BR_260204!$B$3:$D$20,3,FALSE)*Q76,"-") -> 0 | AD76: =IFERROR(VLOOKUP($N76,【管理用】BR_260204!$B$3:$D$20,3,FALSE)*R76,"-") -> 99 | AE76: =IFERROR(VLOOKUP($N76,【管理用】BR_260204!$B$3:$D$20,3,FALSE)*S76,"-") -> 0 | AF76: =IFERROR(VLOOKUP($N76,【管理用】BR_260204!$B$3:$D$20,3,FALSE)*T76,"-") -> 0 | AG76: =IFERROR(VLOOKUP($N76,【管理用】BR_260204!$B$3:$D$20,3,FALSE)*U76,"-") -> 0 | AH76: =IFERROR(VLOOKUP($N76,【管理用】BR_260204!$B$3:$D$20,3,FALSE)*V76,"-") -> 0 | ... AL76: =IFERROR(VLOOKUP($N76,【管理用】BR_260204!$B$3:$D$20,3,FALSE)*Z76,"-") -> 0 | AM76: =SUM(AA76:AL76) -> 99 | AN76: *
B77: =ROW(A77)-4 -> 73 | C77: 53 | D77: =IFERROR(VLOOKUP($C77,'【入力用②】案件ごと売上（D案件以上）'!$B$4:$Y$1048576,2,FALSE),"-") -> YAMAGATA | E77: =IFERROR(VLOOKUP($C77,'【入力用②】案件ごと売上（D案件以上）'!$B$4:$Y$1048576,3,FALSE),"-") -> S1および制作部門変革支援（フェーズ4） | F77: =IFERROR(VLOOKUP($C77,'【入力用②】案件ごと売上（D案件以上）'!$B$4:$Y$1048576,4,FALSE),"-") -> 053_YAMAGATA_S1および制作部門変革支援（フェーズ4） | G77: =IFERROR(VLOOKUP($C77,'【入力用②】案件ごと売上（D案件以上）'!$B$4:$Y$1048576,5,FALSE),"-") -> その他 | H77: =IFERROR(VLOOKUP($C77,'【入力用②】案件ごと売上（D案件以上）'!$B$4:$Y$1048576,6,FALSE),"-") -> 成立 | I77: =IFERROR(VLOOKUP($C77,'【入力用②】案件ごと売上（D案件以上）'!$B$4:$Y$1048576,8,FALSE),"-") -> 33000 | J77: =SUMIF($C$5:$C$1048576,C77,$AM$5:$AM$1048576) -> 29477.6 | K77: =IFERROR(I77-J77,"-") -> 3522.4 | L77: =IFERROR(VLOOKUP($C77,'【入力用②】案件ごと売上（D案件以上）'!$B$4:$Y$1048576,11,FALSE),"-") -> 6 | M77: =IFERROR(I77/L77,"-") -> 5500 | N77: 波多野 | S77: 0.06 | T77: 0.2 | U77: 0.2 | V77: 0.2 | W77: 0.2 | X77: 0.2 | Y77: 0.2 | AA77: =IFERROR(VLOOKUP($N77,【管理用】BR_260204!$B$3:$D$20,3,FALSE)*O77,"-") -> 0 | AB77: =IFERROR(VLOOKUP($N77,【管理用】BR_260204!$B$3:$D$20,3,FALSE)*P77,"-") -> 0 | AC77: =IFERROR(VLOOKUP($N77,【管理用】BR_260204!$B$3:$D$20,3,FALSE)*Q77,"-") -> 0 | AD77: =IFERROR(VLOOKUP($N77,【管理用】BR_260204!$B$3:$D$20,3,FALSE)*R77,"-") -> 0 | AE77: =IFERROR(VLOOKUP($N77,【管理用】BR_260204!$B$3:$D$20,3,FALSE)*S77,"-") -> 510 | AF77: =IFERROR(VLOOKUP($N77,【管理用】BR_260204!$B$3:$D$20,3,FALSE)*T77,"-") -> 1700 | AG77: =IFERROR(VLOOKUP($N77,【管理用】BR_260204!$B$3:$D$20,3,FALSE)*U77,"-") -> 1700 | AH77: =IFERROR(VLOOKUP($N77,【管理用】BR_260204!$B$3:$D$20,3,FALSE)*V77,"-") -> 1700 | ... AL77: =IFERROR(VLOOKUP($N77,【管理用】BR_260204!$B$3:$D$20,3,FALSE)*Z77,"-") -> 0 | AM77: =SUM(AA77:AL77) -> 10710 | AN77: *
B78: =ROW(A78)-4 -> 74 | C78: 53 | D78: =IFERROR(VLOOKUP($C78,'【入力用②】案件ごと売上（D案件以上）'!$B$4:$Y$1048576,2,FALSE),"-") -> YAMAGATA | E78: =IFERROR(VLOOKUP($C78,'【入力用②】案件ごと売上（D案件以上）'!$B$4:$Y$1048576,3,FALSE),"-") -> S1および制作部門変革支援（フェーズ4） | F78: =IFERROR(VLOOKUP($C78,'【入力用②】案件ごと売上（D案件以上）'!$B$4:$Y$1048576,4,FALSE),"-") -> 053_YAMAGATA_S1および制作部門変革支援（フェーズ4） | G78: =IFERROR(VLOOKUP($C78,'【入力用②】案件ごと売上（D案件以上）'!$B$4:$Y$1048576,5,FALSE),"-") -> その他 | H78: =IFERROR(VLOOKUP($C78,'【入力用②】案件ごと売上（D案件以上）'!$B$4:$Y$1048576,6,FALSE),"-") -> 成立 | I78: =IFERROR(VLOOKUP($C78,'【入力用②】案件ごと売上（D案件以上）'!$B$4:$Y$1048576,8,FALSE),"-") -> 33000 | J78: =SUMIF($C$5:$C$1048576,C78,$AM$5:$AM$1048576) -> 29477.6 | K78: =IFERROR(I78-J78,"-") -> 3522.4 | L78: =IFERROR(VLOOKUP($C78,'【入力用②】案件ごと売上（D案件以上）'!$B$4:$Y$1048576,11,FALSE),"-") -> 6 | M78: =IFERROR(I78/L78,"-") -> 5500 | N78: 丸田 | S78: 0.12 | T78: 0.4 | U78: 0.4 | V78: 0.4 | W78: 0.4 | X78: 0.4 | Y78: 0.4 | AA78: =IFERROR(VLOOKUP($N78,【管理用】BR_260204!$B$3:$D$20,3,FALSE)*O78,"-") -> 0 | AB78: =IFERROR(VLOOKUP($N78,【管理用】BR_260204!$B$3:$D$20,3,FALSE)*P78,"-") -> 0 | AC78: =IFERROR(VLOOKUP($N78,【管理用】BR_260204!$B$3:$D$20,3,FALSE)*Q78,"-") -> 0 | AD78: =IFERROR(VLOOKUP($N78,【管理用】BR_260204!$B$3:$D$20,3,FALSE)*R78,"-") -> 0 | AE78: =IFERROR(VLOOKUP($N78,【管理用】BR_260204!$B$3:$D$20,3,FALSE)*S78,"-") -> 225.6 | AF78: =IFERROR(VLOOKUP($N78,【管理用】BR_260204!$B$3:$D$20,3,FALSE)*T78,"-") -> 752 | AG78: =IFERROR(VLOOKUP($N78,【管理用】BR_260204!$B$3:$D$20,3,FALSE)*U78,"-") -> 752 | AH78: =IFERROR(VLOOKUP($N78,【管理用】BR_260204!$B$3:$D$20,3,FALSE)*V78,"-") -> 752 | ... AL78: =IFERROR(VLOOKUP($N78,【管理用】BR_260204!$B$3:$D$20,3,FALSE)*Z78,"-") -> 0 | AM78: =SUM(AA78:AL78) -> 4737.6 | AN78: *
B79: =ROW(A79)-4 -> 75 | C79: 53 | D79: =IFERROR(VLOOKUP($C79,'【入力用②】案件ごと売上（D案件以上）'!$B$4:$Y$1048576,2,FALSE),"-") -> YAMAGATA | E79: =IFERROR(VLOOKUP($C79,'【入力用②】案件ごと売上（D案件以上）'!$B$4:$Y$1048576,3,FALSE),"-") -> S1および制作部門変革支援（フェーズ4） | F79: =IFERROR(VLOOKUP($C79,'【入力用②】案件ごと売上（D案件以上）'!$B$4:$Y$1048576,4,FALSE),"-") -> 053_YAMAGATA_S1および制作部門変革支援（フェーズ4） | G79: =IFERROR(VLOOKUP($C79,'【入力用②】案件ごと売上（D案件以上）'!$B$4:$Y$1048576,5,FALSE),"-") -> その他 | H79: =IFERROR(VLOOKUP($C79,'【入力用②】案件ごと売上（D案件以上）'!$B$4:$Y$1048576,6,FALSE),"-") -> 成立 | I79: =IFERROR(VLOOKUP($C79,'【入力用②】案件ごと売上（D案件以上）'!$B$4:$Y$1048576,8,FALSE),"-") -> 33000 | J79: =SUMIF($C$5:$C$1048576,C79,$AM$5:$AM$1048576) -> 29477.6 | K79: =IFERROR(I79-J79,"-") -> 3522.4 | L79: =IFERROR(VLOOKUP($C79,'【入力用②】案件ごと売上（D案件以上）'!$B$4:$Y$1048576,11,FALSE),"-") -> 6 | M79: =IFERROR(I79/L79,"-") -> 5500 | N79: 加藤 | S79: 0.12 | T79: 0.4 | U79: 0.4 | V79: 0.4 | W79: 0.4 | X79: 0.4 | Y79: 0.4 | AA79: =IFERROR(VLOOKUP($N79,【管理用】BR_260204!$B$3:$D$20,3,FALSE)*O79,"-") -> 0 | AB79: =IFERROR(VLOOKUP($N79,【管理用】BR_260204!$B$3:$D$20,3,FALSE)*P79,"-") -> 0 | AC79: =IFERROR(VLOOKUP($N79,【管理用】BR_260204!$B$3:$D$20,3,FALSE)*Q79,"-") -> 0 | AD79: =IFERROR(VLOOKUP($N79,【管理用】BR_260204!$B$3:$D$20,3,FALSE)*R79,"-") -> 0 | AE79: =IFERROR(VLOOKUP($N79,【管理用】BR_260204!$B$3:$D$20,3,FALSE)*S79,"-") -> 210 | AF79: =IFERROR(VLOOKUP($N79,【管理用】BR_260204!$B$3:$D$20,3,FALSE)*T79,"-") -> 700 | AG79: =IFERROR(VLOOKUP($N79,【管理用】BR_260204!$B$3:$D$20,3,FALSE)*U79,"-") -> 700 | AH79: =IFERROR(VLOOKUP($N79,【管理用】BR_260204!$B$3:$D$20,3,FALSE)*V79,"-") -> 700 | ... AL79: =IFERROR(VLOOKUP($N79,【管理用】BR_260204!$B$3:$D$20,3,FALSE)*Z79,"-") -> 0 | AM79: =SUM(AA79:AL79) -> 4410 | AN79: *
B80: =ROW(A80)-4 -> 76 | C80: 53 | D80: =IFERROR(VLOOKUP($C80,'【入力用②】案件ごと売上（D案件以上）'!$B$4:$Y$1048576,2,FALSE),"-") -> YAMAGATA | E80: =IFERROR(VLOOKUP($C80,'【入力用②】案件ごと売上（D案件以上）'!$B$4:$Y$1048576,3,FALSE),"-") -> S1および制作部門変革支援（フェーズ4） | G80: =IFERROR(VLOOKUP($C80,'【入力用②】案件ごと売上（D案件以上）'!$B$4:$Y$1048576,5,FALSE),"-") -> その他 | H80: =IFERROR(VLOOKUP($C80,'【入力用②】案件ごと売上（D案件以上）'!$B$4:$Y$1048576,6,FALSE),"-") -> 成立 | I80: =IFERROR(VLOOKUP($C80,'【入力用②】案件ごと売上（D案件以上）'!$B$4:$Y$1048576,8,FALSE),"-") -> 33000 | J80: =SUMIF($C$5:$C$1048576,C80,$AM$5:$AM$1048576) -> 29477.6 | K80: =IFERROR(I80-J80,"-") -> 3522.4 | L80: =IFERROR(VLOOKUP($C80,'【入力用②】案件ごと売上（D案件以上）'!$B$4:$Y$1048576,11,FALSE),"-") -> 6 | M80: =IFERROR(I80/L80,"-") -> 5500 | N80: 外部 | S80: 0.36 | T80: 1.21 | U80: 1.61 | V80: 1.61 | W80: 1.61 | X80: 1.61 | Y80: 1.61 | AA80: =IFERROR(VLOOKUP($N80,【管理用】BR_260204!$B$3:$D$20,3,FALSE)*O80,"-") -> 0 | AB80: =IFERROR(VLOOKUP($N80,【管理用】BR_260204!$B$3:$D$20,3,FALSE)*P80,"-") -> 0 | AC80: =IFERROR(VLOOKUP($N80,【管理用】BR_260204!$B$3:$D$20,3,FALSE)*Q80,"-") -> 0 | AD80: =IFERROR(VLOOKUP($N80,【管理用】BR_260204!$B$3:$D$20,3,FALSE)*R80,"-") -> 0 | AE80: =IFERROR(VLOOKUP($N80,【管理用】BR_260204!$B$3:$D$20,3,FALSE)*S80,"-") -> 360 | AF80: =IFERROR(VLOOKUP($N80,【管理用】BR_260204!$B$3:$D$20,3,FALSE)*T80,"-") -> 1210 | AG80: =IFERROR(VLOOKUP($N80,【管理用】BR_260204!$B$3:$D$20,3,FALSE)*U80,"-") -> 1610 | AH80: =IFERROR(VLOOKUP($N80,【管理用】BR_260204!$B$3:$D$20,3,FALSE)*V80,"-") -> 1610 | ... AL80: =IFERROR(VLOOKUP($N80,【管理用】BR_260204!$B$3:$D$20,3,FALSE)*Z80,"-") -> 0 | AM80: =SUM(AA80:AL80) -> 9620 | AN80: *
B81: =ROW(A81)-4 -> 77 | C81: 55 | D81: =IFERROR(VLOOKUP($C81,'【入力用②】案件ごと売上（D案件以上）'!$B$4:$Y$1048576,2,FALSE),"-") -> OKI | E81: =IFERROR(VLOOKUP($C81,'【入力用②】案件ごと売上（D案件以上）'!$B$4:$Y$1048576,3,FALSE),"-") -> 採用＆オンボーディング支援_Ph.1基礎調査 | F81: =IFERROR(VLOOKUP($C81,'【入力用②】案件ごと売上（D案件以上）'!$B$4:$Y$1048576,4,FALSE),"-") -> 55_OKI_採用＆オンボーディング支援_Ph.1基礎調査 | G81: =IFERROR(VLOOKUP($C81,'【入力用②】案件ごと売上（D案件以上）'!$B$4:$Y$1048576,5,FALSE),"-") -> その他 | H81: =IFERROR(VLOOKUP($C81,'【入力用②】案件ごと売上（D案件以上）'!$B$4:$Y$1048576,6,FALSE),"-") -> B | I81: =IFERROR(VLOOKUP($C81,'【入力用②】案件ごと売上（D案件以上）'!$B$4:$Y$1048576,8,FALSE),"-") -> 2000 | J81: =SUMIF($C$5:$C$1048576,C81,$AM$5:$AM$1048576) -> 1565 | K81: =IFERROR(I81-J81,"-") -> 435 | L81: =IFERROR(VLOOKUP($C81,'【入力用②】案件ごと売上（D案件以上）'!$B$4:$Y$1048576,11,FALSE),"-") -> 1 | M81: =IFERROR(I81/L81,"-") -> 2000 | N81: 波多野 | V81: 0.05 | AA81: =IFERROR(VLOOKUP($N81,【管理用】BR_260204!$B$3:$D$20,3,FALSE)*O81,"-") -> 0 | AB81: =IFERROR(VLOOKUP($N81,【管理用】BR_260204!$B$3:$D$20,3,FALSE)*P81,"-") -> 0 | AC81: =IFERROR(VLOOKUP($N81,【管理用】BR_260204!$B$3:$D$20,3,FALSE)*Q81,"-") -> 0 | AD81: =IFERROR(VLOOKUP($N81,【管理用】BR_260204!$B$3:$D$20,3,FALSE)*R81,"-") -> 0 | AE81: =IFERROR(VLOOKUP($N81,【管理用】BR_260204!$B$3:$D$20,3,FALSE)*S81,"-") -> 0 | AF81: =IFERROR(VLOOKUP($N81,【管理用】BR_260204!$B$3:$D$20,3,FALSE)*T81,"-") -> 0 | AG81: =IFERROR(VLOOKUP($N81,【管理用】BR_260204!$B$3:$D$20,3,FALSE)*U81,"-") -> 0 | AH81: =IFERROR(VLOOKUP($N81,【管理用】BR_260204!$B$3:$D$20,3,FALSE)*V81,"-") -> 425 | ... AL81: =IFERROR(VLOOKUP($N81,【管理用】BR_260204!$B$3:$D$20,3,FALSE)*Z81,"-") -> 0 | AM81: =SUM(AA81:AL81) -> 425 | AN81: *
